Workbook
Name \a: #REF!
Name \a: #REF!
Name \a: #REF!
Name \a: #REF!
Name \a: #REF!
Name \C: #REF!
Name \C: #REF!
Name \C: #REF!
Name \C: #REF!
Name \C: #REF!
Name \d: #REF!
Name \d: #REF!
Name \d: #REF!
Name \d: #REF!
Name \d: #REF!
Name \L: #REF!
Name \L: #REF!
Name \L: #REF!
Name \L: #REF!
Name \L: #REF!
Name \p: #REF!
Name \p: #REF!
Name \p: #REF!
Name \p: #REF!
Name \p: #REF!
Name \s: #REF!
Name \s: #REF!
Name \s: #REF!
Name \s: #REF!
Name \s: #REF!
Name \z: #REF!
Name \z: #REF!
Name \z: #REF!
Name \z: #REF!
Name \z: #REF!
Name _.dbf: #REF!
Name _.dbf: #REF!
Name _.dbf: #REF!
Name _.dbf: #REF!
Name _.dbf: #REF!
Name _?: #REF!
Name _?: #REF!
Name _?: #REF!
Name _?: #REF!
Name _?: #REF!
Name _??????: #REF!
Name _??????: #REF!
Name _??????: #REF!
Name _??????: #REF!
Name _??????: #REF!
Name __?: #REF!
Name __?: #REF!
Name __?: #REF!
Name __?: #REF!
Name __?: #REF!
Name __??????: #REF!
Name __??????: #REF!
Name __??????: #REF!
Name __??????: #REF!
Name __??????: #REF!

Sheet args
A1: {'TemplateId':'$TemplateId$'}
A2: {'TableCode':'GZD','TableName':'T00','ColumnCounts':'7','ColumnNames':'A;B;C;D;E;F;G;'}
A3: {'TableCode':'ZZ','TableName':'T01','ColumnCounts':'10','ColumnNames':'A;B;C;D;E;F;G;H;I;J'}
A4: {'TableCode':'XMJCXX','TableName':'T02','ColumnCounts':'87','ColumnNames':'A;B;C;D;E;F;G;H;I;J;K;L;M;N;O;P;Q;R;S;T;U;V;W;X;Y;Z;AA;AB;AC;AD;AE;AF;AG;AH;AI;AJ;AK;AL;AM;AN;AO;AP;AQ;AR;AS;AT;AU;AV;AW;AX;AY;AZ;BA;BB;BC;BD;BE;BF;BG;BH;BI;BJ;BK;BL;BM;BN;BO;BP;BQ;BR;BS;BT;BU;BV;BW;BX;BY;BZ;CA;CB;CC;CD;CE;CF;CG;CH;CI;CJ'}
A5: {'TableCode':'CBCS','TableName':'T03','ColumnCounts':'11','ColumnNames':'A;B;C;D;E;F;G;H;I;J;K'}
A6: {'TableCode':'MBCBKZ','TableName':'T04','ColumnCounts':'30','ColumnNames':'A;B;C;D;E;F;G;H;I;J;K;L;M;N;O;P;Q;R;S;T;U;V;W;X;Y;Z;AA;AB;AC;AD'}
A7: {'TableCode':'CBCSMX','TableName':'T05','ColumnCounts':'21','ColumnNames':'A;B;C;D;E;F;G;H;I;J;K;L;M;N;O;P;Q;R;S;T;U'}
A8: {'TableCode':'FXHBB','TableName':'T06','ColumnCounts':'12','ColumnNames':'A;B;C;D;E;F;G;H;I;J;K;L'}
A9: {'TableCode':'DSJCD','TableName':'T07','ColumnCounts':'236','ColumnNames':'COLA;COLB;COLC;COLD;COLE;COLF;COLG;COLH;COLI;COLJ;COLK;COLL;COLM;COLN;COLO;COLP;COLQ;COLR;COLS;COLT;COLU;COLV;COLW;COLX;COLY;COLZ;COLAA;COLAB;COLAC;COLAD;COLAE;COLAF;COLAG;COLAH;COLAI;COLAJ;COLAK;COLAL;COLAM;COLAN;COLAO;COLAP;COLAQ;COLAR;COLAS;COLAT;COLAU;COLAV;COLAW;COLAX;COLAY;COLAZ;COLBA;COLBB;COLBC;COLBD;COLBE;COLBF;COLBG;COLBH;COLBI;COLBJ;COLBK;COLBL;COLBM;COLBN;COLBO;COLBP;COLBQ;COLBR;COLBS;COLBT;COLBU;COLBV;COLBW;COLBX;COLBY;COLBZ;COLCA;COLCB;COLCC;COLCD;COLCE;COLCF;COLCG;COLCH;COLCI;COLCJ;COLCK;COLCL;COLCM;COLCN;COLCO;COLCP;COLCQ;COLCR;COLCS;COLCT;COLCU;COLCV;COLCW;COLCX;COLCY;COLCZ;COLDA;COLDB;COLDC;COL$pcode1$01;COL$pcode1$02;COL$pcode1$03;COL$pcode1$04;COL$pcode1$05;COL$pcode1$06;COL$pcode1$07;COL$pcode1$08;COL$pcode1$09;COL$pcode1$10;COL$pcode1$11;COL$pcode1$12;COL$pcode1$13;COL$pcode1$14;COL$pcode1$15;COL$pcode1$16;COL$pcode2$01;COL$pcode2$02;COL$pcode2$03;COL$pcode2$04;COL$pcode2$05;COL$pcode2$06;COL$pcode2$07;COL$pcode2$08;COL$pcode2$09;COL$pcode2$10;COL$pcode2$11;COL$pcode2$12;COL$pcode2$13;COL$pcode2$14;COL$pcode2$15;COL$pcode2$16;COL$pcode3$01;COL$pcode3$02;COL$pcode3$03;COL$pcode3$04;COL$pcode3$05;COL$pcode3$06;COL$pcode3$07;COL$pcode3$08;COL$pcode3$09;COL$pcode3$10;COL$pcode3$11;COL$pcode3$12;COL$pcode3$13;COL$pcode3$14;COL$pcode3$15;COL$pcode3$16;COL$pcode4$01;COL$pcode4$02;COL$pcode4$03;COL$pcode4$04;COL$pcode4$05;COL$pcode4$06;COL$pcode4$07;COL$pcode4$08;COL$pcode4$09;COL$pcode4$10;COL$pcode4$11;COL$pcode4$12;COL$pcode4$13;COL$pcode4$14;COL$pcode4$15;COL$pcode4$16;COL$pcode5$01;COL$pcode5$02;COL$pcode5$03;COL$pcode5$04;COL$pcode5$05;COL$pcode5$06;COL$pcode5$07;COL$pcode5$08;COL$pcode5$09;COL$pcode5$10;COL$pcode5$11;COL$pcode5$12;COL$pcode5$13;COL$pcode5$14;COL$pcode5$15;COL$pcode5$16;COL$pcode6$01;COL$pcode6$02;COL$pcode6$03;COL$pcode6$04;COL$pcode6$05;COL$pcode6$06;COL$pcode6$07;COL$pcode6$08;COL$pcode6$09;COL$pcode6$10;COL$pcode6$11;COL$pcode6$12;COL$pcode6$13;COL$pcode6$14;COL$pcode6$15;COL$pcode6$16;COLGV;COLGW;COLGX;COLGY;COLGZ;COLHA;COLHB;COLHC;COLHD;COLHE;COLHF;COLHG;COLHH;COLHI;COLHJ;COLHK;COLHL;COLHM;COLHN;COLHO;COLHP;COLHQ;COLHR;COLHS;COLHT;COLHU;COLHV;COLHW;COLHX;COLHY;COLHZ;COLIA;COLIB'}
A10: {'TableCode':'SFXHBB','TableName':'T08','ColumnCounts':'12','ColumnNames':'A;B;C;D;E;F;G;H;I;J;K;L'}
A11: {'TableCode':'DSJCDSY','TableName':'T09','ColumnCounts':'3','ColumnNames':'A;B;C;D'}

Sheet 00 成本测算关注点
A1: 苏州公司园区永旺北地块项目信息及特性交圈输入表
A2: 2022年4月版
A3: 本表随投资会成本测算资料同步提交，涉及影响成本的部分各职能线下交圈，由合约管理部填写，填写说明： ① 地块特征根据项目情况填写。 ② 风险描述：根据项目实际特性简要说明；如不涉及或无异常，可描述为“是”“否”“与以往一致”等。 ③ 落实措施：主要包括资料提供/数据交圈/指导意见，定性填写，描述大概金额，无需填写具体测算指标（测算指标在成本测算中体现即可）。如已有应对措施且风险可控，风险项选“否”；如风险较大不确定性或缺乏相应落实措施，风险项选“是”。 ④风险项：信息交圈责任部门为各协同职能部门，如有个别风险项难以确定，应征询协同部门意见。城市特征值征询投资、报建与设计意见。
A4: 序号 | B4: 协同职能 | C4: 事项 | D4: 事项特性 | E4: 是否涉及 | F4: 内容描述 | G4: 测算考虑
A5: 一、 | B5: 城市特征 | C5: 城市层级的通用政策，如政策、规范等与本年度城市特征值一致则无需额外修正
A6: =MAX(A$5:A5)+1 -> 1 | B6: 投资 | C6: 产业政策 | D6: 装配式政策 | E6: 与以往一致 | G6: 标准刻度：预制装配式面积____%，单体预制率____%，预制装配率____%
A7: =MAX(A$5:A6)+1 -> 2 | D7: 钢结构政策 | E7: 与以往一致 | G7: 标准刻度：XXXXXXXX
A8: =MAX(A$5:A7)+1 -> 3 | D8: 超低能耗政策 | E8: 与以往一致 | G8: 标准刻度：XXXXXXXX
A9: =MAX(A$5:A8)+1 -> 4 | D9: 绿色建筑政策 | E9: 与以往一致 | G9: 标准刻度：___星
A10: =MAX(A$5:A9)+1 -> 5 | D10: 全装修政策 | E10: 与以往一致 | G10: 基础装：成本XXX元/m2，售价XXXX元/m2，溢价率XXX% 升级装：成本XXXX元/m2，售价XXXX元/m2，溢价率XXX%
A11: =MAX(A$5:A10)+1 -> 6 | D11: 海绵城市 | E11: 与以往一致 | G11: 标准刻度：XXXXXXXX
A12: =MAX(A$5:A11)+1 -> 7 | D12: …
A13: =MAX(A$5:A12)+1 -> 8 | B13: 设计 | C13: 建筑规范 | D13: 常规配建面积规则 | E13: 与以往一致 | F13: 例：A社区用房：60m2每百户（含20m2每百户居家养老用房）；B物业经营：地上4‰；C物业办公：地上3‰；D公变：个数-（住宅面积*80/1000+商业面积*150/1000+办公面积*100/1000）/（800*4）；面积：160m2/个（20*8）；E专变：常规住宅1个，商业1个，面积160m2/个；F环网站：60m2/个；G电视机房：每500户15m2；H通信机房：70m2；I消控室：住宅和商业（集中商业（总建面9万m2）消控室面积约150m2）及办公均需单独设置消控室，常规60m2/个；J水泵房：规范查表
A14: =MAX(A$5:A13)+1 -> 9 | D14: 配建设施下地政策 | E14: 与以往一致
A15: =MAX(A$5:A14)+1 -> 10 | D15: 常规赠送率 | E15: 与以往一致 | F15: 阳台、飘窗、设备阳台、地下夹层、庭院
A16: =MAX(A$5:A15)+1 -> 11 | D16: 人防建设标准 | E16: 与以往一致 | F16: 新建民用住宅应修建人防比例10%，新建其他民用建筑应修建人防比例7% | G16: 是否异地建设，人防等级XXX, 单方增加___元/m2
A17: =MAX(A$5:A16)+1 -> 12 | D17: 车位配比 | E17: 与以往一致 | F17: 规范对车位个数的设置要求描述：按地上住宅建筑面积1.05个/100平方，非住宅为1.02个/100平方，商业为1.0个/100平方
A18: =MAX(A$5:A17)+1 -> 13 | D18: 常规地上车位占比 | E18: 与以往一致 | F18: 规范要求：不超过住宅户数的15%，不小于总车位的3% | G18: 户数的10%
A19: =MAX(A$5:A18)+1 -> 14 | D19: 充电设施 | E19: 与以往一致 | F19: 设备安装配比：_________ 预留容量和电线电缆：_________ | G19: 测算单方______元/m2
A20: =MAX(A$5:A19)+1 -> 15 | D20: 机械车位设置要求 | E20: 与以往一致
A21: =MAX(A$5:A20)+1 -> 16 | D21: 覆土深度要求 | E21: 与以往一致 | G21: 覆土深度：______m
A22: =MAX(A$5:A21)+1 -> 17 | D22: 消防配置要求 | E22: 与以往一致 | F22: 担架梯
A23: =MAX(A$5:A22)+1 -> 18 | D23: 节能配置要求 | E23: 与以往一致 | F23: 太阳能，空气能，常规保温，门窗要求
A24: 一、 | B24: 地块特征 | C24: 地块特殊信息
A25: 1 | B25: 投资 | C25: 出让条件 | D25: 品质政策 | E25: 否
A26: 2 | D26: 公建化立面政策 | E26: 是 | F26: 外立面材料至少为铝板
A27: 3 | D27: 未来社区要求 | E27: 否
A28: 4 | D28: 泛光照明要求 | E28: 是 | G28: 按照刻度计算
A29: 5 | D29: 配建要求 | E29: 否 | F29: 无
A30: 6 | D30: 文保建筑 | E30: 否 | F30: 无 | G30: 文物保护面积_________，测算单方_______元/m2
A31: 7 | D31: 地上拆迁 | E31: 否 | F31: 无 | G31: 场内建筑____m2 信号基站____处 公交站台____m2 高压电线____m
A32: 8 | D32: 地下拆迁 | E32: 否 | F32: 无 | G32: 地下管线：__________ 地下清障：__________
A33: 9 | D33: 地下通道/人行天桥联通要求 | E33: 否 | F33: 无 | G33: 地下连通道面积_______，测算单方_______元/m2 人行天桥面积_______，测算单方_______元/m2
A34: 10 | D34: ……
A35: 11 | C35: 地质地形及土壤条件 | D35: 场地自身高差 | E35: 否 | F35: 无 | G35: 场地高差，高差米数_____m 坡地建筑，测算单方____元/m2 挡土墙设置，测算____元/延米 室外电梯，测算____元/台，共____台
A36: 12 | D36: 场地表土/高堆土/场地平整 | E36: 否 | F36: 无 | G36: 场地堆土，堆土方量______m3
A37: 13 | D37: 土壤污染 | E37: 否 | F37: 无 | G37: 土壤治理：________
A38: 14 | D38: 不良地质/软弱地基/地下水位 | E38: 否 | F38: 无
A39: 15 | D39: 场地内淤泥 | E39: 否 | F39: 无 | G39: 淤泥面积________m2，深度______m
A40: 16 | D40: 场地内河道 | E40: 否 | F40: 无 | G40: 河道面积________m2，是/否涉及改道
A41: 17 | D41: 场地内植被 | E41: 否 | F41: 无 | G41: 灌木面积_________m2，乔木数量_________棵
A42: 18 | D42: 地质勘察 | E42: 否 | G42: 石方爆破及引孔：_________ 地下软弱土层 ：_________ 其他：_________
A43: 19 | D43: 多个子地块 | E43: 否 | F43: 无 | G43: 景观测算影响：_________ 支护测算影响：_________ 配电房设置影响：__________
A44: 20 | C44: 周边四至及周边配套 | D44: 规划道路与场地高差 | E44: 否 | F44: 无 | G44: 场地与道路高差，高差米数_____m
A45: 21 | D45: 周边道路交通情况 | E45: 否 | F45: 南侧：__道路__ 北侧：__河道______ 东侧：__河道________ 西侧：__市政道路________ | G45: 临时道路____m2 红线外租地____m2 ，时间____月
A46: 22 | D46: 红线外不利因素 | E46: 否 | F46: 无 | G46: 降噪、遮挡、工期、民扰等
A47: 23 | D47: 临近地铁建设 | E47: 是 | F47: 临近一号线，在地铁影响线范围 | G47: 轨交接驳费用：_________ 轨交支护采用________形式 轨道检测费用：_________
A48: 24 | C48: 当地 常规做法 | D48: 阳台封闭要求 | E48: 是 | F48: 全封闭 | G48: 防火栏板+封窗
A49: 25 | D49: …… | E49: 否
A50: 26 | C50: 预售条件 | D50: 预售条件 | E50: 是 | F50: 正负零预售 封顶预售 其他：_____1/5 结构预售________
A51: 27 | C51: 交付条件 | D51: 验收条件、交付条件 | E51: 是 | F51: 精装验收，精装交付；别墅毛坯
A52: 28 | C52: 所在区位政府特殊要求 | D52: 如有，简述事项及风险 | E52: 否
A53: 29 | C53: 其他影响成本的土地条件 | D53: 如有，简述事项及风险 | E53: 是
A54: 30 | B54: 营销 | C54: 档次定位 | D54: 商业档次定位 | E54: 否
A55: 31 | D55: 住宅档次定位 | E55: 是 | F55: U3+
A56: 32 | D56: 参考项目（自开发） | E56: 否
A57: 33 | D57: 参考项目（友商开发） | E57: 否
A58: 34 | C58: 客户敏感点 | D58: 单体弹性配置敏感点 | E58: 是 | F58: 外立面，公区装修
A59: 35 | D59: 精装修配置敏感点 | E59: 是 | G59: 详见测算表
A60: 36 | D60: 景观配置敏感点 | E60: 是 | F60: 大门、风雨连廊
A61: 37 | C61: 限价情况 | D61: 是否存在限价情况 | E61: 否 | F61: 限价金额：__________
A62: 38 | D62: 精装可否突破限价 | E62: 否
A63: 39 | C63: 车位配比 | D63: 规范要求/实际车位配比 | E63: 是
A64: 40 | D64: 车位盈亏平衡点 | E64: 否
A65: 41 | D65: 地上车位 | E65: 否
A66: 42 | C66: 卖场配置 | D66: 卖场面积/装修标准/展示区园林标准 | E66: 是
A67: 43 | C67: 户型特性 | D67: 户型面积段 | E67: 是 | F67: 商品住宅 248/285；别墅 300-500 | G67: /
A68: 44 | D68: 特殊户型：LOFT、公寓 | E68: 否 | G68: /
A69: 45 | C69: 赠送方案 | D69: 超常规赠送 | E69: 是 | F69: 屋顶：____屋面闷顶______ 庭院：__________ 地下空间：__________ | G69: /
A70: 46 | D70: 赠送面积溢价 | E70: 是 | F70: 顶层不折价 | G70: /
A71: 47 | D71: 户内后改造 | E71: 是 | F71: 阳台改造
A72: 48 | C72: 工销房 | D72: 是否存在工销房 | E72: 否 | G72: 总包合同总额_________，工抵房金额________，报价影响________
A73: 49 | C73: 其他 | D73: 如有，简述事项及风险 | E73: 否 | F73: 不涉及 | G73: /
A74: 50 | B74: 设计 | C74: 地下 | D74: 柱网尺寸 | E74: 是 | F74: 小柱网：______m*______m 中柱网：___8.1___m*__5.6___m 大柱网：______m*______m
A75: 51 | D75: 地下室赠送率（地下赠送面积/地下室面积） | E75: 否
A76: 52 | D76: 地下夹层 | E76: 否 | F76: 地下夹层面积_________
A77: 53 | D77: 地下空腔 | E77: 否 | F77: 地下空腔面积_________
A78: 54 | C78: 地上 | D78: 城市会客厅 | E78: 否 | F78: 避难层面积_________ | G78: 城市会客厅功能： 活动空间____%，硬装____元/m2，软装____元/m2 展示空间____%，硬装____元/m2，软装____元/m2
A79: 55 | D79: 架空层 | E79: 是 | F79: 架空层面积____3248_____（同时计建面和室外面积） | G79: 架空层功能： 非机动车停车____%，硬装____元/m2 活动空间__70__%，硬装__4000__元/m2，软装____元/m2 展示空间__30__%，硬装__2500__元/m2，软装____元/m2
A80: 56 | D80: 避难层 | E80: 否 | F80: 避难层面积_________ | G80: 避难层功能： 活动空间____%，硬装____元/m2，软装____元/m2 展示空间____%，硬装____元/m2，软装____元/m2
A81: 57 | D81: 同层排水 | E81: 是 | G81: 不降板同层排水 微降板同层排水，降板高度要求___150_______ 其他___________
A82: 58 | D82: 屋顶构架 | E82: 否 | G82: 屋面构架，测算造价____元/个
A83: 59 | D83: 公区后改造 | E83: 否 | F83: 如竣工后改造的小区门头、风雨连廊等
A84: 60 | C84: 其他 | D84: 桩基选型以及长度 | E84: 是 | G84: 全部与预制桩
A85: 61 | B85: 工程 | C85: 土方 | D85: 出土时间/弃土方案/土方平衡 | E85: 否 | F85: 出土时间：__________ 弃土方案：__________ 土方平衡：__________
A86: 62 | C86: 支护 | D86: 特殊支护、复杂支护 | E86: 否
A87: 63 | C87: 检测 | D87: 工程检测 | E87: 是 | F87: 桩基大应变检测：____3%______ 轨交监测：__________ 其他：__________
A88: 64 | C88: 评奖 | D88: 是否要求评奖 | E88: 是 | F88: 市级：__________ 省级：__________ 国家级：__________
A89: 65 | C89: 新工艺 | D89: 集团推荐新工艺及其它 | E89: 是 | F89: 铝模、钢背楞木模、全钢爬架、全砼外墙+外墙企口、卫生间止水节、楼板厚度控制器、高精砌块、薄抹灰/面抹灰、地暖模块、冲孔钢板防护网 | G89: 标准刻度：已考虑（铝模、钢背楞木模、全钢爬架……） 本次新增：XXXX 本次取消：XXXX 建筑工程单方：+XXX元/m2或-XXX元/m2
A90: 66 | C90: 项目分期情况 | D90: 分期情况，开/竣 | E90: 否
A91: 67 | B91: 合约 | C91: 后改造成本 | D91: 户内后改造 | E91: 是 | F91: 阳台改造
A92: 68 | D92: 公区后改造 | E92: 否
A93: 69 | C93: 特殊测算指标 | D93: 如分包过总包账 | E93: 否
A94: 70 | B94: 财务 | C94: / | D94: 如税务跳点处理 | E94: 否
A95: 71 | B95: 法务 | C95: / | D95: 如客户投诉风险 | E95: 否
A96: 72 | B96: 报建 | C96: 配套 | D96: 外线高压电缆及敷设沿线的配套情况 | E96: 否 | F96: 接入位置：__________ 电缆长度：__________ 敷设路线是否已有供使用的电缆沟：__________ 需要开挖道路与破坏绿化带等：__________
A97: 73 | D97: 地块周边市政管网水、气的接入位置和距离 | E97: 否 | F97: 接入位置：__________ 管道长度：__________
A98: 74 | C98: 配建 | D98: 配建用房装饰标准要求 | E98: 否 | F98: 当地对配建用房是否有移交要求 | G98: 面积_________，装修标准要求_______元/m2，测算单方_______元/m2
A99: 75 | C99: / | D99: 如所属区位专业垄断要求、收费标准 | E99: 否
A100: 76 | B100: 客服 | C100: 精装修 加载 | D100: 精装修加载 | E100: 否
...

Sheet 01 商业总则
A1: 总则
A2: 一、商业项目名词解释
A3: 分类 | C3: 指标名称 | D3: 指标分项 | E3: 单位 | F3: 设计控制值 | G3: 控制等级 | H3: 计算规则 | I3: 备注 | J3: 备注
A4: 用地规划指标 | C4: 建筑密度 | D4: 集中商业 | E4: - | F4: ≥60% | G4: 参考值 | I4: 住宅与商业同一块地时，争取地块间平衡覆盖率。 | J4: 《商业项目投资可研阶段方案设计控制参考指标》
C5: 绿化率 | D5: 集中商业 | E5: - | F5: ≥15% | G5: 参考值 | I5: 住宅与商业同一块地时，争取地块间平衡绿化率。
A6: 规划设计控制指标 | B6: 地库控制指标 | C6: 地库建筑面积 | E6: ㎡ | F6: - | H6: 地库建筑面积=地下商业面积+塔楼地下面积+地下车库面积+地下设备机房面积+配套面积+非机动车库面积 | I6: 1、塔楼地下面积指地库内塔楼核心筒及地下大堂面积。_x000D_ 2、地下车库面积指地下停车库及服务于停车库的设备用房面积。_x000D_ 3、地下设备机房面积指服务于商业的设备用房面积。_x000D_ 4、配套面积指地下物业管理用房、后勤用房；酒店项目中酒店后勤等辅助功能用房面积。
C7: 地下商业建筑面积 | E7: ㎡ | F7: - | H7: 即地下商业面积 | I7: - | J7: 成本测算需要_x000D_ 引用拆分指标
C8: 地下建筑面积（非商业） | E8: ㎡ | F8: - | H8: 地下建筑面积（非商业）=塔楼地下面积+地下车库面积+地下设备机房面积+配套面积+非机动车库面积 | I8: -
C9: 机动车单车位指标 | D9: 无人防或人防占地库面积≤10% | E9: ㎡/车位 | F9: 38 | G9: 强控值 | H9: 机动车单车位指标=地下车库面积/地下机动车位总数 | I9: 1、机械车位按一层车位计算停车位数。 | J9: 《商业项目投资可研阶段方案设计控制参考指标》
D10: 人防占地库面积＞10% | E10: ㎡/车位 | F10: 40 | G10: 强控值
C11: 地下设备机房面积配比 | D11: 集中商业 | E11: - | F11: 0.056 | G11: 强控值 | H11: 地下设备机房面积配比=地下设备机房面积/商业业态建筑面积 | I11: 1、商业业态建筑面积指集中商业、写字楼、酒店项目中对应各业态的地上、地下建筑面积之和，不含停车库、公共卸货平台、主要设备机房及地下部分的后勤服务及疏散等建筑面积。
D12: 写字楼 | E12: - | F12: 3.5%_x000D_ （写字楼建筑面积8≥万平米） | G12: 强控值 | H12: 地下设备机房面积配比=地下设备机房面积/商业业态建筑面积 | I12: 1、商业业态建筑面积指集中商业、写字楼、酒店项目中对应各业态的地上、地下建筑面积之和，不含停车库、公共卸货平台、主要设备机房及地下部分的后勤服务及疏散等建筑面积。
E13: - | F13: 4%_x000D_ （写字楼建筑面积5-8万平米） | G13: 强控值
E14: - | F14: 4.5%_x000D_ （写字楼建筑面积≤5万平米） | G14: 强控值
D15: 酒店 | E15: - | F15: 0.08 | G15: 强控值
B16: 集中_x000D_ 商业 | C16: 得铺率 | E16: - | F16: 0.57 | G16: 强控值 | H16: 综合得铺率=可租赁建筑面积/商业建筑面积 | I16: 1、商业建筑面积（GFA）：指建设用地范围内各层商业建筑面积之和，不含停车库、公共卸货平台、主要设备机房及地下部分的后勤服务及疏散等建筑面积。_x000D_ 2、可租赁建筑面积（GLA）：店铺租赁面积加该店铺独立使用的垂直交通、疏散、机房、后勤区等辅助功能面积。（具体详见《集中商业设计指引及配置标准》） | J16: 《商业项目投资可研阶段方案设计控制参考指标》
C17: 地上商业建筑面积 | F17: - | G17: - | H17: 地上商业建筑面积 | I17: 即上述地上各层商业建筑面积之和 | J17: 成本测算需要_x000D_ 引用拆分指标
C18: 小铺率 | E18: % | H18: 小铺率=面积150m2以下的小铺数量/铺位总数量（数量比） | I18: 150m2以下店铺的数量占比 | J18: 《集中商业设计指引及配置标准》
C19: 主力店占比 | E19: % | H19: 主力店占比=主力店面积/可租赁建筑面积（面积比） | I19: 主力店指商管公司确认的主力店店铺类型，如影院、超市等
C20: 层高 | E20: m | F20: 负一层5.7_x000D_ 首层6_x000D_ 二层以上5.4 | G20: 参考值 | I20: 此项为可研阶段拿地方案参考值 | J20: 《商业项目投资可研阶段方案设计控制参考指标》
B21: 写字楼控制指标 | C21: 实用率 | D21: H≤100m | E21: - | F21: ≥75% | G21: 强控值 | H21: 综合实用率=办公可租赁总面积/（办公塔楼地上总建筑面积－避难区面积） | I21: 1、实用率计算中标准层公共走道计入公摊面积。 | J21: 《商业项目投资可研阶段方案设计控制参考指标》
D22: 100m＜H≤150m | E22: - | F22: ≥73% | G22: 强控值
D23: 150m＜H≤200m | E23: - | F23: ≥71% | G23: 强控值
C24: 层高 | E24: m | F24: 4.2~4.5 | G24: 参考值 | I24: 此项为可研阶段拿地方案参考值
C25: 标准层面积 | D25: H≤100m | E25: ㎡ | F25: 1500~2000 | G25: 参考值 | I25: 此项为可研阶段拿地方案参考值
D26: 100m＜H≤150m | E26: ㎡ | F26: 1800~2200 | G26: 参考值
D27: 150m＜H≤200m | E27: ㎡ | F27: 2000~2200 | G27: 参考值
C28: 办公可租赁总面积 | E28: ㎡ | F28: - | G28: - | I28: 各户套内有产权的建筑面积之和 | J28: 《写字楼设计指引及配置标准》
C29: 通风量 | E29: 次/h | F29: - | G29: - | I29: 单位时间内被排出或进入的空气数量
C30: 供电指标 | E30: w/㎡ | F30: - | G30: - | I30: 单位面积用电负荷
C31: 避难层面积 | E31: - | F31: - | G31: 参考值 | I31: 投资阶段进行写字楼项目面积指标测算时应考虑避难层面积。 | J31: 《商业项目投资可研阶段方案设计控制参考指标》
B32: 酒店控制指标 | C32: 酒店建筑面积 | D32: 五星级 | E32: ㎡ | F32: 30000~40000 | G32: 参考值 | H32: 酒店建筑面积=地上酒店建筑面积+地下酒店建筑面积_x000D_ _x000D_ _x000D_ 单客房面积=酒店建筑面积/总客房数 | I32: 1、酒店建筑面积：指地上酒店建筑面积与地下酒店建筑面积和，其中地下酒店建筑面积含为酒店配套的服务用房、设备用房、物业用房、后勤用房、库房、管井等，不含地下车库、人防。_x000D_ 2、自然间：指酒店客房的最小分隔单元，即一个BAY 。_x000D_ 3、钥匙间（key）：对应酒店经营管理中的术语，一个钥匙间可以包含几个自然间。_x000D_ 4、总客房数：对应钥匙间总数。5、单客房面积：每间客房平摊建筑面积。 | J32: 《商业项目投资可研阶段方案设计控制参考指标》
C33: 总客房数 | E33: 间 | F33: 250~350 | G33: 参考值
C34: 单客房面积 | E34: ㎡/key | F34: 125~140 | G34: 强控值
C35: 酒店建筑面积 | D35: 四星级 | E35: ㎡ | F35: 21600~30000 | G35: 参考值
C36: 总客房数 | E36: 间 | F36: 250~350 | G36: 参考值
C37: 单客房面积 | E37: ㎡/key | F37: 90~100 | G37: 强控值
C38: 酒店建筑面积 | D38: 三星级 | E38: ㎡ | F38: 9000~12000 | G38: 参考值
C39: 总客房数 | E39: 间 | F39: 200~250 | G39: 参考值
C40: 单客房面积 | E40: ㎡/key | F40: 55~65 | G40: 强控值
C41: 套房占比 | D41: - | E41: % | F41: - | G41: - | H41: 套房占比=套房总数量/客房总数量 | J41: 《酒店设计指引及配置标准》
C42: 层高 | D42: 五星级 | E42: m | F42: 3.6 | G42: 参考值 | I42: 此项为可研阶段拿地方案参考值 | J42: 《商业项目投资可研阶段方案设计控制参考指标》
D43: 四星级 | E43: m | F43: 3.6 | G43: 参考值
D44: 三星级 | E44: m | F44: 3.5 | G44: 参考值
C45: 标准客房开间 | D45: 五星级 | E45: m | F45: 4.5 | G45: 参考值 | I45: 1、此项为可研阶段拿地方案参考值。_x000D_ 2、此项数值为轴间距。
D46: 四星级 | E46: m | F46: 4.2 | G46: 参考值
D47: 三星级 | E47: m | F47: 3.8~4.0 | G47: 参考值
A48: 二、面积及成本分摊原则
A49: 2.1各专业系统建安成本分摊原则
A50: 序号 | C50: 成本科目 | D50: 成本分摊原则
D51: 地上 | H51: 地下
A52: 1 | C52: 精装修工程 | D52: 写字楼或酒店地下大堂（或电梯厅）精装修成本计入地上各业态成本。 | H52: -
A53: =MAX(A52)+1 -> 2 | C53: 幕墙工程 | D53: 地下外立面工程（如下沉广场幕墙）成本计入地上各业态成本中。 | H53: -
A54: =MAX(A53)+1 -> 3 | C54: 电梯工程 | D54: 商业项目（含地上、地下）分摊所有直梯成本，商业项目内部扶梯及自动坡道计入商业成本； | H54: 地库不分摊直梯成本；地下商业与地库相通的扶梯及自动坡道成本计入商业项目成本。
A55: =MAX(A54)+1 -> 4 | C55: 常规机电-电气工程 | D55: 按受益者分摊原则，分摊地下室内服务于本业态的设备及线缆。 | H55: 地库不分摊为空调设备、水泵房、消防泵房服务的配电指标成本，此部分成本按受益者分摊原则以对应服务业态建筑面积占比（或用电负荷占比）分摊至各业态成本。
A56: =MAX(A55)+1 -> 5 | C56: 常规机电-给排水工程 | D56: 按受益者分摊原则，分摊地下室内服务于本业态的设备及主管线。 | H56: 地库不分摊给水泵房及主管道成本（含中水、雨水、直饮水等），此部分成本按受益者分摊原则以设备及管线服务业态分摊至各业态成本。
A57: =MAX(A56)+1 -> 6 | C57: 暖通空调 | D57: 按各类型空调系统末端服务建筑面积分摊至各业态成本。 | H57: 地库不分摊空调冷热源设备及主管线成本，此部分成本按对应服务业态建筑面积占比分摊至各业态成本。
A58: =MAX(A57)+1 -> 7 | C58: 消防工程 | D58: 按受益者分摊原则，分摊地下室内服务于本业态的设备及主管线。 | H58: 消防水泵房及主管线按受益者分摊原则以对应服务业态建筑面积占比分摊至各业态成本。
A59: =MAX(A58)+1 -> 8 | C59: 智能化系统 | D59: 除停车场管理相关系统外，其余智能化系统按各业态建筑面积（除地下非商业外）占比分摊至各业态成本。 | H59: 停车场管理相关系统计入地库成本。
A60: =MAX(A59)+1 -> 9 | C60: 泛光照明 | D60: 泛光照明成本仅计入到各商业项目业态成本。 | H60: 地库不分摊泛光照明成本。
A61: 2.2各物业类型毛坯建安成本分摊原则（商业项目无户内精装修科目）
A62: 序号 | C62: 成本科目 | D62: 分摊内容 | F62: 分摊原则
D63: 面积 | E63: 成本 | F63: 面积 | H63: 成本
A64: =MAX(A63)+1 -> 1 | C64: 前期工程 | D64: - | E64: √ | F64: - | H64: 以各建筑单体的地上建筑面积占比分摊（地下商业建筑面积参与成本分摊）。
A65: =MAX(A64)+1 -> 2 | C65: 桩基础工程 | D65: - | E65: √ | F65: - | H65: 以各建筑单体的地上建筑面积占比分摊（地下商业建筑面积参与成本分摊）。
A66: =MAX(A65)+1 -> 3 | C66: 岩土工程 | D66: - | E66: √ | F66: - | H66: 以各建筑单体的地上建筑面积占比分摊（地下商业建筑面积参与成本分摊）。
A67: =MAX(A66)+1 -> 4 | C67: 地库及机房 | D67: √ | E67: √ | F67: 以地库上建筑单体的地上建筑面积占比分摊（地下商业建筑面积参与成本分摊）。 | H67: 以地库上建筑单体的地上建筑面积占比分摊（地下商业建筑面积参与成本分摊）。
A68: =MAX(A67)+1 -> 5 | C68: 集中商业 | D68: 不分摊 | F68: - | H68: 全部属于集中商业成本
A69: =MAX(A68)+1 -> 6 | C69: 写字楼 | D69: 不分摊 | F69: - | H69: 全部属于写字楼成本
A70: =MAX(A69)+1 -> 7 | C70: 酒店 | D70: 不分摊 | F70: - | H70: 全部属于酒店成本
A71: =MAX(A70)+1 -> 8 | C71: 配套工程 | D71: - | E71: √ | F71: - | H71: 以各建筑单体的地上建筑面积占比分摊（地下商业建筑面积参与成本分摊）。
A72: =MAX(A71)+1 -> 9 | C72: 室外工程 | D72: - | E72: √ | F72: - | H72: 以各建筑单体的地上建筑面积占比分摊（地下商业建筑面积参与成本分摊）。
A73: =MAX(A72)+1 -> 10 | C73: 基础设施工程 | D73: - | E73: - | F73: - | H73: -
A74: =MAX(A73)+1 -> 11 | C74: 卖场包装费用 | D74: - | E74: - | F74: - | H74: -
A75: 三、不可预见费记取原则
A76: 1、设置条件：300米以上超高层建筑或重大重要商业项目可研究设置不可预见费。
A77: 2、使用条件：项目方案重有大调整、主要材料市场涨价等情况。
A78: 四、填写色块说明
A79: 1）白色表格需手动输入；_x000D_ 2）绿色、灰色表格无法输入、自动链接生成；其中绿色为关键指标、灰色为基础数据链接；
A80: 五、固定、暂定、弹性成本划分原则
A81: 1）暂定成本：前期工程、桩基础工程、岩土工程、配套工程；_x000D_ 2）固定：土建工程（建筑工程、人防工程、防水工程、防火门工程）、钢结构工程、常规机电工程、消防工程；_x000D_ 3）弹性：外立面工程（幕墙工程、外立面门窗工程、外墙保温工程）、精装修工程、门类工程（入户门工程、大堂门工程）、栏杆工程、电梯工程、暖通空调工程、智能化工程、泛光照明工程、景观工程、标识工程。
A82: 六、各业态适用范围说明
A83: 示例一：独立集中商业，划分为2个业态，地库+集中商业； 示例二：独立写字楼，划分为2个业态，地库+写字楼； 示例三：独立酒店，划分为2个业态，地库+酒店； 示例四：综合体商业+写字楼，划分为3个业态，地库+集中商业+写字楼 示例五：综合体商业+酒店，划分为3个业态，地库+集中商业+酒店 示例六：综合体酒店+写字楼，划分为3个业态，地库+酒店+写字楼 示例七：综合体商业+酒店+写字楼，划分为4个业态，地库+集中商业+酒店+写字楼 示例八：如存在长租公寓，长租公寓与其他商业业态划分口径一致

Sheet 02 项目基础信息（输入）
A1: 一、基础信息 | CI1: C020001
A2: 1、通用 | H2: 2、住宅 | O2: 3、集中商业 | V2: 4、写字楼 | AC2: 5、酒店 | CI2: C020002
A3: 序号 | B3: 编码 | C3: 基础信息 | D3: 指标值 | E3: 单位 | F3: 属性 | H3: 序号 | I3: 编码 | J3: 基础信息 | K3: 指标值 | L3: 单位 | M3: 属性 | O3: 序号 | P3: 编码 | Q3: 基础信息 | R3: 指标值 | S3: 单位 | T3: 属性 | V3: 序号 | W3: 编码 | X3: 基础信息 | Y3: 指标值 | Z3: 单位 | AA3: 属性 | AC3: 序号 | AD3: 编码 | AE3: 基础信息 | AF3: 指标值 | AG3: 单位 | AH3: 属性 | CI3: C020003
A4: 1 | B4: PJ.01.03 | C4: 总建筑面积 | D4: =C69+C96 -> 74626.755 | E4: ㎡ | F4: 通用 | H4: 1 | I4: PJ.02.10.01 | J4: 项目定档 | K4: U4 | M4: 住宅 | O4: 1 | P4: PJ.02.10.01 | Q4: 项目定档 | T4: 集中商业 | V4: 1 | W4: PJ.02.10.01 | X4: 项目定档 | AA4: 写字楼 | AC4: 1 | AD4: PJ.02.10.01 | AE4: 项目定档 | AH4: 酒店 | CI4: C020004
A5: =MAX(A4)+1 -> 2 | B5: PJ.01.01 | C5: 地上建筑面积 | D5: =D4-D6 -> 52694.835 | E5: ㎡ | F5: 通用 | H5: =MAX(H4)+1 -> 2 | I5: PJ.02.02.01 | J5: 总计容面积 | K5: =D69 -> 46561.065 | L5: ㎡ | M5: 住宅 | O5: 2 | P5: PJ.03.10 | Q5: 集中商业建筑面积 | R5: =C75 -> 0 | S5: ㎡ | T5: 集中商业 | V5: 2 | W5: PJ.04.10 | X5: 写字楼建筑面积 | Y5: =C78 -> 0 | Z5: ㎡ | AA5: 写字楼 | AC5: 2 | AD5: PJ.05.10 | AE5: 酒店总建筑面积 | AF5: =AF6+AF7 -> 0 | AG5: ㎡ | AH5: 酒店 | CI5: C020005
A6: =MAX(A5)+1 -> 3 | B6: PJ.01.02 | C6: 地下建筑面积 | D6: =C32+E96 -> 21931.92 | E6: ㎡ | F6: 通用 | H6: =MAX(H5)+1 -> 3 | I6: PJ.02.02.02 | J6: 地上计容面积 | K6: =K5-K7 -> 46561.065 | L6: ㎡ | M6: 住宅 | O6: =MAX(O5)+1 -> 3 | P6: PJ.03.10.01 | Q6: 集中商业（地下）建筑面积 | R6: =E75 -> 0 | S6: ㎡ | T6: 集中商业 | V6: =MAX(V5)+1 -> 3 | W6: PJ.04.11 | X6: 办公可租赁面积 | Y6: =H78 -> 0 | Z6: ㎡ | AA6: 写字楼 | AC6: =MAX(AC5)+1 -> 3 | AD6: PJ.05.10.01 | AE6: 酒店地上建筑面积 | AF6: =C81 -> 0 | AG6: ㎡ | AH6: 酒店 | CI6: C020006
A7: =MAX(A6)+1 -> 4 | B7: PJ.01.43 | C7: 总商业建筑面积 | D7: =C96-C72 -> 0 | E7: ㎡ | F7: 通用 | H7: =MAX(H6)+1 -> 4 | I7: PJ.02.02.03 | J7: 地下计容面积 | K7: =D32 -> 0 | L7: ㎡ | M7: 住宅 | O7: =MAX(O6)+1 -> 4 | P7: PJ.03.10.02 | Q7: 集中商业（地上）建筑面积 | R7: =D75 -> 0 | S7: ㎡ | T7: 集中商业 | V7: =MAX(V6)+1 -> 4 | W7: PJ.04.12 | X7: 写字楼租赁展示区面积 | Y7: =M78 -> 0 | Z7: ㎡ | AA7: 写字楼 | AC7: =MAX(AC6)+1 -> 4 | AD7: PJ.05.10.02 | AE7: 酒店地下建筑面积 | AG7: ㎡ | AH7: 酒店 | CI7: C020007
A8: =MAX(A7)+1 -> 5 | B8: PJ.01.03.01 | C8: 地上商业建筑面积 | D8: =D7-D9 -> 0 | E8: ㎡ | F8: 通用 | H8: =MAX(H7)+1 -> 5 | I8: PJ.02.01 | J8: 容积率 | K8: =IFERROR(K5/D13,0) -> 1.616 | L8: ㎡/㎡ | M8: 住宅 | O8: =MAX(O7)+1 -> 5 | P8: PJ.03.11 | Q8: 可租赁建筑面积 | R8: =H75 -> 0 | S8: ㎡ | T8: 集中商业 | V8: =MAX(V7)+1 -> 5 | W8: PJ.04.13 | X8: 避难区面积 | Y8: =N78 -> 0 | Z8: ㎡ | AA8: 写字楼 | AC8: =MAX(AC7)+1 -> 5 | AD8: PJ.05.11 | AE8: 客房总数 | AF8: =BN81+BP81+BR81+BT81 -> 0 | AG8: key | AH8: 酒店 | CI8: C020008
A9: =MAX(A8)+1 -> 6 | B9: PJ.01.03.02 | C9: 地下商业建筑面积 | D9: =E75+E84 -> 0 | E9: ㎡ | F9: 通用 | H9: =MAX(H8)+1 -> 6 | I9: PJ.01.12 | J9: 户数 | K9: =AC69 -> 301 | L9: 户 | M9: 住宅 | O9: =MAX(O8)+1 -> 6 | P9: PJ.03.11.01 | Q9: 地上可租赁建筑面积 | R9: =R8-R10 -> 0 | S9: ㎡ | T9: 集中商业 | V9: =MAX(V8)+1 -> 6 | W9: PJ.04.14 | X9: 实用率 | Y9: =IFERROR(Y6/(Y5-Y8),0) -> 0 | Z9: ㎡ | AA9: 写字楼 | AC9: =MAX(AC8)+1 -> 6 | AD9: PJ.05.12 | AE9: 套房总数 | AF9: =BT81+BR81 -> 0 | AG9: key | AH9: 酒店 | CI9: C020009
A10: =MAX(A9)+1 -> 7 | B10: PJ.01.06 | C10: 总建造面积 | D10: =I69+C96 -> 74626.755 | E10: ㎡ | F10: 通用 | H10: =MAX(H9)+1 -> 7 | I10: PJ.80.38 | J10: 可售率 | K10: =IFERROR(K11/D4,0) -> 0.61896119 | L10: % | M10: 住宅 | O10: =MAX(O9)+1 -> 7 | P10: PJ.03.11.02 | Q10: 地下可租赁建筑面积 | S10: ㎡ | T10: 集中商业 | V10: =MAX(V9)+1 -> 7 | W10: PJ.04.15 | X10: 标准层层高 | Y10: =V78 -> 0 | Z10: m | AA10: 写字楼 | AC10: =MAX(AC9)+1 -> 7 | AD10: PJ.05.13 | AE10: 单客房面积 | AF10: =IFERROR((AF6+AF7)/AF8,0) -> 0 | AG10: ㎡/key | AH10: 酒店 | CI10: C0200010
A11: =MAX(A10)+1 -> 8 | B11: PJ.01.04 | C11: 地上建造面积 | D11: =D10-D12 -> 52694.835 | E11: ㎡ | F11: 通用 | H11: =MAX(H10)+1 -> 8 | I11: PJ.01.14 | J11: 可售面积 | K11: =E69 -> 46191.065 | L11: ㎡ | M11: 住宅 | O11: =MAX(O10)+1 -> 8 | P11: PJ.03.13 | Q11: 公共区域精装面积 | R11: =AD75 -> 0 | S11: ㎡ | T11: 集中商业 | V11: =MAX(V10)+1 -> 8 | W11: PJ.04.16 | X11: 标准层净高 | Y11: =U78 -> 0 | Z11: m | AA11: 写字楼 | AC11: =MAX(AC10)+1 -> 8 | AD11: PJ.05.14 | AE11: 套房占比 | AF11: =IFERROR(AF9/AF8,0) -> 0 | AG11: % | AH11: 酒店 | CI11: C0200011
A12: =MAX(A11)+1 -> 9 | B12: PJ.01.05 | C12: 地下建造面积 | D12: =E96+I32 -> 21931.92 | E12: ㎡ | F12: 通用 | H12: =MAX(H11)+1 -> 9 | I12: PJ.02.03.01 | J12: 套内面积 | K12: =+F69 -> 46191.065 | L12: ㎡ | M12: 住宅 | O12: =MAX(O11)+1 -> 9 | P12: PJ.03.14 | Q12: 得铺率 | R12: =I75 -> 0 | S12: % | T12: 集中商业 | V12: =MAX(V11)+1 -> 9 | W12: PJ.04.17 | X12: 建筑高度 | Y12: =F78 -> 0 | Z12: m | AA12: 写字楼 | AC12: =MAX(AC11)+1 -> 9 | AD12: PJ.05.15 | AE12: 标准层层高 | AF12: =V81 -> 0 | AG12: m | AH12: 酒店 | CI12: C0200012
A13: =MAX(A12)+1 -> 10 | B13: PJ.80.37 | C13: 占地面积 | D13: =总指标!E4 -> 28812.54 | E13: ㎡ | F13: 通用 | H13: =MAX(H12)+1 -> 10 | I13: PJ.02.04.01 | J13: 得房率 | K13: =IFERROR(K12/D69,0) -> 0.99205345 | L13: % | M13: 住宅 | O13: =MAX(O12)+1 -> 10 | P13: PJ.03.15 | Q13: 小铺率 | R13: =J75 -> 0 | S13: % | T13: 集中商业 | V13: =MAX(V12)+1 -> 10 | W13: PJ.04.18 | X13: 结构高度 | Y13: =G78 -> 0 | Z13: m | AA13: 写字楼 | AC13: =MAX(AC12)+1 -> 10 | AD13: PJ.05.16 | AE13: 标准层净高 | AF13: =U81 -> 0 | AG13: m | AH13: 酒店 | CI13: C0200013
A14: =MAX(A13)+1 -> 11 | B14: PJ.01.20 | C14: 室外面积 | D14: =总指标!E55-K26 -> 18786.64 | E14: ㎡ | F14: 通用 | H14: =MAX(H13)+1 -> 11 | I14: PJ.02.02.04 | J14: 室外面积占比 （室外/占地） | K14: =IFERROR(D14/D13,0) -> 0.65202998 | L14: % | M14: 住宅 | O14: =MAX(O13)+1 -> 11 | P14: PJ.03.16 | Q14: 主力店占比 | R14: =K75 -> 0 | S14: % | T14: 集中商业 | V14: =MAX(V13)+1 -> 11 | W14: PJ.04.19 | X14: 通风量 | Y14: =P78 -> 0 | Z14: 次/h | AA14: 写字楼 | AC14: =MAX(AC13)+1 -> 11 | AD14: PJ.05.20 | AE14: 综合用电指标 | AF14: =Q81 -> 0 | AG14: （VA/㎡） | AH14: 酒店 | CI14: C0200014
A15: =MAX(A14)+1 -> 12 | B15: PJ.01.22 | C15: 基坑面积 | D15: 24661 | E15: ㎡ | F15: 通用 | H15: =MAX(H14)+1 -> 12 | I15: PJ.02.02.05 | J15: 绿地率 （规划指标） | K15: 0 | L15: % | M15: 住宅 | O15: =MAX(O14)+1 -> 12 | P15: PJ.04.12 | Q15: 商场租赁展示区面积 | R15: =L75 -> 0 | S15: ㎡ | T15: 集中商业 | V15: =MAX(V14)+1 -> 12 | W15: PJ.04.20 | X15: 综合用电指标 | Y15: =Q78 -> 0 | Z15: （VA/㎡） | AA15: 写字楼 | AC15: =MAX(AC14)+1 -> 12 | AD15: PJ.05.21 | AE15: 供冷指标 | AF15: =R81 -> 0 | AG15: w/㎡ | AH15: 酒店 | CI15: C0200015
A16: =MAX(A15)+1 -> 13 | B16: PJ.80.36 | C16: 基坑延米长度 | D16: =支护!F3 -> 861 | E16: 延米 | F16: 通用 | H16: =MAX(H15)+1 -> 13 | I16: PJ.02.02.06 | J16: 硬景占比 （硬景/室外） | K16: 0 | L16: % | M16: 住宅 | O16: =MAX(O15)+1 -> 13 | P16: PJ.04.20 | Q16: 综合用电指标 | R16: =Q75 -> 0 | S16: （VA/㎡） | T16: 集中商业 | V16: =MAX(V15)+1 -> 13 | W16: PJ.04.21 | X16: 供冷指标 | Y16: =R78 -> 0 | Z16: w/㎡ | AA16: 写字楼 | AC16: =MAX(AC15)+1 -> 13 | AD16: PJ.05.19 | AE16: 酒店星级 | AG16: - | AH16: 酒店 | CI16: C0200016
A17: =MAX(A16)+1 -> 14 | B17: PJ.80.40 | C17: 总装机容量 | E17: KVA | F17: 通用 | H17: =MAX(H16)+1 -> 14 | I17: PJ.02.02.07 | J17: 软景占比 （软景/室外） | K17: 0 | L17: % | M17: 住宅 | O17: =MAX(O16)+1 -> 14 | P17: PJ.04.21 | Q17: 供冷指标 | R17: =R75 -> 0 | S17: w/㎡ | T17: 集中商业 | V17: =MAX(V16)+1 -> 14 | W17: PJ.04.22 | X17: 行业认证 | Z17: - | AA17: 写字楼 | AC17: =MAX(AC16)+1 -> 14 | AD17: PJ.05.22 | AE17: 行业认证 | AG17: - | AH17: 酒店 | CI17: C0200017
A18: =MAX(A17)+1 -> 15 | B18: PJ.80.34 | C18: 高压干线长度含通道 | E18: km | F18: 通用 | H18: =MAX(H17)+1 -> 15 | I18: PJ.02.03.02 | J18: 水景面积 | L18: ㎡ | M18: 住宅 | O18: =MAX(O17)+1 -> 15 | P18: PJ.04.22 | Q18: 行业认证 | S18: - | T18: 集中商业 | CI18: C0200018
A19: =MAX(A18)+1 -> 16 | B19: PJ.02.12 | C19: 车位数 | D19: =AI69+CD96 -> 522.5 | E19: 个 | F19: 通用 | H19: =MAX(H18)+1 -> 16 | I19: PJ.01.15 | J19: 户内装饰面积 | K19: =G69 -> 46191.065 | L19: ㎡ | M19: 住宅 | CI19: C0200019
A20: =MAX(A19)+1 -> 17 | B20: PJ.01.02.01 | C20: 地下车位数 | D20: =AI32+CD72 -> 522.5 | E20: 个 | F20: 通用 | H20: =MAX(H19)+1 -> 17 | I20: PJ.01.17 | J20: 赠送面积 | K20: =H69 -> 0 | L20: ㎡ | M20: 住宅 | CI20: C0200020
A21: =MAX(A20)+1 -> 18 | B21: PJ.02.04 | C21: 机动车单车位面积 （不含地下配套、可售） | D21: =IFERROR((I33+E72)/D20,0) -> 38.912766 | E21: ㎡/个 | F21: 通用 | H21: =MAX(H20)+1 -> 18 | I21: PJ.01.21 | J21: 卖场总面积 （含样板房） | K21: =总指标!K3+1000 -> 1370 | L21: ㎡ | M21: 住宅 | CI21: C0200021
A22: =MAX(A21)+1 -> 19 | B22: PJ.80.08 | C22: 充电桩数量 | D22: =AJ69+CG96 -> 156.75 | E22: (个) | F22: 通用 | H22: =MAX(H21)+1 -> 19 | I22: PJ.02.03.03 | J22: 售楼处面积 | K22: =总指标!K3 -> 370 | L22: ㎡ | M22: 住宅 | CI22: C0200022
A23: =MAX(A22)+1 -> 20 | B23: PJ.80.35 | C23: 停车场出入口数量 | D23: =AK69+CH96 -> 2 | E23: 个 | F23: 通用 | H23: =MAX(H22)+1 -> 20 | I23: PJ.02.04.02 | J23: 样板房数量 | K23: 2 | L23: 个 | M23: 住宅 | CI23: C0200023
A24: =MAX(A23)+1 -> 21 | B24: PJ.01.02.02 | C24: 地下车库-1F层高 | D24: 3.7 | E24: m | F24: 通用 | H24: =MAX(H23)+1 -> 21 | I24: PJ.02.03.04 | J24: 样板房总面积 | K24: =SUM(总指标!J24:J26) -> 319 | L24: ㎡ | M24: 住宅 | CI24: C0200024
A25: =MAX(A24)+1 -> 22 | B25: PJ.01.02.03 | C25: 地下车库-2F层高 | E25: m | F25: 通用 | H25: =MAX(H24)+1 -> 22 | I25: PJ.02.05.01 | J25: 看房通道长度 | L25: m | M25: 住宅 | CI25: C0200025
A26: =MAX(A25)+1 -> 23 | B26: PJ.01.02.04 | C26: 地下车库-3F层高 | E26: m | F26: 通用 | H26: =MAX(H25)+1 -> 23 | I26: PJ.80.33 | J26: 示范区室外面积 | K26: 4600 | L26: ㎡ | M26: 住宅 | CI26: C0200026
CI27: C0200027
CI28: C0200028
A29: 二、信息明细 | CI29: C0200029
A30: 1、住宅 | CI30: C0200030
A31: 分类 | B31: 业态/楼栋 | C31: 建筑面积 （㎡） | D31: 计容面积 （㎡） | E31: 可售面积 （㎡） | F31: 套内面积 （㎡） | G31: 户内装饰面积 （㎡） | H31: 赠送/空腔面积 （㎡） | I31: 建造面积_x000D_ （业态） | J31: 电梯数 | K31: 单个电梯厅面积_x000D_ （m2/个） | L31: 电梯厅数量 | M31: 电梯厅总面积_x000D_ （m2） | N31: 单个大堂面积（m2/个） | O31: 大堂数量 | P31: 大堂总面积_x000D_ （m2） | Q31: 单个标准层连廊面积_x000D_ （m2/个） | R31: 标准层连廊数量 | S31: 标准层连廊总面积_x000D_ （m2） | T31: 单个地下大堂面积_x000D_ （m2/个） | U31: 地下大堂数量 | V31: 地下大堂总面积_x000D_ （m2） | W31: 单个车马厅面积_x000D_ （m2/个） | X31: 车马厅数量 | Y31: 车马厅总面积_x000D_ （m2） | Z31: 架空层面积_x000D_ （m2） | AA31: 楼层数 | AB31: 标准层_x000D_层高_x000D_ （m） | AC31: 户数 | AD31: 卫生间数 | AE31: 墙积比 | AF31: 外墙装饰面积 | AG31: 楼栋数 | AH31: 母婴室 | AI31: 车位数 | AJ31: 充电桩数量 | AK31: 停车场出入口数量 | CI31: C0200031
A32: 业态 | B32: 地下室其他(住宅) | C32: =SUM(C33:C35) -> 21931.92 | D32: =SUM(D33:D35) -> 0 | E32: =SUM(E33:E35) -> 0 | F32: =SUM(F33:F35) -> 0 | G32: =SUM(G33) -> 0 | H32: =SUM(H33:H35) -> 0 | I32: =SUM(I33:I35) -> 21931.92 | AA32: =SUM(AA33) -> 0 | AB32: =SUM(AB33:AB35) -> 0 | AI32: =SUM(AI33) -> 522.5 | AJ32: =SUM(AJ33) -> 156.75 | AK32: =SUM(AK33) -> 2 | CI32: C02_21
A33: 楼栋 | B33: 地下机动车库及机房 | C33: =总指标!E19+总指标!E20 -> 20331.92 | D33: 0 | I33: =C33+H33 -> 20331.92 | AI33: =总指标!E39 -> 522.5 | AJ33: =AI33*0.3 -> 156.75 | AK33: 2 | CI33: C02_21_1
A34: 楼栋 | B34: 地下规划配套 | C34: =总指标!E21 -> 1600 | D34: 0 | I34: =C34+H34 -> 1600 | CI34: C02_21_2
A35: 楼栋 | B35: 地下可售 | C35: =总指标!E22 -> 0 | D35: 0 | E35: =C35 -> 0 | G35: 0 | I35: =C35+H35 -> 0 | CI35: C02_21_3
A36: 业态 | B36: $pname1$ | C36: =SUM(C37:C38) -> 0 | D36: =SUM(D37:D38) -> 0 | E36: =SUM(E37:E38) -> 0 | F36: =SUM(F37:F38) -> 0 | G36: =SUM(G37:G38) -> 0 | H36: =SUM(H37:H38) -> 0 | I36: =SUM(I37:I38) -> 0 | J36: =SUM(J37:J38) -> 0 | K36: =IF(L36=0,0,M36/L36) -> 0 | L36: =SUM(L37:L38) -> 0 | M36: =SUM(M37:M38) -> 0 | N36: =IF(O36=0,0,P36/O36) -> 0 | O36: =SUM(O37:O38) -> 0 | P36: =SUM(P37:P38) -> 0 | Q36: =IF(R36=0,0,S36/R36) -> 0 | R36: =SUM(R37:R38) -> 0 | S36: =SUM(S37:S38) -> 0 | T36: =IF(U36=0,0,V36/U36) -> 0 | U36: =SUM(U37:U38) -> 0 | V36: =SUM(V37:V38) -> 0 | W36: =IF(X36=0,0,Y36/X36) -> 0 | X36: =SUM(X37:X38) -> 0 | Y36: =SUM(Y37:Y38) -> 0 | Z36: =SUM(Z37:Z38) -> 0 | AA36: =SUM(AA37:AA38) -> 0 | AB36: =SUM(AB37:AB38) -> 0 | AC36: =SUM(AC37:AC38) -> 0 | AD36: =SUM(AD37:AD38) -> 0 | AE36: =IFERROR(AF36/C36,0) -> 0 | AF36: =SUM(AF37:AF38) -> 0 | AG36: =SUM(AG37:AG38) -> 0 | AH36: =SUM(AH37:AH38) -> 0 | AI36: =SUM(AI37:AI38) -> 0 | CI36: C02_$pcode1$
A37: 楼栋 | B37: A1-A3栋 | I37: =C37+H37 -> 0 | M37: =K37*L37 -> 0 | P37: =N37*O37 -> 0 | S37: =Q37*R37 -> 0 | V37: =T37*U37 -> 0 | Y37: =W37*X37 -> 0 | AF37: =C37*AE37 -> 0 | CI37: C02_$pcode1$_1
A38: 楼栋 | B38: A4-A6栋 | I38: =C38+H38 -> 0 | M38: =K38*L38 -> 0 | P38: =N38*O38 -> 0 | S38: =Q38*R38 -> 0 | V38: =T38*U38 -> 0 | Y38: =W38*X38 -> 0 | AF38: =C38*AE38 -> 0 | CI38: C02_$pcode1$_2
A39: 业态 | B39: 普通多层 | C39: =SUM(C40:C41) -> 0 | D39: =SUM(D40:D41) -> 0 | E39: =SUM(E40:E41) -> 0 | F39: =SUM(F40:F41) -> 0 | G39: =SUM(G40:G41) -> 0 | H39: =SUM(H40:H41) -> 0 | I39: =SUM(I40:I41) -> 0 | J39: =SUM(J40:J41) -> 0 | K39: =IF(L39=0,0,M39/L39) -> 0 | L39: =SUM(L40:L41) -> 0 | M39: =SUM(M40:M41) -> 0 | N39: =IF(O39=0,0,P39/O39) -> 0 | O39: =SUM(O40:O41) -> 0 | P39: =SUM(P40:P41) -> 0 | Q39: =IF(R39=0,0,S39/R39) -> 0 | R39: =SUM(R40:R41) -> 0 | S39: =SUM(S40:S41) -> 0 | T39: =IF(U39=0,0,V39/U39) -> 0 | U39: =SUM(U40:U41) -> 0 | V39: =SUM(V40:V41) -> 0 | W39: =IF(X39=0,0,Y39/X39) -> 0 | X39: =SUM(X40:X41) -> 0 | Y39: =SUM(Y40:Y41) -> 0 | Z39: =SUM(Z40:Z41) -> 0 | AA39: =SUM(AA40:AA41) -> 0 | AB39: =SUM(AB40:AB41) -> 0 | AC39: =SUM(AC40:AC41) -> 0 | AD39: =SUM(AD40:AD41) -> 0 | AE39: =IFERROR(AF39/C39,0) -> 0 | AF39: =SUM(AF40:AF41) -> 0 | AG39: =SUM(AG40:AG41) -> 0 | AH39: =SUM(AH40:AH41) -> 0 | AI39: =SUM(AI40:AI41) -> 0 | CI39: C02_12
A40: 楼栋 | B40: A1-A3栋 | G40: 0 | H40: 0 | I40: =C40+H40 -> 0 | M40: =K40*L40 -> 0 | P40: =N40*O40 -> 0 | S40: =Q40*R40 -> 0 | V40: =T40*U40 -> 0 | Y40: =W40*X40 -> 0 | AF40: =C40*AE40 -> 0 | CI40: C02_12_1
A41: 楼栋 | B41: A4-A6栋 | I41: =C41+H41 -> 0 | M41: =K41*L41 -> 0 | P41: =N41*O41 -> 0 | S41: =Q41*R41 -> 0 | V41: =T41*U41 -> 0 | Y41: =W41*X41 -> 0 | AF41: =C41*AE41 -> 0 | CI41: C02_12_2
A42: 业态 | B42: 小高层 | C42: =SUM(C43:C44) -> 51879.835 | D42: =SUM(D43:D44) -> 46191.065 | E42: =SUM(E43:E44) -> 46191.065 | F42: =SUM(F43:F44) -> 46191.065 | G42: =SUM(G43:G44) -> 46191.065 | H42: =SUM(H43:H44) -> 0 | I42: =SUM(I43:I44) -> 51879.835 | J42: =SUM(J43:J44) -> 15 | K42: =IF(L42=0,0,M42/L42) -> 15.52 | L42: =SUM(L43:L44) -> 135 | M42: =SUM(M43:M44) -> 2095.2 | N42: =IF(O42=0,0,P42/O42) -> 55 | O42: =SUM(O43:O44) -> 15 | P42: =SUM(P43:P44) -> 825 | Q42: =IF(R42=0,0,S42/R42) -> 0 | R42: =SUM(R43:R44) -> 0 | S42: =SUM(S43:S44) -> 0 | T42: =IF(U42=0,0,V42/U42) -> 60 | U42: =SUM(U43:U44) -> 15 | V42: =SUM(V43:V44) -> 900 | W42: =IF(X42=0,0,Y42/X42) -> 75 | X42: =SUM(X43:X44) -> 15 | Y42: =SUM(Y43:Y44) -> 1125 | Z42: =SUM(Z43:Z44) -> 4318.77 | AA42: =SUM(AA43:AA44) -> 210 | AB42: =SUM(AB43:AB44) -> 3.1 | AC42: =SUM(AC43:AC44) -> 300 | AD42: =SUM(AD43:AD44) -> 900 | AE42: =IFERROR(AF42/C42,0) -> 1.2 | AF42: =SUM(AF43:AF44) -> 62255.802 | AG42: =SUM(AG43:AG44) -> 8 | AH42: =SUM(AH43:AH44) -> 0 | AI42: =SUM(AI43:AI44) -> 0 | CI42: C02_13
A43: 楼栋 | B43: 10F小高层 | C43: =总指标!E6+总指标!K15+总指标!K14 -> 51879.835 | D43: =总指标!E6 -> 46191.065 | E43: =D43 -> 46191.065 | F43: =D43 -> 46191.065 | G43: =D43 -> 46191.065 | H43: 0 | I43: =C43+H43 -> 51879.835 | J43: 15 | K43: 15.52 | L43: =15*9 -> 135 | M43: =K43*L43 -> 2095.2 | N43: 55 | O43: 15 | P43: =N43*O43 -> 825 | Q43: 0 | R43: 0 | S43: =Q43*R43 -> 0 | T43: 60 | U43: =O43 -> 15 | V43: =T43*U43 -> 900 | W43: 75 | X43: =O43 -> 15 | Y43: =W43*X43 -> 1125 | Z43: =总指标!K15 -> 4318.77 | AA43: =15*14 -> 210 | AB43: 3.1 | AC43: =总指标!L26 -> 300 | AD43: =AC43*3 -> 900 | AE43: 1.2 | AF43: =C43*AE43 -> 62255.802 | AG43: 8 | CI43: C02_13_1
A44: 楼栋 | I44: =C44+H44 -> 0 | M44: =K44*L44 -> 0 | P44: =N44*O44 -> 0 | S44: =Q44*R44 -> 0 | V44: =T44*U44 -> 0 | Y44: =W44*X44 -> 0 | AF44: =C44*AE44 -> 0 | CI44: C02_13_2
A45: 业态 | B45: 高层 | C45: =SUM(C46:C47) -> 0 | D45: =SUM(D46:D47) -> 0 | E45: =SUM(E46:E47) -> 0 | F45: =SUM(F46:F47) -> 0 | G45: =SUM(G46:G47) -> 0 | H45: =SUM(H46:H47) -> 0 | I45: =SUM(I46:I47) -> 0 | J45: =SUM(J46:J47) -> 0 | K45: =IF(L45=0,0,M45/L45) -> 0 | L45: =SUM(L46:L47) -> 0 | M45: =SUM(M46:M47) -> 0 | N45: =IF(O45=0,0,P45/O45) -> 0 | O45: =SUM(O46:O47) -> 0 | P45: =SUM(P46:P47) -> 0 | Q45: =IF(R45=0,0,S45/R45) -> 0 | R45: =SUM(R46:R47) -> 0 | S45: =SUM(S46:S47) -> 0 | T45: =IF(U45=0,0,V45/U45) -> 0 | U45: =SUM(U46:U47) -> 0 | V45: =SUM(V46:V47) -> 0 | W45: =IF(X45=0,0,Y45/X45) -> 0 | X45: =SUM(X46:X47) -> 0 | Y45: =SUM(Y46:Y47) -> 0 | Z45: =SUM(Z46:Z47) -> 0 | AA45: =SUM(AA46:AA47) -> 0 | AB45: =SUM(AB46:AB47) -> 0 | AC45: =SUM(AC46:AC47) -> 0 | AD45: =SUM(AD46:AD47) -> 0 | AE45: =IFERROR(AF45/C45,0) -> 0 | AF45: =SUM(AF46:AF47) -> 0 | AG45: =SUM(AG46:AG47) -> 0 | AH45: =SUM(AH46:AH47) -> 0 | AI45: =SUM(AI46:AI47) -> 0 | CI45: C02_14
A46: 楼栋 | B46: A1-A3栋 | I46: =C46+H46 -> 0 | M46: =K46*L46 -> 0 | P46: =N46*O46 -> 0 | S46: =Q46*R46 -> 0 | V46: =T46*U46 -> 0 | Y46: =W46*X46 -> 0 | AF46: =C46*AE46 -> 0 | CI46: C02_14_1
A47: 楼栋 | B47: A4-A6栋 | I47: =C47+H47 -> 0 | M47: =K47*L47 -> 0 | P47: =N47*O47 -> 0 | S47: =Q47*R47 -> 0 | V47: =T47*U47 -> 0 | Y47: =W47*X47 -> 0 | AF47: =C47*AE47 -> 0 | CI47: C02_14_2
A48: 业态 | B48: $pname2$ | C48: =SUM(C49:C50) -> 0 | D48: =SUM(D49:D50) -> 0 | E48: =SUM(E49:E50) -> 0 | F48: =SUM(F49:F50) -> 0 | G48: =SUM(G49:G50) -> 0 | H48: =SUM(H49:H50) -> 0 | I48: =SUM(I49:I50) -> 0 | J48: =SUM(J49:J50) -> 0 | K48: =IF(L48=0,0,M48/L48) -> 0 | L48: =SUM(L49:L50) -> 0 | M48: =SUM(M49:M50) -> 0 | N48: =IF(O48=0,0,P48/O48) -> 0 | O48: =SUM(O49:O50) -> 0 | P48: =SUM(P49:P50) -> 0 | Q48: =IF(R48=0,0,S48/R48) -> 0 | R48: =SUM(R49:R50) -> 0 | S48: =SUM(S49:S50) -> 0 | T48: =IF(U48=0,0,V48/U48) -> 0 | U48: =SUM(U49:U50) -> 0 | V48: =SUM(V49:V50) -> 0 | W48: =IF(X48=0,0,Y48/X48) -> 0 | X48: =SUM(X49:X50) -> 0 | Y48: =SUM(Y49:Y50) -> 0 | Z48: =SUM(Z49:Z50) -> 0 | AA48: =SUM(AA49:AA50) -> 0 | AB48: =SUM(AB49:AB50) -> 0 | AC48: =SUM(AC49:AC50) -> 0 | AD48: =SUM(AD49:AD50) -> 0 | AE48: =IFERROR(AF48/C48,0) -> 0 | AF48: =SUM(AF49:AF50) -> 0 | AG48: =SUM(AG49:AG50) -> 0 | AH48: =SUM(AH49:AH50) -> 0 | AI48: =SUM(AI49:AI50) -> 0 | CI48: C02_$pcode2$
A49: 楼栋 | B49: A1-A3栋 | I49: =C49+H49 -> 0 | M49: =K49*L49 -> 0 | P49: =N49*O49 -> 0 | S49: =Q49*R49 -> 0 | V49: =T49*U49 -> 0 | Y49: =W49*X49 -> 0 | AF49: =C49*AE49 -> 0 | CI49: C02_$pcode2$_1
A50: 楼栋 | B50: A4-A6栋 | I50: =C50+H50 -> 0 | M50: =K50*L50 -> 0 | P50: =N50*O50 -> 0 | S50: =Q50*R50 -> 0 | V50: =T50*U50 -> 0 | Y50: =W50*X50 -> 0 | AF50: =C50*AE50 -> 0 | CI50: C02_$pcode2$_2
A51: 业态 | B51: $pname3$ | C51: =SUM(C52:C53) -> 0 | D51: =SUM(D52:D53) -> 0 | E51: =SUM(E52:E53) -> 0 | F51: =SUM(F52:F53) -> 0 | G51: =SUM(G52:G53) -> 0 | H51: =SUM(H52:H53) -> 0 | I51: =SUM(I52:I53) -> 0 | J51: =SUM(J52:J53) -> 0 | K51: =IF(L51=0,0,M51/L51) -> 0 | L51: =SUM(L52:L53) -> 0 | M51: =SUM(M52:M53) -> 0 | N51: =IF(O51=0,0,P51/O51) -> 0 | O51: =SUM(O52:O53) -> 0 | P51: =SUM(P52:P53) -> 0 | Q51: =IF(R51=0,0,S51/R51) -> 0 | R51: =SUM(R52:R53) -> 0 | S51: =SUM(S52:S53) -> 0 | T51: =IF(U51=0,0,V51/U51) -> 0 | U51: =SUM(U52:U53) -> 0 | V51: =SUM(V52:V53) -> 0 | W51: =IF(X51=0,0,Y51/X51) -> 0 | X51: =SUM(X52:X53) -> 0 | Y51: =SUM(Y52:Y53) -> 0 | Z51: =SUM(Z52:Z53) -> 0 | AA51: =SUM(AA52:AA53) -> 0 | AB51: =SUM(AB52:AB53) -> 0 | AC51: =SUM(AC52:AC53) -> 0 | AD51: =SUM(AD52:AD53) -> 0 | AE51: =IFERROR(AF51/C51,0) -> 0 | AF51: =SUM(AF52:AF53) -> 0 | AG51: =SUM(AG52:AG53) -> 0 | AH51: =SUM(AH52:AH53) -> 0 | AI51: =SUM(AI52:AI53) -> 0 | CI51: C02_$pcode3$
A52: 楼栋 | B52: A1-A3栋 | I52: =C52+H52 -> 0 | M52: =K52*L52 -> 0 | P52: =N52*O52 -> 0 | S52: =Q52*R52 -> 0 | V52: =T52*U52 -> 0 | Y52: =W52*X52 -> 0 | AF52: =C52*AE52 -> 0 | CI52: C02_$pcode3$_1
A53: 楼栋 | B53: A4-A6栋 | I53: =C53+H53 -> 0 | M53: =K53*L53 -> 0 | P53: =N53*O53 -> 0 | S53: =Q53*R53 -> 0 | V53: =T53*U53 -> 0 | Y53: =W53*X53 -> 0 | AF53: =C53*AE53 -> 0 | CI53: C02_$pcode3$_2
A54: 业态 | B54: $pname4$ | C54: =SUM(C55:C56) -> 0 | D54: =SUM(D55:D56) -> 0 | E54: =SUM(E55:E56) -> 0 | F54: =SUM(F55:F56) -> 0 | G54: =SUM(G55:G56) -> 0 | H54: =SUM(H55:H56) -> 0 | I54: =SUM(I55:I56) -> 0 | J54: =SUM(J55:J56) -> 0 | K54: =IF(L54=0,0,M54/L54) -> 0 | L54: =SUM(L55:L56) -> 0 | M54: =SUM(M55:M56) -> 0 | N54: =IF(O54=0,0,P54/O54) -> 0 | O54: =SUM(O55:O56) -> 0 | P54: =SUM(P55:P56) -> 0 | Q54: =IF(R54=0,0,S54/R54) -> 0 | R54: =SUM(R55:R56) -> 0 | S54: =SUM(S55:S56) -> 0 | T54: =IF(U54=0,0,V54/U54) -> 0 | U54: =SUM(U55:U56) -> 0 | V54: =SUM(V55:V56) -> 0 | W54: =IF(X54=0,0,Y54/X54) -> 0 | X54: =SUM(X55:X56) -> 0 | Y54: =SUM(Y55:Y56) -> 0 | Z54: =SUM(Z55:Z56) -> 0 | AA54: =SUM(AA55:AA56) -> 0 | AB54: =SUM(AB55:AB56) -> 0 | AC54: =SUM(AC55:AC56) -> 0 | AD54: =SUM(AD55:AD56) -> 0 | AE54: =IFERROR(AF54/C54,0) -> 0 | AF54: =SUM(AF55:AF56) -> 0 | AG54: =SUM(AG55:AG56) -> 0 | AH54: =SUM(AH55:AH56) -> 0 | AI54: =SUM(AI55:AI56) -> 0 | CI54: C02_$pcode4$
A55: 楼栋 | B55: A1-A3栋 | I55: =C55+H55 -> 0 | M55: =K55*L55 -> 0 | P55: =N55*O55 -> 0 | S55: =Q55*R55 -> 0 | V55: =T55*U55 -> 0 | Y55: =W55*X55 -> 0 | AF55: =C55*AE55 -> 0 | CI55: C02_$pcode4$_1
A56: 楼栋 | B56: A4-A6栋 | I56: =C56+H56 -> 0 | M56: =K56*L56 -> 0 | P56: =N56*O56 -> 0 | S56: =Q56*R56 -> 0 | V56: =T56*U56 -> 0 | Y56: =W56*X56 -> 0 | AF56: =C56*AE56 -> 0 | CI56: C02_$pcode4$_2
A57: 业态 | B57: $pname5$ | C57: =SUM(C58:C59) -> 0 | D57: =SUM(D58:D59) -> 0 | E57: =SUM(E58:E59) -> 0 | F57: =SUM(F58:F59) -> 0 | G57: =SUM(G58:G59) -> 0 | H57: =SUM(H58:H59) -> 0 | I57: =SUM(I58:I59) -> 0 | J57: =SUM(J58:J59) -> 0 | K57: =IF(L57=0,0,M57/L57) -> 0 | L57: =SUM(L58:L59) -> 0 | M57: =SUM(M58:M59) -> 0 | N57: =IF(O57=0,0,P57/O57) -> 0 | O57: =SUM(O58:O59) -> 0 | P57: =SUM(P58:P59) -> 0 | Q57: =IF(R57=0,0,S57/R57) -> 0 | R57: =SUM(R58:R59) -> 0 | S57: =SUM(S58:S59) -> 0 | T57: =IF(U57=0,0,V57/U57) -> 0 | U57: =SUM(U58:U59) -> 0 | V57: =SUM(V58:V59) -> 0 | W57: =IF(X57=0,0,Y57/X57) -> 0 | X57: =SUM(X58:X59) -> 0 | Y57: =SUM(Y58:Y59) -> 0 | Z57: =SUM(Z58:Z59) -> 0 | AA57: =SUM(AA58:AA59) -> 0 | AB57: =SUM(AB58:AB59) -> 0 | AC57: =SUM(AC58:AC59) -> 0 | AD57: =SUM(AD58:AD59) -> 0 | AE57: =IFERROR(AF57/C57,0) -> 0 | AF57: =SUM(AF58:AF59) -> 0 | AG57: =SUM(AG58:AG59) -> 0 | AH57: =SUM(AH58:AH59) -> 0 | AI57: =SUM(AI58:AI59) -> 0 | CI57: C02_$pcode5$
A58: 楼栋 | B58: A1-A3栋 | I58: =C58+H58 -> 0 | M58: =K58*L58 -> 0 | P58: =N58*O58 -> 0 | S58: =Q58*R58 -> 0 | V58: =T58*U58 -> 0 | Y58: =W58*X58 -> 0 | AF58: =C58*AE58 -> 0 | CI58: C02_$pcode5$_1
A59: 楼栋 | B59: A4-A6栋 | I59: =C59+H59 -> 0 | M59: =K59*L59 -> 0 | P59: =N59*O59 -> 0 | S59: =Q59*R59 -> 0 | V59: =T59*U59 -> 0 | Y59: =W59*X59 -> 0 | AF59: =C59*AE59 -> 0 | CI59: C02_$pcode5$_2
A60: 业态 | B60: $pname6$ | C60: =SUM(C61:C62) -> 0 | D60: =SUM(D61:D62) -> 0 | E60: =SUM(E61:E62) -> 0 | F60: =SUM(F61:F62) -> 0 | G60: =SUM(G61:G62) -> 0 | H60: =SUM(H61:H62) -> 0 | I60: =SUM(I61:I62) -> 0 | J60: =SUM(J61:J62) -> 0 | K60: =IF(L60=0,0,M60/L60) -> 0 | L60: =SUM(L61:L62) -> 0 | M60: =SUM(M61:M62) -> 0 | N60: =IF(O60=0,0,P60/O60) -> 0 | O60: =SUM(O61:O62) -> 0 | P60: =SUM(P61:P62) -> 0 | Q60: =IF(R60=0,0,S60/R60) -> 0 | R60: =SUM(R61:R62) -> 0 | S60: =SUM(S61:S62) -> 0 | T60: =IF(U60=0,0,V60/U60) -> 0 | U60: =SUM(U61:U62) -> 0 | V60: =SUM(V61:V62) -> 0 | W60: =IF(X60=0,0,Y60/X60) -> 0 | X60: =SUM(X61:X62) -> 0 | Y60: =SUM(Y61:Y62) -> 0 | Z60: =SUM(Z61:Z62) -> 0 | AA60: =SUM(AA61:AA62) -> 0 | AB60: =SUM(AB61:AB62) -> 0 | AC60: =SUM(AC61:AC62) -> 0 | AD60: =SUM(AD61:AD62) -> 0 | AE60: =IFERROR(AF60/C60,0) -> 0 | AF60: =SUM(AF61:AF62) -> 0 | AG60: =SUM(AG61:AG62) -> 0 | AH60: =SUM(AH61:AH62) -> 0 | AI60: =SUM(AI61:AI62) -> 0 | CI60: C02_$pcode6$
A61: 楼栋 | B61: A1-A3栋 | I61: =C61+H61 -> 0 | M61: =K61*L61 -> 0 | P61: =N61*O61 -> 0 | S61: =Q61*R61 -> 0 | V61: =T61*U61 -> 0 | Y61: =W61*X61 -> 0 | AF61: =C61*AE61 -> 0 | CI61: C02_$pcode6$_1
A62: 楼栋 | B62: A4-A6栋 | I62: =C62+H62 -> 0 | M62: =K62*L62 -> 0 | P62: =N62*O62 -> 0 | S62: =Q62*R62 -> 0 | V62: =T62*U62 -> 0 | Y62: =W62*X62 -> 0 | AF62: =C62*AE62 -> 0 | CI62: C02_$pcode6$_2
A63: 业态 | B63: 幼儿园 | C63: =SUM(C64:C65) -> 0 | D63: =SUM(D64:D65) -> 0 | E63: =SUM(E64:E65) -> 0 | H63: =SUM(H64:H65) -> 0 | I63: =SUM(I64:I65) -> 0 | J63: =SUM(J64:J65) -> 0 | K63: =IF(L63=0,0,M63/L63) -> 0 | L63: =SUM(L64:L65) -> 0 | M63: =SUM(M64:M65) -> 0 | N63: =IF(O63=0,0,P63/O63) -> 0 | O63: =SUM(O64:O65) -> 0 | P63: =SUM(P64:P65) -> 0 | Q63: =IF(R63=0,0,S63/R63) -> 0 | R63: =SUM(R64:R65) -> 0 | S63: =SUM(S64:S65) -> 0 | T63: =IF(U63=0,0,V63/U63) -> 0 | U63: =SUM(U64:U65) -> 0 | V63: =SUM(V64:V65) -> 0 | W63: =IF(X63=0,0,Y63/X63) -> 0 | X63: =SUM(X64:X65) -> 0 | Y63: =SUM(Y64:Y65) -> 0 | Z63: =SUM(Z64:Z65) -> 0 | AA63: =SUM(AA64:AA65) -> 0 | AB63: =SUM(AB64:AB65) -> 0 | AC63: =SUM(AC64:AC65) -> 0 | AD63: =SUM(AD64:AD65) -> 0 | AE63: =IFERROR(AF63/C63,0) -> 0 | AF63: =SUM(AF64:AF65) -> 0 | AG63: =SUM(AG64:AG65) -> 0 | AH63: =SUM(AH64:AH65) -> 0 | AI63: =SUM(AI64:AI65) -> 0 | CI63: C02_33
A64: 楼栋 | B64: A1-A3栋 | I64: =C64+H64 -> 0 | M64: =K64*L64 -> 0 | P64: =N64*O64 -> 0 | S64: =Q64*R64 -> 0 | V64: =T64*U64 -> 0 | Y64: =W64*X64 -> 0 | AF64: =C64*AE64 -> 0 | CI64: C02_33_1
A65: 楼栋 | B65: A4-A6栋 | I65: =C65+H65 -> 0 | M65: =K65*L65 -> 0 | P65: =N65*O65 -> 0 | S65: =Q65*R65 -> 0 | V65: =T65*U65 -> 0 | Y65: =W65*X65 -> 0 | AF65: =C65*AE65 -> 0 | CI65: C02_33_2
A66: 业态 | B66: 其他公共配套 | C66: =SUM(C67:C68) -> 815 | D66: =SUM(D67:D68) -> 370 | E66: =SUM(E67:E68) -> 0 | I66: =SUM(I67:I68) -> 815 | J66: =SUM(J67:J68) -> 1 | K66: =IF(L66=0,0,M66/L66) -> 0 | L66: =SUM(L67:L68) -> 0 | M66: =SUM(M67:M68) -> 0 | N66: =IF(O66=0,0,P66/O66) -> 0 | O66: =SUM(O67:O68) -> 0 | P66: =SUM(P67:P68) -> 0 | Q66: =IF(R66=0,0,S66/R66) -> 0 | R66: =SUM(R67:R68) -> 0 | S66: =SUM(S67:S68) -> 0 | T66: =IF(U66=0,0,V66/U66) -> 0 | U66: =SUM(U67:U68) -> 0 | V66: =SUM(V67:V68) -> 0 | W66: =IF(X66=0,0,Y66/X66) -> 0 | X66: =SUM(X67:X68) -> 0 | Y66: =SUM(Y67:Y68) -> 0 | Z66: =SUM(Z67:Z68) -> 0 | AA66: =SUM(AA67:AA68) -> 2 | AB66: =SUM(AB67:AB68) -> 0 | AC66: =SUM(AC67:AC68) -> 1 | AD66: =SUM(AD67:AD68) -> 0 | AE66: =IFERROR(AF66/C66,0) -> 1.4 | AF66: =SUM(AF67:AF68) -> 1141 | AG66: =SUM(AG67:AG68) -> 1 | AH66: =SUM(AH67:AH68) -> 0 | AI66: =SUM(AI67:AI68) -> 0 | CI66: C02_36
A67: 楼栋 | B67: 物业及其他配套 | C67: =总指标!E15+SUM(总指标!K9:K12) -> 815 | D67: =总指标!E15 -> 370 | E67: 0 | I67: =C67+H67 -> 815 | J67: 1 | M67: =K67*L67 -> 0 | P67: =N67*O67 -> 0 | S67: =Q67*R67 -> 0 | V67: =T67*U67 -> 0 | Y67: =W67*X67 -> 0 | AA67: 2 | AC67: 1 | AE67: 1.4 | AF67: =C67*AE67 -> 1141 | AG67: 1 | CI67: C02_36_1
A68: 楼栋 | I68: =C68+H68 -> 0 | M68: =K68*L68 -> 0 | P68: =N68*O68 -> 0 | S68: =Q68*R68 -> 0 | V68: =T68*U68 -> 0 | Y68: =W68*X68 -> 0 | AF68: =C68*AE68 -> 0 | CI68: C02_36_2
B69: 合计 | C69: =C66+C63+C60+C57+C54+C51+C48+C45+C42+C39+C36+C32 -> 74626.755 | D69: =D66+D63+D60+D57+D54+D51+D48+D45+D42+D39+D36+D32 -> 46561.065 | E69: =E66+E63+E60+E57+E54+E51+E48+E45+E42+E39+E36+E32 -> 46191.065 | F69: =F60+F57+F54+F51+F48+F45+F42+F39+F36 -> 46191.065 | G69: =G60+G57+G54+G51+G48+G45+G42+G39+G36+G32 -> 46191.065 | H69: =H63+H60+H57+H54+H51+H48+H45+H42+H39+H36+H32 -> 0 | I69: =I66+I63+I60+I57+I54+I51+I48+I45+I42+I39+I36+I32 -> 74626.755 | J69: =J66+J63+J60+J57+J54+J51+J48+J45+J42+J39+J36+J32 -> 16 | L69: =L66+L63+L60+L57+L54+L51+L48+L45+L42+L39+L36+L32 -> 135 | M69: =M66+M63+M60+M57+M54+M51+M48+M45+M42+M39+M36+M32 -> 2095.2 | O69: =O66+O63+O60+O57+O54+O51+O48+O45+O42+O39+O36+O32 -> 15 | P69: =P66+P63+P60+P57+P54+P51+P48+P45+P42+P39+P36+P32 -> 825 | R69: =R66+R63+R60+R57+R54+R51+R48+R45+R42+R39+R36+R32 -> 0 | S69: =S66+S63+S60+S57+S54+S51+S48+S45+S42+S39+S36+S32 -> 0 | U69: =U66+U63+U60+U57+U54+U51+U48+U45+U42+U39+U36+U32 -> 15 | V69: =V66+V63+V60+V57+V54+V51+V48+V45+V42+V39+V36+V32 -> 900 | X69: =X66+X63+X60+X57+X54+X51+X48+X45+X42+X39+X36+X32 -> 15 | Y69: =Y66+Y63+Y60+Y57+Y54+Y51+Y48+Y45+Y42+Y39+Y36+Y32 -> 1125 | Z69: =Z66+Z63+Z60+Z57+Z54+Z51+Z48+Z45+Z42+Z39+Z36+Z32 -> 4318.77 | AA69: =AA66+AA63+AA60+AA57+AA54+AA51+AA48+AA45+AA42+AA39+AA36+AA32 -> 212 | AC69: =AC66+AC63+AC60+AC57+AC54+AC51+AC48+AC45+AC42+AC39+AC36+AC32 -> 301 | AD69: =AD66+AD63+AD60+AD57+AD54+AD51+AD48+AD45+AD42+AD39+AD36+AD32 -> 900 | AE69: =IFERROR(AF69/(C69-C32),0) -> 1.2030933 | AF69: =AF66+AF63+AF60+AF57+AF54+AF51+AF48+AF45+AF42+AF39+AF36+AF32 -> 63396.802 | AG69: =AG66+AG63+AG60+AG57+AG54+AG51+AG48+AG45+AG42+AG39+AG36+AG32 -> 9 | AH69: =AH66+AH63+AH60+AH57+AH54+AH51+AH48+AH45+AH42+AH39+AH36+AH32 -> 0 | AI69: =AI66+AI63+AI60+AI57+AI54+AI51+AI48+AI45+AI42+AI39+AI36+AI32 -> 522.5 | AJ69: =AJ66+AJ63+AJ60+AJ57+AJ54+AJ51+AJ48+AJ45+AJ42+AJ39+AJ36+AJ32 -> 156.75 | AK69: =AK66+AK63+AK60+AK57+AK54+AK51+AK48+AK45+AK42+AK39+AK36+AK32 -> 2 | CI69: C0299990
A70: 2、商业 | CI70: C0200068
A71: 分类 | B71: 业态/楼栋 | C71: 建筑面积 （业态） （㎡） | D71: 地上建筑面积 （业态） （㎡） | E71: 地下建筑面积 （业态） （㎡） | F71: 建筑高度_x000D_ （m） | G71: 结构高度_x000D_ （m） | H71: 可租赁面积_x000D_ （㎡） | I71: 得铺率 | J71: 小铺率 | K71: 主力店占比 | L71: 商场租赁展示区面积 （㎡） | M71: 写字楼租赁展示区面积 （㎡） | N71: 避难区面积_x000D_ （㎡） | O71: 实用率 | P71: 通风量_x000D_ （次/h） | Q71: 综合用电指标 含空调 （VA/㎡） | R71: 供冷指标_x000D_ （w/㎡） | S71: 总楼层_x000D_ 数量_x000D_ （层） | T71: 标准层_x000D_ 数量_x000D_ （层） | U71: 标准层_x000D_ 净高_x000D_ （m） | V71: 标准层_x000D_ 层高_x000D_ （m） | W71: 标准层_x000D_ 建筑面积_x000D_ （㎡） | X71: 首层大堂_x000D_ 面积_x000D_ （㎡） | Y71: 首层大_x000D_ 堂数量_x000D_ （个） | Z71: 其他大堂_x000D_ 面积_x000D_ （㎡） | AA71: 其他大堂_x000D_ 数量_x000D_ （个） | AB71: 大堂 总数量 （个） | AC71: 大堂_x000D_ 总面积_x000D_ （㎡） | AD71: 公共区域_x000D_ 精装修面积_x000D_ （㎡） | AE71: 电梯厅_x000D_ 装修面积_x000D_ （㎡） | AF71: 走道_x000D_ 装修面积 _x000D_ （㎡） | AG71: 卫生间、饮水间装修面积 （㎡） | AH71: 茶水间、清洁间装修面积_x000D_ （㎡） | AI71: 宴会厅_x000D_ 装修面积_x000D_ （㎡） | AJ71: 餐厅_x000D_ 装修面积_x000D_ （㎡） | AK71: 会议室_x000D_ 装修面积_x000D_ （㎡） | AL71: 健身房_x000D_ 装修面积_x000D_ （㎡） | AM71: 游泳池 装修面积 （㎡） | AN71: SPA及棋牌室_x000D_ 装修面积_x000D_ （㎡） | AO71: 厨房装修面积 （㎡） | AP71: 精装区域面积_x000D_ （㎡） | AQ71: 后勤区域_x000D_ 面积_x000D_ （㎡） | AR71: 货梯或VIP电梯厅总面积_x000D_ （㎡） | AS71: 避难层_x000D_ 总面积_x000D_ （㎡） | AT71: 避难层个数_x000D_ （层） | AU71: 非精装区域面积_x000D_ （㎡） | AV71: 电梯总数_x000D_ （部） | AW71: 直梯竖向分区_x000D_ （个） | AX71: 直梯数量 （部） | AY71: 扶梯数量 （部） | AZ71: 自动坡道数量（部） | BA71: 直梯轿厢二次装饰数量 （部） | BB71: 扶梯、自动坡道装饰总数 （部） | BC71: 单层出租区或商铺面积_x000D_ （㎡） | BD71: 出租区或商铺总面积_x000D_ （㎡） | BE71: 冰场面积_x000D_ （㎡） | BF71: 电影院面积_x000D_ （㎡） | BG71: OZ面积_x000D_ （㎡） | BH71: 商务中心面积_x000D_ （㎡） | BI71: 商务休闲区面积_x000D_ （㎡） | BJ71: 多功能培训室面积_x000D_ （㎡） | BK71: 会议中心（楼层）面积_x000D_ （㎡） | BL71: 专项工程_x000D_ 总面积_x000D_ （㎡） | BM71: 大床房_x000D_ 面积_x000D_ （㎡/间） | BN71: 大床房 数量 （间） | BO71: 双床房_x000D_ 面积_x000D_ （㎡/间） | BP71: 双床房_x000D_ 数量_x000D_ （间） | BQ71: 家庭房_x000D_ 面积_x000D_ （㎡/间） | BR71: 家庭_x000D_ 房数量_x000D_ （间） | BS71: 总统套房 面积 （㎡/间） | BT71: 总统套房 数量 （间） | BU71: 客房总数（间） | BV71: 酒店客房精装区域面积_x000D_ （㎡） | BW71: 玻璃幕墙_x000D_ 面积_x000D_ （㎡） | BX71: 外墙石材幕墙面积_x000D_ （㎡） | BY71: 外墙金属板幕墙面积_x000D_ （㎡） | BZ71: 下沉广场幕墙面积_x000D_ （㎡） | CA71: 其他幕墙体系面积_x000D_ （㎡） | CB71: 幕墙总面积_x000D_ （㎡） | CC71: 墙积比 | CD71: 车位数 | CE71: 充电桩_x000D_ 快充 | CF71: 充电桩_x000D_ 慢充 | CG71: 充电桩数量 | CH71: 停车场出入口数量 | CI71: C0200069
A72: 业态 | B72: 地库及机房(商业) | C72: =SUM(C73:C74) -> 0 | E72: =SUM(E73:E74) -> 0 | F72: =SUM(F73:F74) -> 0 | G72: =SUM(G73:G74) -> 0 | Q72: =IFERROR(SUMPRODUCT(Q73:Q74,$C73:$C74)/$C72,0) -> 0 | S72: =SUM(S73:S74) -> 0 | AO72: =SUM(AO73:AO74) -> 0 | AP72: =SUM(AP73:AP74) -> 0 | AQ72: =SUM(AQ73:AQ74) -> 0 | AU72: =SUM(AU73:AU74) -> 0 | CD72: =SUM(CD73:CD74) -> 0 | CE72: =SUM(CE73:CE74) -> 0 | CF72: =SUM(CF73:CF74) -> 0 | CG72: =SUM(CG73:CG74) -> 0 | CH72: =SUM(CH73:CH74) -> 0 | CI72: C02_20012
A73: 楼栋 | B73: 地库及机房 | C73: =D73+E73 -> 0 | AP73: =SUM(AD73:AO73) -> 0 | AU73: =SUM(AQ73) -> 0 | CG73: =SUM(CE73:CF73) -> 0 | CI73: C02_20012_1
A74: 楼栋 | C74: =D74+E74 -> 0 | AP74: =SUM(AD74:AO74) -> 0 | AU74: =SUM(AQ74) -> 0 | CG74: =SUM(CE74:CF74) -> 0 | CI74: C02_20012_2
A75: 业态 | B75: $pnames01$集中商业 | C75: =SUM(C76:C77) -> 0 | D75: =SUM(D76:D77) -> 0 | E75: =SUM(E76:E77) -> 0 | F75: =SUM(F76:F77) -> 0 | G75: =SUM(G76:G77) -> 0 | H75: =SUM(H76:H77) -> 0 | I75: =IFERROR(H75/C75,0) -> 0 | J75: =SUM(J76:J77) -> 0 | K75: =IFERROR(SUMPRODUCT(K76:K77,C76:C77)/C75,0) -> 0 | L75: =SUM(L76:L77) -> 0 | Q75: =IFERROR(SUMPRODUCT(Q76:Q77,$C76:$C77)/$C75,0) -> 0 | R75: =IFERROR(SUMPRODUCT(R76:R77,$C76:$C77)/$C75,0) -> 0 | S75: =SUM(S76:S77) -> 0 | T75: =SUM(T76:T77) -> 0 | W75: =SUM(W76:W77) -> 0 | AD75: =SUM(AD76:AD77) -> 0 | AG75: =SUM(AG76:AG77) -> 0 | AO75: =SUM(AO76:AO77) -> 0 | AP75: =SUM(AP76:AP77) -> 0 | AQ75: =SUM(AQ76:AQ77) -> 0 | AU75: =SUM(AU76:AU77) -> 0 | AV75: =SUM(AV76:AV77) -> 0 | AW75: =SUM(AW76:AW77) -> 0 | AX75: =SUM(AX76:AX77) -> 0 | AY75: =SUM(AY76:AY77) -> 0 | AZ75: =SUM(AZ76:AZ77) -> 0 | BA75: =SUM(BA76:BA77) -> 0 | BB75: =SUM(BB76:BB77) -> 0 | ... BF75: =SUM(BF76:BF77) -> 0 | BL75: =SUM(BL76:BL77) -> 0 | BW75: =SUM(BW76:BW77) -> 0 | BX75: =SUM(BX76:BX77) -> 0 | BY75: =SUM(BY76:BY77) -> 0 | BZ75: =SUM(BZ76:BZ77) -> 0 | CA75: =SUM(CA76:CA77) -> 0 | CB75: =SUM(CB76:CB77) -> 0 | CC75: =IFERROR(CB75/D75,0) -> 0 | CI75: C02_$pcodes01$
A76: 楼栋 | B76: 集中商业 | C76: =D76+E76 -> 0 | I76: =IFERROR(H76/C76,0) -> 0 | AP76: =SUM(AD76:AO76) -> 0 | AU76: =SUM(AQ76) -> 0 | AV76: =SUM(AX76:AZ76) -> 0 | BL76: =SUM(BE76:BK76) -> 0 | CB76: =SUM(BW76:CA76) -> 0 | CC76: =IFERROR(CB76/D76,0) -> 0 | CI76: C02_$pcodes01$_1
A77: 楼栋 | C77: =D77+E77 -> 0 | I77: =IFERROR(H77/C77,0) -> 0 | AP77: =SUM(AD77:AO77) -> 0 | AU77: =SUM(AQ77) -> 0 | AV77: =SUM(AX77:AZ77) -> 0 | BL77: =SUM(BE77:BK77) -> 0 | CB77: =SUM(BW77:CA77) -> 0 | CC77: =IFERROR(CB77/D77,0) -> 0 | CI77: C02_$pcodes01$_2
A78: 业态 | B78: $pnamex01$写字楼 | C78: =SUM(C79:C80) -> 0 | D78: =SUM(D79:D80) -> 0 | F78: =SUM(F79:F80) -> 0 | G78: =SUM(G79:G80) -> 0 | H78: =SUM(H79:H80) -> 0 | M78: =SUM(M79:M80) -> 0 | N78: =SUM(N79:N80) -> 0 | O78: =IFERROR(H78/(C78-N78),0) -> 0 | P78: =SUM(P79:P80) -> 0 | Q78: =IFERROR(SUMPRODUCT(Q79:Q80,$C79:$C80)/$C78,0) -> 0 | R78: =IFERROR(SUMPRODUCT(R79:R80,$C79:$C80)/$C78,0) -> 0 | S78: =SUM(S79:S80) -> 0 | T78: =SUM(T79:T80) -> 0 | U78: =SUM(U79:U80) -> 0 | V78: =SUM(V79:V80) -> 0 | W78: =SUM(W79:W80) -> 0 | X78: =SUM(X79:X80) -> 0 | Y78: =SUM(Y79:Y80) -> 0 | Z78: =SUM(Z79:Z80) -> 0 | ... AC78: =SUM(AC79:AC80) -> 0 | AE78: =SUM(AE79:AE80) -> 0 | AF78: =SUM(AF79:AF80) -> 0 | AG78: =SUM(AG79:AG80) -> 0 | AH78: =SUM(AH79:AH80) -> 0 | AO78: =SUM(AO79:AO80) -> 0 | AP78: =SUM(AP79:AP80) -> 0 | AQ78: =SUM(AQ79:AQ80) -> 0 | AR78: =SUM(AR79:AR80) -> 0 | AS78: =SUM(AS79:AS80) -> 0 | AT78: =SUM(AT79:AT80) -> 0 | AU78: =SUM(AU79:AU80) -> 0 | AV78: =SUM(AV79:AV80) -> 0 | ... AX78: =SUM(AX79:AX80) -> 0 | BA78: =SUM(BA79:BA80) -> 0 | BC78: =SUM(BC79:BC80) -> 0 | BD78: =SUM(BD79:BD80) -> 0 | BG78: =SUM(BG79:BG80) -> 0 | BH78: =SUM(BH79:BH80) -> 0 | BI78: =SUM(BI79:BI80) -> 0 | BJ78: =SUM(BJ79:BJ80) -> 0 | BK78: =SUM(BK79:BK80) -> 0 | BL78: =SUM(BL79:BL80) -> 0 | BW78: =SUM(BW79:BW80) -> 0 | BX78: =SUM(BX79:BX80) -> 0 | BY78: =SUM(BY79:BY80) -> 0 | BZ78: =SUM(BZ79:BZ80) -> 0 | CA78: =SUM(CA79:CA80) -> 0 | CB78: =SUM(CB79:CB80) -> 0 | CC78: =IFERROR(CB78/D78,0) -> 0 | CI78: C02_$pcodex01$
A79: 楼栋 | B79: 写字楼 | C79: =D79+E79 -> 0 | O79: =IFERROR(H79/(C79-N79),0) -> 0 | AB79: =Y79+AA79 -> 0 | AC79: =X79*Y79+Z79*AA79 -> 0 | AP79: =SUM(AD79:AO79) -> 0 | AU79: =SUM(AQ79:AS79) -> 0 | AV79: =SUM(AX79:AZ79) -> 0 | BL79: =SUM(BE79:BK79) -> 0 | CB79: =SUM(BW79:CA79) -> 0 | CC79: =IFERROR(CB79/D79,0) -> 0 | CI79: C02_$pcodex01$_1
A80: 楼栋 | C80: =D80+E80 -> 0 | O80: =IFERROR(H80/(C80-N80),0) -> 0 | AB80: =Y80+AA80 -> 0 | AC80: =X80*Y80+Z80*AA80 -> 0 | AP80: =SUM(AD80:AO80) -> 0 | AU80: =SUM(AQ80:AS80) -> 0 | AV80: =SUM(AX80:AZ80) -> 0 | BL80: =SUM(BE80:BK80) -> 0 | CB80: =SUM(BW80:CA80) -> 0 | CC80: =IFERROR(CB80/D80,0) -> 0 | CI80: C02_$pcodex01$_2
A81: 业态 | B81: $pnamej01$酒店 | C81: =SUM(C82:C83) -> 0 | D81: =SUM(D82:D83) -> 0 | F81: =SUM(F82:F83) -> 0 | G81: =SUM(G82:G83) -> 0 | Q81: =IFERROR(SUMPRODUCT(Q82:Q83,$C82:$C83)/$C81,0) -> 0 | R81: =IFERROR(SUMPRODUCT(R82:R83,$C82:$C83)/$C81,0) -> 0 | S81: =SUM(S82:S83) -> 0 | T81: =SUM(T82:T83) -> 0 | U81: =SUM(U82:U83) -> 0 | V81: =SUM(V82:V83) -> 0 | W81: =SUM(W82:W83) -> 0 | X81: =SUM(X82:X83) -> 0 | Y81: =SUM(Y82:Y83) -> 0 | Z81: =SUM(Z82:Z83) -> 0 | ... AC81: =SUM(AC82:AC83) -> 0 | AE81: =SUM(AE82:AE83) -> 0 | AF81: =SUM(AF82:AF83) -> 0 | AG81: =SUM(AG82:AG83) -> 0 | AH81: =SUM(AH82:AH83) -> 0 | AI81: =SUM(AI82:AI83) -> 0 | AJ81: =SUM(AJ82:AJ83) -> 0 | AK81: =SUM(AK82:AK83) -> 0 | AL81: =SUM(AL82:AL83) -> 0 | ... AX81: =SUM(AX82:AX83) -> 0 | BA81: =SUM(BA82:BA83) -> 0 | BL81: =SUM(BL82:BL83) -> 0 | BM81: =IFERROR(SUMPRODUCT(BN82:BN83,BM82:BM83)/BN81,0) -> 0 | BN81: =SUM(BN82:BN83) -> 0 | BO81: =IFERROR(SUMPRODUCT(BP82:BP83,BO82:BO83)/BP81,0) -> 0 | BP81: =SUM(BP82:BP83) -> 0 | BQ81: =IFERROR(SUMPRODUCT(BR82:BR83,BQ82:BQ83)/BR81,0) -> 0 | BR81: =SUM(BR82:BR83) -> 0 | BS81: =IFERROR(SUMPRODUCT(BT82:BT83,BS82:BS83)/BT81,0) -> 0 | BT81: =SUM(BT82:BT83) -> 0 | BU81: =SUM(BU82:BU83) -> 0 | BV81: =SUM(BV82:BV83) -> 0 | BW81: =SUM(BW82:BW83) -> 0 | BX81: =SUM(BX82:BX83) -> 0 | BY81: =SUM(BY82:BY83) -> 0 | BZ81: =SUM(BZ82:BZ83) -> 0 | CA81: =SUM(CA82:CA83) -> 0 | CB81: =SUM(CB82:CB83) -> 0 | CC81: =IFERROR(CB81/D81,0) -> 0 | CI81: C02_$pcodej01$
A82: 楼栋 | B82: 酒店 | C82: =D82+E82 -> 0 | AB82: =Y82+AA82 -> 0 | AC82: =X82*Y82+Z82*AA82 -> 0 | AP82: =SUM(AD82:AO82) -> 0 | AU82: =SUM(AQ82:AS82) -> 0 | AV82: =SUM(AX82:AZ82) -> 0 | BL82: =SUM(BE82:BK82) -> 0 | BU82: =BN82+BP82+BR82+BT82 -> 0 | BV82: =BM82*BN82+BO82*BP82+BQ82*BR82+BS82*BT82 -> 0 | CB82: =SUM(BW82:CA82) -> 0 | CC82: =IFERROR(CB82/D82,0) -> 0 | CI82: C02_$pcodej01$_1
A83: 楼栋 | C83: =D83+E83 -> 0 | AB83: =Y83+AA83 -> 0 | AC83: =X83*Y83+Z83*AA83 -> 0 | AP83: =SUM(AD83:AO83) -> 0 | AU83: =SUM(AQ83:AS83) -> 0 | AV83: =SUM(AX83:AZ83) -> 0 | BL83: =SUM(BE83:BK83) -> 0 | BU83: =BN83+BP83+BR83+BT83 -> 0 | BV83: =BM83*BN83+BO83*BP83+BQ83*BR83+BS83*BT83 -> 0 | CB83: =SUM(BW83:CA83) -> 0 | CC83: =IFERROR(CB83/D83,0) -> 0 | CI83: C02_$pcodej01$_2
A84: 业态 | B84: $pname7$商业 | C84: =SUM(C85:C86) -> 0 | D84: =SUM(D85:D86) -> 0 | E84: =SUM(E85:E86) -> 0 | F84: =SUM(F85:F86) -> 0 | G84: =SUM(G85:G86) -> 0 | H84: =SUM(H85:H86) -> 0 | I84: =IFERROR(H84/C84,0) -> 0 | J84: =SUM(J85:J86) -> 0 | K84: =IFERROR(SUMPRODUCT(K85:K86,C85:C86)/C84,0) -> 0 | L84: =SUM(L85:L86) -> 0 | O84: =IFERROR(H84/(C84-N84),0) -> 0 | P84: =SUM(P85:P86) -> 0 | Q84: =IFERROR(SUMPRODUCT(Q85:Q86,$C85:$C86)/$C84,0) -> 0 | R84: =IFERROR(SUMPRODUCT(R85:R86,$C85:$C86)/$C84,0) -> 0 | S84: =SUM(S85:S86) -> 0 | T84: =SUM(T85:T86) -> 0 | W84: =SUM(W85:W86) -> 0 | X84: =SUM(X85:X86) -> 0 | Y84: =SUM(Y85:Y86) -> 0 | Z84: =SUM(Z85:Z86) -> 0 | AA84: =SUM(AA85:AA86) -> 0 | AB84: =SUM(AB85:AB86) -> 0 | AC84: =SUM(AC85:AC86) -> 0 | AD84: =SUM(AD85:AD86) -> 0 | AG84: =SUM(AG85:AG86) -> 0 | AO84: =SUM(AO85:AO86) -> 0 | AP84: =SUM(AP85:AP86) -> 0 | AQ84: =SUM(AQ85:AQ86) -> 0 | AU84: =SUM(AU85:AU86) -> 0 | AV84: =SUM(AV85:AV86) -> 0 | AW84: =SUM(AW85:AW86) -> 0 | AX84: =SUM(AX85:AX86) -> 0 | AY84: =SUM(AY85:AY86) -> 0 | AZ84: =SUM(AZ85:AZ86) -> 0 | BA84: =SUM(BA85:BA86) -> 0 | BB84: =SUM(BB85:BB86) -> 0 | ... BF84: =SUM(BF85:BF86) -> 0 | BL84: =SUM(BL85:BL86) -> 0 | BW84: =SUM(BW85:BW86) -> 0 | BX84: =SUM(BX85:BX86) -> 0 | BY84: =SUM(BY85:BY86) -> 0 | BZ84: =SUM(BZ85:BZ86) -> 0 | CA84: =SUM(CA85:CA86) -> 0 | CB84: =SUM(CB85:CB86) -> 0 | CC84: =IFERROR(CB84/D84,0) -> 0 | CI84: C02_$pcode7$
A85: 楼栋 | C85: =D85+E85 -> 0 | I85: =IFERROR(H85/C85,0) -> 0 | O85: =IFERROR(H85/(C85-N85),0) -> 0 | AB85: =Y85+AA85 -> 0 | AC85: =X85*Y85+Z85*AA85 -> 0 | AP85: =SUM(AD85:AO85) -> 0 | AU85: =SUM(AQ85:AS85) -> 0 | AV85: =SUM(AX85:AZ85) -> 0 | BL85: =SUM(BE85:BK85) -> 0 | CB85: =SUM(BW85:CA85) -> 0 | CC85: =IFERROR(CB85/D85,0) -> 0 | CI85: C02_$pcode7$_1
A86: 楼栋 | C86: =D86+E86 -> 0 | I86: =IFERROR(H86/C86,0) -> 0 | O86: =IFERROR(H86/(C86-N86),0) -> 0 | AB86: =Y86+AA86 -> 0 | AC86: =X86*Y86+Z86*AA86 -> 0 | AP86: =SUM(AD86:AO86) -> 0 | AU86: =SUM(AQ86:AS86) -> 0 | AV86: =SUM(AX86:AZ86) -> 0 | BL86: =SUM(BE86:BK86) -> 0 | CB86: =SUM(BW86:CA86) -> 0 | CC86: =IFERROR(CB86/D86,0) -> 0 | CI86: C02_$pcode7$_2
A87: 业态 | B87: $pname8$写字楼 | C87: =SUM(C88:C89) -> 0 | D87: =SUM(D88:D89) -> 0 | F87: =SUM(F88:F89) -> 0 | G87: =SUM(G88:G89) -> 0 | H87: =SUM(H88:H89) -> 0 | I87: =IFERROR(H87/C87,0) -> 0 | M87: =SUM(M88:M89) -> 0 | N87: =SUM(N88:N89) -> 0 | O87: =IFERROR(H87/(C87-N87),0) -> 0 | P87: =SUM(P88:P89) -> 0 | Q87: =IFERROR(SUMPRODUCT(Q88:Q89,$C88:$C89)/$C87,0) -> 0 | R87: =IFERROR(SUMPRODUCT(R88:R89,$C88:$C89)/$C87,0) -> 0 | S87: =SUM(S88:S89) -> 0 | T87: =SUM(T88:T89) -> 0 | U87: =SUM(U88:U89) -> 0 | V87: =SUM(V88:V89) -> 0 | W87: =SUM(W88:W89) -> 0 | X87: =SUM(X88:X89) -> 0 | Y87: =SUM(Y88:Y89) -> 0 | Z87: =SUM(Z88:Z89) -> 0 | ... AC87: =SUM(AC88:AC89) -> 0 | AE87: =SUM(AE88:AE89) -> 0 | AF87: =SUM(AF88:AF89) -> 0 | AG87: =SUM(AG88:AG89) -> 0 | AH87: =SUM(AH88:AH89) -> 0 | AO87: =SUM(AO88:AO89) -> 0 | AP87: =SUM(AP88:AP89) -> 0 | AQ87: =SUM(AQ88:AQ89) -> 0 | AR87: =SUM(AR88:AR89) -> 0 | AS87: =SUM(AS88:AS89) -> 0 | AT87: =SUM(AT88:AT89) -> 0 | AU87: =SUM(AU88:AU89) -> 0 | AV87: =SUM(AV88:AV89) -> 0 | ... AX87: =SUM(AX88:AX89) -> 0 | BA87: =SUM(BA88:BA89) -> 0 | BC87: =SUM(BC88:BC89) -> 0 | BD87: =SUM(BD88:BD89) -> 0 | BG87: =SUM(BG88:BG89) -> 0 | BH87: =SUM(BH88:BH89) -> 0 | BI87: =SUM(BI88:BI89) -> 0 | BJ87: =SUM(BJ88:BJ89) -> 0 | BK87: =SUM(BK88:BK89) -> 0 | BL87: =SUM(BL88:BL89) -> 0 | BW87: =SUM(BW88:BW89) -> 0 | BX87: =SUM(BX88:BX89) -> 0 | BY87: =SUM(BY88:BY89) -> 0 | BZ87: =SUM(BZ88:BZ89) -> 0 | CA87: =SUM(CA88:CA89) -> 0 | CB87: =SUM(CB88:CB89) -> 0 | CC87: =IFERROR(CB87/D87,0) -> 0 | CI87: C02_$pcode8$
A88: 楼栋 | C88: =D88+E88 -> 0 | I88: =IFERROR(H88/C88,0) -> 0 | O88: =IFERROR(H88/(C88-N88),0) -> 0 | AB88: =Y88+AA88 -> 0 | AC88: =X88*Y88+Z88*AA88 -> 0 | AP88: =SUM(AD88:AO88) -> 0 | AU88: =SUM(AQ88:AS88) -> 0 | AV88: =SUM(AX88:AZ88) -> 0 | BL88: =SUM(BE88:BK88) -> 0 | CB88: =SUM(BW88:CA88) -> 0 | CC88: =IFERROR(CB88/D88,0) -> 0 | CI88: C02_$pcode8$_1
A89: 楼栋 | C89: =D89+E89 -> 0 | I89: =IFERROR(H89/C89,0) -> 0 | O89: =IFERROR(H89/(C89-N89),0) -> 0 | AB89: =Y89+AA89 -> 0 | AC89: =X89*Y89+Z89*AA89 -> 0 | AP89: =SUM(AD89:AO89) -> 0 | AU89: =SUM(AQ89:AS89) -> 0 | AV89: =SUM(AX89:AZ89) -> 0 | BL89: =SUM(BE89:BK89) -> 0 | CB89: =SUM(BW89:CA89) -> 0 | CC89: =IFERROR(CB89/D89,0) -> 0 | CI89: C02_$pcode8$_2
A90: 业态 | B90: $pname9$写字楼 | C90: =SUM(C91:C92) -> 0 | D90: =SUM(D91:D92) -> 0 | F90: =SUM(F91:F92) -> 0 | G90: =SUM(G91:G92) -> 0 | H90: =SUM(H91:H92) -> 0 | I90: =IFERROR(H90/C90,0) -> 0 | M90: =SUM(M91:M92) -> 0 | N90: =SUM(N91:N92) -> 0 | O90: =IFERROR(H90/(C90-N90),0) -> 0 | P90: =SUM(P91:P92) -> 0 | Q90: =IFERROR(SUMPRODUCT(Q91:Q92,$C91:$C92)/$C90,0) -> 0 | R90: =IFERROR(SUMPRODUCT(R91:R92,$C91:$C92)/$C90,0) -> 0 | S90: =SUM(S91:S92) -> 0 | T90: =SUM(T91:T92) -> 0 | U90: =SUM(U91:U92) -> 0 | V90: =SUM(V91:V92) -> 0 | W90: =SUM(W91:W92) -> 0 | X90: =SUM(X91:X92) -> 0 | Y90: =SUM(Y91:Y92) -> 0 | Z90: =SUM(Z91:Z92) -> 0 | ... AC90: =SUM(AC91:AC92) -> 0 | AE90: =SUM(AE91:AE92) -> 0 | AF90: =SUM(AF91:AF92) -> 0 | AG90: =SUM(AG91:AG92) -> 0 | AH90: =SUM(AH91:AH92) -> 0 | AO90: =SUM(AO91:AO92) -> 0 | AP90: =SUM(AP91:AP92) -> 0 | AQ90: =SUM(AQ91:AQ92) -> 0 | AR90: =SUM(AR91:AR92) -> 0 | AS90: =SUM(AS91:AS92) -> 0 | AT90: =SUM(AT91:AT92) -> 0 | AU90: =SUM(AU91:AU92) -> 0 | AV90: =SUM(AV91:AV92) -> 0 | ... AX90: =SUM(AX91:AX92) -> 0 | BA90: =SUM(BA91:BA92) -> 0 | BC90: =SUM(BC91:BC92) -> 0 | BD90: =SUM(BD91:BD92) -> 0 | BG90: =SUM(BG91:BG92) -> 0 | BH90: =SUM(BH91:BH92) -> 0 | BI90: =SUM(BI91:BI92) -> 0 | BJ90: =SUM(BJ91:BJ92) -> 0 | BK90: =SUM(BK91:BK92) -> 0 | BL90: =SUM(BL91:BL92) -> 0 | BW90: =SUM(BW91:BW92) -> 0 | BX90: =SUM(BX91:BX92) -> 0 | BY90: =SUM(BY91:BY92) -> 0 | BZ90: =SUM(BZ91:BZ92) -> 0 | CA90: =SUM(CA91:CA92) -> 0 | CB90: =SUM(CB91:CB92) -> 0 | CC90: =IFERROR(CB90/D90,0) -> 0 | CI90: C02_$pcode9$
A91: 楼栋 | C91: =D91+E91 -> 0 | I91: =IFERROR(H91/C91,0) -> 0 | O91: =IFERROR(H91/(C91-N91),0) -> 0 | AB91: =Y91+AA91 -> 0 | AC91: =X91*Y91+Z91*AA91 -> 0 | AP91: =SUM(AD91:AO91) -> 0 | AU91: =SUM(AQ91:AS91) -> 0 | AV91: =SUM(AX91:AZ91) -> 0 | BL91: =SUM(BE91:BK91) -> 0 | CB91: =SUM(BW91:CA91) -> 0 | CC91: =IFERROR(CB91/D91,0) -> 0 | CI91: C02_$pcode9$_1
A92: 楼栋 | C92: =D92+E92 -> 0 | I92: =IFERROR(H92/C92,0) -> 0 | O92: =IFERROR(H92/(C92-N92),0) -> 0 | AB92: =Y92+AA92 -> 0 | AC92: =X92*Y92+Z92*AA92 -> 0 | AP92: =SUM(AD92:AO92) -> 0 | AU92: =SUM(AQ92:AS92) -> 0 | AV92: =SUM(AX92:AZ92) -> 0 | BL92: =SUM(BE92:BK92) -> 0 | CB92: =SUM(BW92:CA92) -> 0 | CC92: =IFERROR(CB92/D92,0) -> 0 | CI92: C02_$pcode9$_2
A93: 业态 | B93: $pname10$酒店 | C93: =SUM(C94:C95) -> 0 | D93: =SUM(D94:D95) -> 0 | F93: =SUM(F94:F95) -> 0 | G93: =SUM(G94:G95) -> 0 | Q93: =IFERROR(SUMPRODUCT(Q94:Q95,$C94:$C95)/$C93,0) -> 0 | R93: =IFERROR(SUMPRODUCT(R94:R95,$C94:$C95)/$C93,0) -> 0 | S93: =SUM(S94:S95) -> 0 | T93: =SUM(T94:T95) -> 0 | U93: =SUM(U94:U95) -> 0 | V93: =SUM(V94:V95) -> 0 | W93: =SUM(W94:W95) -> 0 | X93: =SUM(X94:X95) -> 0 | Y93: =SUM(Y94:Y95) -> 0 | Z93: =SUM(Z94:Z95) -> 0 | ... AC93: =SUM(AC94:AC95) -> 0 | AE93: =SUM(AE94:AE95) -> 0 | AF93: =SUM(AF94:AF95) -> 0 | AG93: =SUM(AG94:AG95) -> 0 | AH93: =SUM(AH94:AH95) -> 0 | AI93: =SUM(AI94:AI95) -> 0 | AJ93: =SUM(AJ94:AJ95) -> 0 | AK93: =SUM(AK94:AK95) -> 0 | AL93: =SUM(AL94:AL95) -> 0 | ... AX93: =SUM(AX94:AX95) -> 0 | BA93: =SUM(BA94:BA95) -> 0 | BL93: =SUM(BL94:BL95) -> 0 | BM93: =SUM(BM94:BM95) -> 0 | BN93: =SUM(BN94:BN95) -> 0 | BO93: =SUM(BO94:BO95) -> 0 | BP93: =SUM(BP94:BP95) -> 0 | BQ93: =SUM(BQ94:BQ95) -> 0 | BR93: =SUM(BR94:BR95) -> 0 | BS93: =SUM(BS94:BS95) -> 0 | ... CB93: =SUM(CB94:CB95) -> 0 | CC93: =IFERROR(CB93/D93,0) -> 0 | CI93: C02_$pcode10$
A94: 楼栋 | C94: =D94+E94 -> 0 | AB94: =Y94+AA94 -> 0 | AC94: =X94*Y94+Z94*AA94 -> 0 | AP94: =SUM(AD94:AO94) -> 0 | AU94: =SUM(AQ94:AS94) -> 0 | AV94: =SUM(AX94:AZ94) -> 0 | BL94: =SUM(BE94:BK94) -> 0 | BU94: =BN94+BP94+BR94+BT94 -> 0 | BV94: =BM94*BN94+BO94*BP94+BQ94*BR94+BS94*BT94 -> 0 | CB94: =SUM(BW94:CA94) -> 0 | CC94: =IFERROR(CB94/D94,0) -> 0 | CI94: C02_$pcode10$_1
A95: 楼栋 | C95: =D95+E95 -> 0 | AB95: =Y95+AA95 -> 0 | AC95: =X95*Y95+Z95*AA95 -> 0 | AP95: =SUM(AD95:AO95) -> 0 | AU95: =SUM(AQ95:AS95) -> 0 | AV95: =SUM(AX95:AZ95) -> 0 | BL95: =SUM(BE95:BK95) -> 0 | BU95: =BN95+BP95+BR95+BT95 -> 0 | BV95: =BM95*BN95+BO95*BP95+BQ95*BR95+BS95*BT95 -> 0 | CB95: =SUM(BW95:CA95) -> 0 | CC95: =IFERROR(CB95/D95,0) -> 0 | CI95: C02_$pcode10$_2
B96: 小计 | C96: =C72+C75+C78+C81+C84+C87+C93+C90 -> 0 | D96: =D72+D75+D78+D81+D84+D87+D93+D90 -> 0 | E96: =E72+E75+E78+E81+E84+E87+E93+E90 -> 0 | H96: =H72+H75+H78+H81+H84+H87+H93+H90 -> 0 | I96: =IFERROR(H96/C96,0) -> 0 | J96: =J72+J75+J78+J81+J84+J87+J93+J90 -> 0 | L96: =L72+L75+L78+L81+L84+L87+L93+L90 -> 0 | M96: =M72+M75+M78+M81+M84+M87+M93+M90 -> 0 | N96: =N72+N75+N78+N81+N84+N87+N93+N90 -> 0 | O96: =IFERROR(H96/(C96-N96),0) -> 0 | P96: =P72+P75+P78+P81+P84+P87+P93+P90 -> 0 | S96: =S72+S75+S78+S81+S84+S87+S93+S90 -> 0 | T96: =T72+T75+T78+T81+T84+T87+T93+T90 -> 0 | U96: =U72+U75+U78+U81+U84+U87+U93+U90 -> 0 | V96: =V72+V75+V78+V81+V84+V87+V93+V90 -> 0 | W96: =W72+W75+W78+W81+W84+W87+W93+W90 -> 0 | X96: =X72+X75+X78+X81+X84+X87+X93+X90 -> 0 | Y96: =Y72+Y75+Y78+Y81+Y84+Y87+Y93+Y90 -> 0 | Z96: =Z72+Z75+Z78+Z81+Z84+Z87+Z93+Z90 -> 0 | ... CB96: =CB72+CB75+CB78+CB81+CB84+CB87+CB93+CB90 -> 0 | CC96: =IFERROR(CB96/D96,0) -> 0 | CD96: =CD72+CD75+CD78+CD81+CD84+CD87+CD93+CD90 -> 0 | CE96: =CE72+CE75+CE78+CE81+CE84+CE87+CE93+CE90 -> 0 | CF96: =CF72+CF75+CF78+CF81+CF84+CF87+CF93+CF90 -> 0 | CG96: =CG72+CG75+CG78+CG81+CG84+CG87+CG93+CG90 -> 0 | CH96: =CH72+CH75+CH78+CH81+CH84+CH87+CH93+CH90 -> 0 | CI96: C0299991

Sheet 03 成本测算（输入）
A1: 成本科目 | B1: 填写信息 | C1: 单位 | D1: 数值 | E1: 配置要求 | F1: 档次/品牌要求 | G1: 设计参考值 | H1: 标准刻度 | I1: 备注说明 | K1: C030001_title
A2: 大宗材料基价 | E2: 测算单价指各业态综合单价 | K2: C030002_1_title
A3: 钢筋 | B3: 主材基价 | C3: 元/kg | E3: 参照20XX年X月螺纹钢（Φ16-25mm，HRB400E）平均价格（国家统计局http://www.stats.gov.cn） | I3: 参照20XX年X月螺纹钢（Φ16-25mm，HRB400E）平均价格（国家统计局http://www.stats.gov.cn） | K3: C030002
A4: 钢板 | B4: 主材基价 | C4: 元/kg | E4: 参照20XX年X月普通中板（20mm，Q235）平均价格（国家统计局http://www.stats.gov.cn） | K4: C030004_1
A5: 混凝土 | B5: 主材基价 | C5: 元/m3 | E5: 参照20XX年X月XX市含泵送C30信息价 | I5: 参照20XX年X月XX市含泵送C30信息价 | K5: C030003
A6: 平板玻璃 | B6: 主材基价 | C6: 元/㎡ | E6: 参照20XX年X月浮法平板玻璃（4.8/5mm）平均价格（国家统计局http://www.stats.gov.cn） | K6: C030006_1
A7: 铝材 | B7: 主材基价 | C7: 元/kg | E7: 参照20XX年X月铝锭（A00）平均价格（国家统计局http://www.stats.gov.cn） | K7: C030007
A8: 铜 | B8: 主材基价 | C8: 元/kg | E8: 参照20XX年X月电解铜（1#）平均价格（国家统计局http://www.stats.gov.cn） | K8: C030008
A9: 单体工程-住宅类 | K9: C030009_title
A10: 主要材料 | K10: C030010_title
A11: 钢筋工程 | B11: 主材单价 | C11: 元/kg | D11: 3.36 | E11: 2025年11月7日苏州市HRB400信息价 | K11: C030011
A12: 混凝土工程 | B12: 主材单价 | C12: 元/m3 | D12: =0.9*387.86+18 -> 367.074 | E12: 2025年10月苏州市泵送C30信息价*0.9+18泵送费 | K12: C030012
A13: 地下室其他(住宅) | K13: C03_21_title
A14: 钢筋工程 | B14: 含量 | C14: kg/m2 | D14: =含量测算!O15 -> 117.94887 | E14: 刻度项目为高层，本项目类似姑苏第小高项目，体量偏小，参考姑苏第项目修正 | H14: 115.544 | I14: 参考竹园路项目，层高3.7m | K14: C03_21_1
A15: 混凝土工程 | B15: 含量 | C15: m3/m2 | D15: =含量测算!O32 -> 1.224269 | E15: 刻度项目为高层，本项目类似姑苏第小高项目，体量偏小，参考姑苏第项目修正 | H15: 1.03 | I15: 参考竹园路项目，层高3.7m | K15: C03_21_2
A16: 土建改造（如有） | B16: 相对面积单方 | C16: 元/m2 | K16: C03_21_3
A17: 人防工程 | B17: 人防占比 | C17: m2/m2 | D17: =总指标!E19/总指标!E18 -> 0.081002484 | H17: 0.2482 | K17: C03_21_4
A18: 充电桩（如有） | B18: 充电桩数量 | C18: 个 | D18: ='02 项目基础信息（输入）'!AJ32 -> 156.75 | E18: 充电桩安装 30% | H18: 711 | I18: （快慢充比例） | K18: C03_21_5
A19: 停车场管理系统 | B19: 出入口数量 | C19: 个 | D19: ='02 项目基础信息（输入）'!AK32 -> 2 | E19: （类型：） | H19: 2 | I19: （类型：） | K19: C03_21_6
A20: 机械停车（如有） | B20: 数量 | C20: 个 | D20: 0 | H20: 0 | K20: C03_21_7
A21: 其他单体工程（如有） | B21: 相对面积单方 | C21: 元/m2 | D21: =15+(800000*2+750*3000+3000*190)/'02 项目基础信息（输入）'!C32 -> 216.53274 | E21: 1、地下室无线信号覆盖；收费标准15元/m2； 2、车库坡道顶盖及坡道装饰按照2个考虑，80万元/个； 4、地库车道吊顶为铝板+灯带+柱面装修；装修单方750 元/m2，扣除车马厅部分，面积3000m2。地面彩石地坪计入地下地坪工程。 5、会所中央车站，单方3000 元/m2；面积 190m2； | H21: 15 | I21: 地下室无线信号覆盖；收费标准15元/m2 | K21: C03_21_8
A22: 普通多层 | K22: C03_12_title
A23: 预制构件影响 | B23: 相对面积单方 | C23: 元/m2 | D23: 0 | E23: 装配面积比例：XX%；PC构件占比：XX%；ALC占比：XX% | K23: C03_12_1
A24: 外墙保温工程 | B24: 保温墙积比 | C24: m2/m2 | D24: 0 | E24: ①大墙面保温材料类型1：( )；②厚度( ) | K24: C03_12_2
B25: 综合单价 | C25: 元/m2 | D25: 0 | E25: ①大墙面保温材料类型2：( )；②厚度( ) | K25: C03_12_3
A26: 土建改造（如有） | B26: 相对面积单方 | C26: 元/m2 | D26: 0 | E26: （改造部位、大致工作量等） | K26: C03_12_4
A27: 太阳能热水器 | B27: 综合单价 | C27: 元/户 | D27: 0 | E27: ①品牌：( ) ；②型号：( ) | K27: C03_12_5
A28: 其他单体工程（如有） | B28: 相对面积单方 | C28: 元/m2 | D28: 0 | E28: （具体什么内容？单方计算过程？） | K28: C03_12_6
A29: 入户门工程 | B29: 每平米户数 | C29: 户/m2 | D29: =IFERROR('02 项目基础信息（输入）'!AC39/'02 项目基础信息（输入）'!C39,0) -> 0 | K29: C03_12_7
B30: 入户门综合单价 | C30: 元/樘 | D30: 0 | E30: ①类型：(钢质门、钢木复合、铸铝门) ；②品牌：( )；③ 型号：( ) | K30: C03_12_8
B31: 入户门锁综合单价 | C31: 元/把 | D31: 0 | E31: ①类型：(电子锁、机械锁) ；②品牌：( )；③ 型号：( ) | K31: C03_12_9
A32: 外立面普通门窗工程_x000D_ （含防火窗） | B32: 窗积比 | C32: m2/m2 | D32: 0 | E32: ①普通窗类型：(塑钢、铝合金（粉末）、铝合金（氟碳）、铝合金（电泳）、铝木复合、其他（手动输入）)；②是否断桥：(是、否)；③是否系统窗：(是、否)；④普通窗玻璃：(普通、中空、中空夹胶、Low-e、中空Low-e、中空夹胶Low-e)；⑤普通窗其他配置(多选)：(纱窗、钢副框、遮阳系统、防坠落) | K32: C03_12_10
B33: 综合单价 | C33: 元/m2 | D33: 0 | E33: ①防火窗类型：(铝合金、镀锌钢、不锈钢、水晶硅、其他（手动输入）)；②是否断桥：(是、否) | K33: C03_12_11
A34: 外立面装饰工程 | B34: 墙积比 | C34: m2/m2 | D34: ='02 项目基础信息（输入）'!AE39 -> 0 | K34: C03_12_12
B35: 外墙单方造价 | C35: 元/m2 | D35: =(D36*D37+D38*D39+D40*D41+D42*D43+D44*D45)/100 -> 0 | K35: C03_12_13
B36: 外墙石材占比 | C36: % | D36: 0 | K36: C03_12_14
B37: 外墙石材综合单价 | C37: 元/m2 | D37: 0 | E37: ①种类：( )；②厚度：( )；③档次：(进口、国产) | K37: C03_12_15
B38: 外墙面砖装饰占比 | C38: % | D38: 0 | K38: C03_12_16
B39: 外墙面砖综合单价 | C39: 元/m2 | D39: 0 | E39: ①类型：(普通砖、劈开砖)；②档次：(进口、国产) | K39: C03_12_17
B40: 外墙铝板占比 | C40: % | D40: 0 | K40: C03_12_18
B41: 外墙铝板综合单价 | C41: 元/m2 | D41: 0 | E41: ①规格：( )；②厚度：( )；③档次：(进口、国产) | K41: C03_12_19
B42: 外墙普通涂料占比 | C42: % | D42: 0 | K42: C03_12_20
B43: 外墙普通涂料综合单价 | C43: 元/m2 | D43: 0 | E43: ①类型：( ) ；②品牌：( )；③ 档次：(进口、国产) | K43: C03_12_21
B44: 外墙真石漆占比 | C44: % | D44: 0 | K44: C03_12_22
B45: 外墙真石漆综合单价 | C45: 元/m2 | D45: 0 | E45: ①类型：( ) ；②品牌：( )；③ 档次：(进口、国产) | K45: C03_12_23
A46: 栏杆工程 | B46: 阳台栏杆含量 | C46: m/户 | D46: 0 | K46: C03_12_24
B47: 阳台栏杆综合单价 | C47: 元/m | D47: 0 | E47: ①类型：(锌钢、铁艺、铝合金、铝合金玻璃、不锈钢)；②其他： | K47: C03_12_25
B48: 护窗栏杆含量 | C48: m/户 | D48: 0 | K48: C03_12_26
B49: 护窗栏杆综合单价 | C49: 元/m | D49: 0 | E49: ①类型：(锌钢、铁艺、铝合金、铝合金玻璃、不锈钢)；②其他： | K49: C03_12_27
A50: 公共部位装饰工程 | B50: 大堂面积占比 | C50: m2/m2 | D50: =IFERROR('02 项目基础信息（输入）'!P39/'02 项目基础信息（输入）'!C39,0) -> 0 | E50: 数量：( )；单个面积：( ) | K50: C03_12_28
B51: 大堂装饰标准 | C51: 元/m2 | D51: 0 | E51: ①硬装标准：( )；②软装标准：( ) | K51: C03_12_29
B52: 电梯厅面积占比 | C52: m2/m2 | D52: =IFERROR('02 项目基础信息（输入）'!M39/'02 项目基础信息（输入）'!C39,0) -> 0 | E52: 数量：( )；单个面积：( ) | K52: C03_12_30
B53: 电梯厅装饰标准 | C53: 元/m2 | D53: 0 | E53: ①硬装标准：( )；②软装标准：( ) | K53: C03_12_31
B54: 标准层连廊面积占比 | C54: m2/m2 | D54: =IFERROR('02 项目基础信息（输入）'!S39/'02 项目基础信息（输入）'!C39,0) -> 0 | E54: 数量：( )；单个面积：( ) | I54: 标准层电梯厅通往入户门之间区域，非消防连廊，消防连廊一般不做装修 | K54: C03_12_32
B55: 标准层连廊装饰标准 | C55: 元/m2 | D55: 0 | E55: ①硬装标准：( )；②软装标准：( ) | K55: C03_12_33
B56: 地下大堂面积占比 | C56: m2/m2 | D56: =IFERROR('02 项目基础信息（输入）'!V39/'02 项目基础信息（输入）'!C39,0) -> 0 | E56: 数量：( )；单个面积：( ) | K56: C03_12_34
B57: 地下大堂装饰标准 | C57: 元/m2 | D57: 0 | E57: ①硬装标准：( )；②软装标准：( ) | K57: C03_12_35
B58: 车马厅面积占比 | C58: m2/m2 | D58: =IFERROR('02 项目基础信息（输入）'!Y39/'02 项目基础信息（输入）'!C39,0) -> 0 | E58: 数量：( )；单个面积：( ) | K58: C03_12_36
B59: 车马厅装饰标准 | C59: 元/m2 | D59: 0 | E59: ①硬装标准：( )；②软装标准：( ) | K59: C03_12_37
B60: 架空层面积占比 | C60: m2/m2 | D60: =IFERROR('02 项目基础信息（输入）'!Z39/'02 项目基础信息（输入）'!C39,0) -> 0 | E60: 面积：( ) | K60: C03_12_38
B61: 架空层装饰标准 | C61: 元/m2 | D61: 0 | E61: ①硬装标准：( )；②软装标准：( ) | K61: C03_12_39
B62: 其他公共部位面积占比 | C62: m2/m2 | D62: 0 | E62: 部位：( )；数量：( )；单个面积：( ) | K62: C03_12_40
B63: 其他公共部位装饰标准 | C63: 元/m2 | D63: 0 | E63: ①硬装标准：( )；②软装标准：( ) | K63: C03_12_41
A64: 安防系统 | B64: 每户标准 | C64: 元/户 | D64: 0 | K64: C03_12_42
A65: 电梯 | B65: 单台电梯服务面积 | C65: m2/台 | D65: =IFERROR('02 项目基础信息（输入）'!C39/'02 项目基础信息（输入）'!J39,0) -> 0 | K65: C03_12_43
B66: 供货单价 | C66: 元/台 | D66: 0 | E66: ①型号：( )；②载重：( )；③梯速：( )；④是否无机房：( ) | K66: C03_12_44
B67: 安装单价 | C67: 元/台 | D67: 0 | E67: ⑤层数：( )；⑥站数：( )；⑦辅助配置(多选)：(厅门装修、轿厢装修、空调、停电平层、IC卡、群控系统、信号系统)；⑧是否贯通门：( ) | K67: C03_12_45
A68: 小高层 | K68: C03_13_title
A69: 预制构件影响 | B69: 相对面积单方 | C69: 元/m2 | D69: ='PC 增量测算'!G49 -> 152.91589 | E69: 装配面积比例：100%；增加装配面积，增加1%容积率奖励 | H69: 94.5 | I69: 装配面积比例：100%；(其中45%面积做到50%，剩下面积做到30%）参考劳动路项目，层高3.0-3.1m | K69: C03_13_1
A70: 外墙保温工程 | B70: 保温墙积比 | C70: m2/m2 | D70: 0.94 | E70: ①大墙面保温材料类型1：( 35厚岩棉+35厚EPS )；②厚度( 35 ) | H70: 1.03 | I70: ①大墙面保温材料类型1：( 35厚岩棉+35厚EPS )；②厚度( 35 ) | K70: C03_13_2
B71: 综合单价 | C71: 元/m2 | D71: 90.51 | E71: ①大墙面保温材料类型2：( 大于27m采用岩棉 )；②厚度( 35 ) | H71: 90.51 | I71: ①大墙面保温材料类型2：( )；②厚度( ) | K71: C03_13_3
A72: 土建改造（如有） | B72: 相对面积单方 | C72: 元/m2 | D72: =7500*总指标!L26/'02 项目基础信息（输入）'!C42 -> 43.369452 | E72: 新建主卧阳台墙面及装饰2500一户+拆除推拉门及墙垛，壁纸以及地面装饰恢复5000一户 | K72: C03_13_4
A73: 太阳能热水器 | B73: 综合单价 | C73: 元/户 | D73: =太阳能!K39*0.6 -> 5477.6664 | E73: ①品牌：( 中科蓝天 ) ；②型号：( 承压式一体机300L )；每单元10户按照顶6户设置太阳能； 坡屋面需平板分体承压系统300L单盘管水箱+6平方米平板集热器 | H73: 2375.8 | I73: ①品牌：( 沐阳 ) ；②型号：( 承压式一体机150L ) | K73: C03_13_5
A74: 其他单体工程（如有） | B74: 相对面积单方 | C74: 元/m2 | D74: 12 | E74: 好房子：满足隔声要求增加聚氨酯隔音垫+12 | K74: C03_13_6
A75: 入户门工程 | B75: 每平米户数 | C75: 户/m2 | D75: =IFERROR('02 项目基础信息（输入）'!AC42/'02 项目基础信息（输入）'!C42,0) -> 0.0057825936 | H75: 0.0080837498 | K75: C03_13_7
B76: 入户门综合单价 | C76: 元/樘 | D76: =11431+121+800+600 -> 12952 | E76: ①类型：(超A级子母门+门槛+猫眼+拉手贝母片+安装费) ；②品牌：( 天山)；③ 型号：( 子母门 ) | H76: 4700 | I76: ①类型：(C级铸铝门+不考虑非标调差) ；②品牌：( 天山)；③ 型号：( 单扇门 ) | K76: C03_13_8
B77: 入户门锁综合单价 | C77: 元/把 | D77: 2622 | E77: ①类型：(电子锁) ；②品牌：( 飞利浦五合一马达锁)； | F77: 封窗影响单方 | H77: 1308.7 | I77: ①类型：(电子锁) ；②品牌：( 飞利浦四合一 )； | K77: C03_13_9
A78: 外立面普通门窗工程_x000D_ （含防火窗） | B78: 窗积比 | C78: m2/m2 | D78: =门窗栏杆!E11+门窗栏杆!I11 -> 0.35338393 | E78: 普通窗，阳台封窗 | F78: =门窗栏杆!E17 -> 114.4689 | H78: 0.22 | I78: ①普通窗类型：铝合金（粉末）、铝合金（氟碳）、铝合金（电泳）、铝木复合、其他（手动输入）)；②是否断桥：(是、否)；③是否系统窗：(是、否)；④普通窗玻璃：(普通、中空、中空夹胶、Low-e、中空Low-e、中空夹胶Low-e)；⑤普通窗其他配置(多选)：(纱窗、钢副框、遮阳系统、防坠落)-三玻两腔铝合金 | K78: C03_13_10
B79: 综合单价 | C79: 元/m2 | D79: =门窗栏杆!E13 -> 804.90368 | E79: 门窗采用三玻，阳台拆改部分推拉门按照塑钢综合换算（户内三玻两腔+客厅推拉门塑钢） | F79: U3+一城一策限额 | H79: 924.3 | I79: 参考劳动路定标单价水平 | K79: C03_13_11
A80: 外立面装饰工程 | B80: 墙积比 | C80: m2/m2 | D80: ='02 项目基础信息（输入）'!AE42 -> 1.2 | E80: =D81*D80 -> 814.34832 | F80: 1050 | H80: 1.52 | I80: 512.81 | K80: C03_13_12
B81: 外墙单方造价 | C81: 元/m2 | D81: =(D82*D83+D84*D85+D86*D87+D88*D89+D90*D91)/100 -> 678.6236 | F81: 本项目外立面一城一策口径单方 | H81: 337.3774 | I81: 参考项目为U3，外立面定标单方为一城一策的95%，本次刻度按照一城一策下浮（830*0.95）；789 | K81: C03_13_13
B82: 外墙石材占比 | C82: % | D82: 15 | E82: 首层及山墙干挂石材 | F82: ='05 成本测算明细'!O725+'05 成本测算明细'!O736+'05 成本测算明细'!O753+'05 成本测算明细'!O780 -> 1163.96 | H82: 1 | K82: C03_13_14
B83: 外墙石材综合单价 | C83: 元/m2 | D83: 900 | E83: ①种类：( )；②厚度：( )；③档次：(进口) | H83: 746.38 | I83: ①种类：( )；②厚度：( )；③档次：(进口、国产) | K83: C03_13_15
B84: 外墙面砖装饰占比 | C84: % | D84: 5 | E84: 部分架空层封闭玻璃幕墙 | H84: 24 | K84: C03_13_16
B85: 外墙面砖综合单价 | C85: 元/m2 | D85: 750 | E85: 架空层封闭玻璃幕墙 | H85: 211.54 | I85: ①类型：(涂料一体板)；②档次：(进口、国产) | K85: C03_13_17
B86: 外墙铝板占比 | C86: % | D86: 76 | H86: 40 | K86: C03_13_18
B87: 外墙铝板综合单价 | C87: 元/m2 | D87: 664.11 | E87: ①规格：( )；②厚度：( )；③档次：(进口、国产) | H87: 664.11 | I87: ①规格：( )；②厚度：( )；③档次：(进口、国产) | K87: C03_13_19
B88: 外墙普通涂料占比 | C88: % | D88: 4 | E88: 设备平台顶面局部涂料 | H88: 30 | K88: C03_13_20
B89: 外墙普通涂料综合单价 | C89: 元/m2 | D89: 35 | E89: ①类型：( ) ；②品牌：( )；③ 档次：(进口、国产) | H89: 35 | I89: ①类型：( ) ；②品牌：( )；③ 档次：(进口、国产) | K89: C03_13_21
B90: 外墙真石漆占比 | C90: % | D90: 0 | H90: 5 | K90: C03_13_22
B91: 外墙真石漆综合单价 | C91: 元/m2 | D91: 60 | E91: ①类型：( ) ；②品牌：( )；③ 档次：(进口、国产) | H91: 60 | I91: ①类型：( ) ；②品牌：( )；③ 档次：(进口、国产) | K91: C03_13_23
A92: 栏杆工程 | B92: 阳台栏杆含量 | C92: m/户 | D92: =门窗栏杆!X8 -> 8.5666667 | E92: 阳台为封窗，内侧设置防火玻璃栏板 | H92: 8.213 | K92: C03_13_24
B93: 阳台栏杆综合单价 | C93: 元/m | D93: =H93 -> 664.87 | E93: 防火玻璃栏板 | H93: 664.87 | I93: ①类型：(锌钢、铁艺、铝合金、铝合金玻璃、不锈钢)；②其他： | K93: C03_13_25
B94: 护窗栏杆含量 | C94: m/户 | D94: =门窗栏杆!V8 -> 1.8 | H94: 7.891 | K94: C03_13_26
B95: 护窗栏杆综合单价 | C95: 元/m | D95: 121.6 | E95: ①类型：(锌钢、铁艺、铝合金、铝合金玻璃、不锈钢)；②其他： | H95: 121.6 | I95: ①类型：(锌钢、铁艺、铝合金、铝合金玻璃、不锈钢)；②其他： | K95: C03_13_27
A96: 公共部位装饰工程 | B96: 大堂面积占比 | C96: m2/m2 | D96: =IFERROR('02 项目基础信息（输入）'!P42/'02 项目基础信息（输入）'!C42,0) -> 0.015902132 | H96: 0.015242087 | K96: C03_13_28
B97: 大堂装饰标准 | C97: 元/m2 | D97: 5000 | E97: 参考新U3+硬装3000；大堂挑高5m；单方上浮1.5倍，硬装4500，软装500 | H97: 3350 | I97: 参考项目为U3，大堂定标单方为一城一策的86%；本次刻度按照同样下浮（3500*0.86） | K97: C03_13_29
B98: 电梯厅面积占比 | C98: m2/m2 | D98: =IFERROR('02 项目基础信息（输入）'!M42/'02 项目基础信息（输入）'!C42,0) -> 0.040385634 | H98: 0.048992423 | K98: C03_13_30
B99: 电梯厅装饰标准 | C99: 元/m2 | D99: 1900 | E99: 参考新U3+硬装1900； | H99: 1380 | I99: 参考项目为U3，标厅定标单方为一城一策的93%；本次刻度按照同样下浮（1500*0.93） | K99: C03_13_31
B100: 标准层连廊面积占比 | C100: m2/m2 | D100: =IFERROR('02 项目基础信息（输入）'!S42/'02 项目基础信息（输入）'!C42,0) -> 0 | H100: 0 | I100: 数量：( )；单个面积：( ) | K100: C03_13_32
...

Sheet 04 目标成本控制表
AD1: C040001
A2: 中国海外发展有限公司 | AD2: C040002
A3: 建安成本目标控制表 | AD3: C040003
A4: 项目名称： | C4: 集团商业标准成本 | E4: 建筑面积： | F4: ='02 项目基础信息（输入）'!D4 -> 74626.755 | G4: 建造面积： | H4: ='02 项目基础信息（输入）'!D10 -> 74626.755 | I4: 可租售面积： | J4: ='02 项目基础信息（输入）'!D7+'02 项目基础信息（输入）'!K11 -> 46191.065 | L4: 可租售率： | M4: =IFERROR(J4/'02 项目基础信息（输入）'!D4,0) -> 0.61896119 | N4: 制表日期： | O4: 2024-07-15 19:18:08 | AD4: C040004
A5: 成本科目 | C5: 总价_x000D_ (万元) | D5: 技术经济指标 | J5: 成本属性分类 | Q5: 与项目标准成本刻度差异小计 | U5: 与项目标准刻度差异分析说明 | W5: 项目标准刻度（元/㎡） | AD5: C040005
D6: 相对建筑面积 | F6: 相对建造面积 | H6: 可租售面积 | J6: 总价（万元） | M6: 相对建筑面积单方（元/㎡） | Q6: 合计 | R6: 暂定 | S6: 固定 | T6: 弹性 | W6: 相对建筑面积 | X6: 相对可售面积 | Y6: 相对建筑面积单方（元/㎡） | AD6: C040006
D7: 面积_x000D_ （㎡） | E7: 单价_x000D_ （元/㎡） | F7: 面积_x000D_ （㎡） | G7: 单价_x000D_ （元/㎡） | H7: 面积_x000D_ （㎡） | I7: 单价_x000D_ （元/㎡） | J7: 暂定 | K7: 固定 | L7: 弹性 | M7: 暂定 | N7: 固定 | O7: 弹性 | R7: 小计 | S7: 小计 | T7: 小计 | W7: 单价 | X7: 单价 | Y7: 暂定 | Z7: 固定 | AA7: 弹性 | AD7: C040007
A8: 前期工程 | C8: ='05 成本测算明细'!M4 -> 325.90753 | D8: ='05 成本测算明细'!$N$4 -> 74626.755 | E8: =IF(D8=0,0,C8*10000/D8) -> 43.671675 | F8: ='05 成本测算明细'!$P$4 -> 74626.755 | G8: =IF(F8=0,0,C8*10000/F8) -> 43.671675 | H8: ='02 项目基础信息（输入）'!$E$69 -> 46191.065 | I8: =IF(H8=0,0,C8*10000/H8) -> 70.556403 | J8: =C8 -> 325.90753 | M8: =IFERROR(J8/$F$4*10000,0) -> 43.671675 | Q8: =E8-W8 -> 43.671675 | R8: =M8-Y8 -> 11.235243 | X8: 47.146668 | Y8: 32.436431 | AD8: C041008
A9: 桩基础工程 | C9: ='05 成本测算明细'!M29 -> 1599.5578 | D9: ='05 成本测算明细'!$N$29 -> 74626.755 | E9: =IF(D9=0,0,C9*10000/D9) -> 214.34107 | F9: ='05 成本测算明细'!$P$29 -> 74626.755 | G9: =IF(F9=0,0,C9*10000/F9) -> 214.34107 | H9: ='02 项目基础信息（输入）'!$E$69 -> 46191.065 | I9: =IF(H9=0,0,C9*10000/H9) -> 346.29161 | J9: =C9 -> 1599.5578 | M9: =IFERROR(J9/$F$4*10000,0) -> 214.34107 | Q9: =E9-W9 -> 214.34107 | R9: =M9-Y9 -> 90.682268 | X9: 179.73926 | Y9: 123.6588 | AD9: C042009
A10: 岩土工程 | C10: ='05 成本测算明细'!M47 -> 2510.4349 | D10: ='05 成本测算明细'!$N$47 -> 74626.755 | E10: =IF(D10=0,0,C10*10000/D10) -> 336.39878 | F10: ='05 成本测算明细'!$P$47 -> 74626.755 | G10: =IF(F10=0,0,C10*10000/F10) -> 336.39878 | H10: ='02 项目基础信息（输入）'!$E$69 -> 46191.065 | I10: =IF(H10=0,0,C10*10000/H10) -> 543.4893 | J10: =C10 -> 2510.4349 | M10: =IFERROR(J10/$F$4*10000,0) -> 336.39878 | Q10: =E10-W10 -> 336.39878 | R10: =M10-Y10 -> 149.93878 | X10: 271.02142 | Y10: 186.46 | AD10: C043010
A11: 单体工程 | B11: 小计 | C11: ='05 成本测算明细'!M93 -> 26554.992 | D11: ='05 成本测算明细'!$N$93 -> 74626.755 | E11: =IF(D11=0,0,C11*10000/D11) -> 3558.3742 | F11: ='05 成本测算明细'!$P$93 -> 74626.755 | G11: =IF(F11=0,0,C11*10000/F11) -> 3558.3742 | H11: ='02 项目基础信息（输入）'!$E$69 -> 46191.065 | I11: =IF(H11=0,0,C11*10000/H11) -> 5748.9457 | J11: =SUM(J12:J31) -> 0 | K11: =SUM(K12:K31) -> 16816.793 | L11: =SUM(L12:L31) -> 9738.1989 | N11: =IF($D11=0,0,K11/$D11*10000) -> 2253.4536 | O11: =IF($D11=0,0,L11/$D11*10000) -> 1304.9206 | AD11: C044011
B12: 地下室其他(住宅) | C12: ='05 成本测算明细'!M94 -> 6146.9459 | D12: ='05 成本测算明细'!N94 -> 21931.92 | E12: =IF(D12=0,0,C12*10000/D12) -> 2802.7395 | F12: ='05 成本测算明细'!P94 -> 21931.92 | G12: =IF(F12=0,0,C12*10000/F12) -> 2802.7395 | H12: ='02 项目基础信息（输入）'!$E$32 -> 0 | I12: =IF(H12=0,0,C12*10000/H12) -> 0 | K12: =SUMIF('05 成本测算明细'!$S95:$S253,'04 目标成本控制表'!K$7,'05 成本测算明细'!$M95:$M253) -> 6146.9459 | L12: =SUMIF('05 成本测算明细'!$S95:$S253,'04 目标成本控制表'!L$7,'05 成本测算明细'!$M95:$M253) -> 0 | N12: =IF(D12=0,0,K12/$D12*10000) -> 2802.7395 | O12: =IF($D12=0,0,L12/$D12*10000) -> 0 | Q12: =E12-W12 -> 211.40067 | S12: =N12-Z12 -> 211.40067 | T12: =O12-AA12 -> 0 | W12: 2591.3389 | X12: 0 | Z12: 2591.3389 | AA12: 0 | AD12: C044012_21
B13: $pname1$ | C13: ='05 成本测算明细'!M255 -> 0 | D13: ='05 成本测算明细'!N255 -> 0 | E13: =IF(D13=0,0,C13*10000/D13) -> 0 | F13: ='05 成本测算明细'!P255 -> 0 | G13: =IF(F13=0,0,C13*10000/F13) -> 0 | H13: ='02 项目基础信息（输入）'!$E$36 -> 0 | I13: =IF(H13=0,0,C13*10000/H13) -> 0 | K13: =SUMIF('05 成本测算明细'!$S256:$S446,'04 目标成本控制表'!K$7,'05 成本测算明细'!$M256:$M446) -> 0 | L13: =SUMIF('05 成本测算明细'!$S256:$S446,'04 目标成本控制表'!L$7,'05 成本测算明细'!$M256:$M446) -> 0 | N13: =IF(D13=0,0,K13/$D13*10000) -> 0 | O13: =IF($D13=0,0,L13/$D13*10000) -> 0 | Q13: =E13-W13 -> 0 | S13: =N13-Z13 -> 0 | T13: =O13-AA13 -> 0 | AD13: C044013_$pcode1$
B14: 普通多层 | C14: ='05 成本测算明细'!M448 -> 0 | D14: ='05 成本测算明细'!N448 -> 0 | E14: =IF(D14=0,0,C14*10000/D14) -> 0 | F14: ='05 成本测算明细'!P448 -> 0 | G14: =IF(F14=0,0,C14*10000/F14) -> 0 | H14: ='02 项目基础信息（输入）'!$E$39 -> 0 | I14: =IF(H14=0,0,C14*10000/H14) -> 0 | K14: =SUMIF('05 成本测算明细'!$S449:$S639,'04 目标成本控制表'!K$7,'05 成本测算明细'!$M449:$M639) -> 0 | L14: =SUMIF('05 成本测算明细'!$S449:$S639,'04 目标成本控制表'!L$7,'05 成本测算明细'!$M449:$M639) -> 0 | N14: =IF(D14=0,0,K14/$D14*10000) -> 0 | O14: =IF($D14=0,0,L14/$D14*10000) -> 0 | Q14: =E14-W14 -> -2999.6143 | S14: =N14-Z14 -> -1869.3238 | T14: =O14-AA14 -> -1130.2905 | W14: 2999.6143 | X14: 2999.6143 | Z14: 1869.3238 | AA14: 1130.2905 | AC14: 备注：标准刻度业态，灰色格锁定 | AD14: C044014_12
B15: 小高层 | C15: ='05 成本测算明细'!M641 -> 19954.021 | D15: ='05 成本测算明细'!N641 -> 51879.835 | E15: =IF(D15=0,0,C15*10000/D15) -> 3846.1998 | F15: ='05 成本测算明细'!P641 -> 51879.835 | G15: =IF(F15=0,0,C15*10000/F15) -> 3846.1998 | H15: ='02 项目基础信息（输入）'!$E$42 -> 46191.065 | I15: =IF(H15=0,0,C15*10000/H15) -> 4319.8877 | K15: =SUMIF('05 成本测算明细'!$S642:$S832,'04 目标成本控制表'!K$7,'05 成本测算明细'!$M642:$M832) -> 10215.822 | L15: =SUMIF('05 成本测算明细'!$S642:$S832,'04 目标成本控制表'!L$7,'05 成本测算明细'!$M642:$M832) -> 9738.1989 | N15: =IF(D15=0,0,K15/$D15*10000) -> 1969.1316 | O15: =IF($D15=0,0,L15/$D15*10000) -> 1877.0682 | Q15: =E15-W15 -> 771.81915 | S15: =N15-Z15 -> 10.459995 | T15: =O15-AA15 -> 761.35916 | W15: 3074.3807 | X15: 3074.3807 | Z15: 1958.6716 | AA15: 1115.7091 | AD15: C044015_13
B16: 高层 | C16: ='05 成本测算明细'!M834 -> 0 | D16: ='05 成本测算明细'!N834 -> 0 | E16: =IF(D16=0,0,C16*10000/D16) -> 0 | F16: ='05 成本测算明细'!P834 -> 0 | G16: =IF(F16=0,0,C16*10000/F16) -> 0 | H16: ='02 项目基础信息（输入）'!$E$45 -> 0 | I16: =IF(H16=0,0,C16*10000/H16) -> 0 | K16: =SUMIF('05 成本测算明细'!$S835:$S1025,'04 目标成本控制表'!K$7,'05 成本测算明细'!$M835:$M1025) -> 0 | L16: =SUMIF('05 成本测算明细'!$S835:$S1025,'04 目标成本控制表'!L$7,'05 成本测算明细'!$M835:$M1025) -> 0 | N16: =IF(D16=0,0,K16/$D16*10000) -> 0 | O16: =IF($D16=0,0,L16/$D16*10000) -> 0 | Q16: =E16-W16 -> -2963.3941 | S16: =N16-Z16 -> -1854.1448 | T16: =O16-AA16 -> -1109.2493 | W16: 2963.3941 | X16: 2963.3941 | Z16: 1854.1448 | AA16: 1109.2493 | AD16: C044016_14
B17: $pname2$ | C17: ='05 成本测算明细'!M1027 -> 0 | D17: ='05 成本测算明细'!N1027 -> 0 | E17: =IF(D17=0,0,C17*10000/D17) -> 0 | F17: ='05 成本测算明细'!P1027 -> 0 | G17: =IF(F17=0,0,C17*10000/F17) -> 0 | H17: ='02 项目基础信息（输入）'!$E$48 -> 0 | I17: =IF(H17=0,0,C17*10000/H17) -> 0 | K17: =SUMIF('05 成本测算明细'!$S1028:$S1218,'04 目标成本控制表'!K$7,'05 成本测算明细'!$M1028:$M1218) -> 0 | L17: =SUMIF('05 成本测算明细'!$S1028:$S1218,'04 目标成本控制表'!L$7,'05 成本测算明细'!$M1028:$M1218) -> 0 | N17: =IF(D17=0,0,K17/$D17*10000) -> 0 | O17: =IF($D17=0,0,L17/$D17*10000) -> 0 | Q17: =E17-W17 -> 0 | S17: =N17-Z17 -> 0 | T17: =O17-AA17 -> 0 | AC17: 备注：非标准刻度业态，经办人手填参考项目值，放开 | AD17: C044017_$pcode2$
B18: $pname3$ | C18: ='05 成本测算明细'!M1220 -> 0 | D18: ='05 成本测算明细'!N1220 -> 0 | E18: =IF(D18=0,0,C18*10000/D18) -> 0 | F18: ='05 成本测算明细'!P1220 -> 0 | G18: =IF(F18=0,0,C18*10000/F18) -> 0 | H18: ='02 项目基础信息（输入）'!$E$51 -> 0 | I18: =IF(H18=0,0,C18*10000/H18) -> 0 | K18: =SUMIF('05 成本测算明细'!$S1221:$S1411,'04 目标成本控制表'!K$7,'05 成本测算明细'!$M1221:$M1411) -> 0 | L18: =SUMIF('05 成本测算明细'!$S1221:$S1411,'04 目标成本控制表'!L$7,'05 成本测算明细'!$M1221:$M1411) -> 0 | N18: =IF(D18=0,0,K18/$D18*10000) -> 0 | O18: =IF($D18=0,0,L18/$D18*10000) -> 0 | Q18: =E18-W18 -> 0 | S18: =N18-Z18 -> 0 | T18: =O18-AA18 -> 0 | AD18: C044018_$pcode3$
B19: $pname4$ | C19: ='05 成本测算明细'!M1413 -> 0 | D19: ='05 成本测算明细'!N1413 -> 0 | E19: =IF(D19=0,0,C19*10000/D19) -> 0 | F19: ='05 成本测算明细'!P1413 -> 0 | G19: =IF(F19=0,0,C19*10000/F19) -> 0 | H19: ='02 项目基础信息（输入）'!$E$54 -> 0 | I19: =IF(H19=0,0,C19*10000/H19) -> 0 | K19: =SUMIF('05 成本测算明细'!$S1414:$S1604,'04 目标成本控制表'!K$7,'05 成本测算明细'!$M1414:$M1604) -> 0 | L19: =SUMIF('05 成本测算明细'!$S1414:$S1604,'04 目标成本控制表'!L$7,'05 成本测算明细'!$M1414:$M1604) -> 0 | N19: =IF(D19=0,0,K19/$D19*10000) -> 0 | O19: =IF($D19=0,0,L19/$D19*10000) -> 0 | Q19: =E19-W19 -> 0 | S19: =N19-Z19 -> 0 | T19: =O19-AA19 -> 0 | AD19: C044019_$pcode4$
B20: $pname5$ | C20: ='05 成本测算明细'!M1606 -> 0 | D20: ='05 成本测算明细'!N1606 -> 0 | E20: =IF(D20=0,0,C20*10000/D20) -> 0 | F20: ='05 成本测算明细'!P1606 -> 0 | G20: =IF(F20=0,0,C20*10000/F20) -> 0 | H20: ='02 项目基础信息（输入）'!$E$57 -> 0 | I20: =IF(H20=0,0,C20*10000/H20) -> 0 | K20: =SUMIF('05 成本测算明细'!$S1607:$S1797,'04 目标成本控制表'!K$7,'05 成本测算明细'!$M1607:$M1797) -> 0 | L20: =SUMIF('05 成本测算明细'!$S1607:$S1797,'04 目标成本控制表'!L$7,'05 成本测算明细'!$M1607:$M1797) -> 0 | N20: =IF(D20=0,0,K20/$D20*10000) -> 0 | O20: =IF($D20=0,0,L20/$D20*10000) -> 0 | Q20: =E20-W20 -> 0 | S20: =N20-Z20 -> 0 | T20: =O20-AA20 -> 0 | AD20: C044020_$pcode5$
B21: $pname6$ | C21: ='05 成本测算明细'!M1799 -> 0 | D21: ='05 成本测算明细'!N1799 -> 0 | E21: =IF(D21=0,0,C21*10000/D21) -> 0 | F21: ='05 成本测算明细'!P1799 -> 0 | G21: =IF(F21=0,0,C21*10000/F21) -> 0 | H21: ='02 项目基础信息（输入）'!$E$60 -> 0 | I21: =IF(H21=0,0,C21*10000/H21) -> 0 | K21: =SUMIF('05 成本测算明细'!$S1799:$S1990,'04 目标成本控制表'!K$7,'05 成本测算明细'!$M1799:$M1990) -> 0 | L21: =SUMIF('05 成本测算明细'!$S1799:$S1990,'04 目标成本控制表'!L$7,'05 成本测算明细'!$M1799:$M1990) -> 0 | N21: =IF(D21=0,0,K21/$D21*10000) -> 0 | O21: =IF($D21=0,0,L21/$D21*10000) -> 0 | Q21: =E21-W21 -> 0 | S21: =N21-Z21 -> 0 | T21: =O21-AA21 -> 0 | AD21: C044021_$pcode6$
B22: 幼儿园 | C22: ='05 成本测算明细'!M1992 -> 0 | D22: ='05 成本测算明细'!N1992 -> 0 | E22: =IF(D22=0,0,C22*10000/D22) -> 0 | F22: ='05 成本测算明细'!P1992 -> 0 | G22: =IF(F22=0,0,C22*10000/F22) -> 0 | H22: ='02 项目基础信息（输入）'!$E$63 -> 0 | I22: =IF(H22=0,0,C22*10000/H22) -> 0 | K22: =C22 -> 0 | N22: =IF(D22=0,0,K22/$D22*10000) -> 0 | Q22: =E22-W22 -> 0 | S22: =N22-Z22 -> 0 | T22: =O22-AA22 -> 0 | AD22: C044022_33
B23: 其他公共配套 | C23: ='05 成本测算明细'!M2185 -> 454.02509 | D23: ='05 成本测算明细'!N2185 -> 815 | E23: =IF(D23=0,0,C23*10000/D23) -> 5570.86 | F23: ='05 成本测算明细'!P2185 -> 815 | G23: =IF(F23=0,0,C23*10000/F23) -> 5570.86 | H23: ='02 项目基础信息（输入）'!$E$66 -> 0 | I23: =IF(H23=0,0,C23*10000/H23) -> 0 | K23: =C23 -> 454.02509 | N23: =IF(D23=0,0,K23/$D23*10000) -> 5570.86 | Q23: =E23-W23 -> 5570.86 | S23: =N23-Z23 -> 5570.86 | T23: =O23-AA23 -> 0 | AD23: C044023_36
B24: 地库及机房(商业) | C24: ='05 成本测算明细'!M2378 -> 0 | D24: ='05 成本测算明细'!N2378 -> 0 | E24: =IF(D24=0,0,C24*10000/D24) -> 0 | F24: ='05 成本测算明细'!P2378 -> 0 | G24: =IF(F24=0,0,C24*10000/F24) -> 0 | H24: =D24 -> 0 | I24: =IF(H24=0,0,C24*10000/H24) -> 0 | K24: =SUMIF('05 成本测算明细'!$S2378:$S2484,'04 目标成本控制表'!K$7,'05 成本测算明细'!$M2378:$M2484) -> 0 | L24: =SUMIF('05 成本测算明细'!$S2378:$S2484,'04 目标成本控制表'!L$7,'05 成本测算明细'!$M2378:$M2484) -> 0 | N24: =IF(D24=0,0,K24/$D24*10000) -> 0 | O24: =IF($D24=0,0,L24/$D24*10000) -> 0 | Q24: =E24-W24 -> 0 | S24: =N24-Z24 -> 0 | T24: =O24-AA24 -> 0 | X24: 0 | Z24: 0 | AA24: 0 | AD24: C044024_20012
B25: $pnames01$集中商业 | C25: ='05 成本测算明细'!M2485 -> 0 | D25: ='05 成本测算明细'!N2485 -> 0 | E25: =IF(D25=0,0,C25*10000/D25) -> 0 | F25: ='05 成本测算明细'!P2485 -> 0 | G25: =IF(F25=0,0,C25*10000/F25) -> 0 | H25: =D25 -> 0 | I25: =IF(H25=0,0,C25*10000/H25) -> 0 | K25: =SUMIF('05 成本测算明细'!$S2485:$S2712,'04 目标成本控制表'!K$7,'05 成本测算明细'!$M2485:$M2712) -> 0 | L25: =SUMIF('05 成本测算明细'!$S2485:$S2712,'04 目标成本控制表'!L$7,'05 成本测算明细'!$M2485:$M2712) -> 0 | N25: =IF(D25=0,0,K25/$D25*10000) -> 0 | O25: =IF($D25=0,0,L25/$D25*10000) -> 0 | Q25: =E25-W25 -> 0 | S25: =N25-Z25 -> 0 | T25: =O25-AA25 -> 0 | X25: =I25 -> 0 | Z25: =N25 -> 0 | AA25: =O25 -> 0 | AD25: C044025_$pcodes01$
B26: $pnamex01$写字楼 | C26: ='05 成本测算明细'!M2713 -> 0 | D26: ='05 成本测算明细'!N2713 -> 0 | E26: =IF(D26=0,0,C26*10000/D26) -> 0 | F26: ='05 成本测算明细'!P2713 -> 0 | G26: =IF(F26=0,0,C26*10000/F26) -> 0 | H26: =D26 -> 0 | I26: =IF(H26=0,0,C26*10000/H26) -> 0 | K26: =SUMIF('05 成本测算明细'!$S2713:$S2939,'04 目标成本控制表'!K$7,'05 成本测算明细'!$M2713:$M2939) -> 0 | L26: =SUMIF('05 成本测算明细'!$S2713:$S2939,'04 目标成本控制表'!L$7,'05 成本测算明细'!$M2713:$M2939) -> 0 | N26: =IF(D26=0,0,K26/$D26*10000) -> 0 | O26: =IF($D26=0,0,L26/$D26*10000) -> 0 | Q26: =E26-W26 -> 0 | S26: =N26-Z26 -> 0 | T26: =O26-AA26 -> 0 | X26: =I26 -> 0 | Z26: =N26 -> 0 | AA26: =O26 -> 0 | AD26: C044026_$pcodex01$
B27: $pnamej01$酒店 | C27: ='05 成本测算明细'!M2940 -> 0 | D27: ='05 成本测算明细'!N2940 -> 0 | E27: =IF(D27=0,0,C27*10000/D27) -> 0 | F27: ='05 成本测算明细'!P2940 -> 0 | G27: =IF(F27=0,0,C27*10000/F27) -> 0 | H27: =D27 -> 0 | I27: =IF(H27=0,0,C27*10000/H27) -> 0 | K27: =SUMIF('05 成本测算明细'!$S2940:$S3210,'04 目标成本控制表'!K$7,'05 成本测算明细'!$M2940:$M3210) -> 0 | L27: =SUMIF('05 成本测算明细'!$S2940:$S3210,'04 目标成本控制表'!L$7,'05 成本测算明细'!$M2940:$M3210) -> 0 | N27: =IF(D27=0,0,K27/$D27*10000) -> 0 | O27: =IF($D27=0,0,L27/$D27*10000) -> 0 | Q27: =E27-W27 -> 0 | S27: =N27-Z27 -> 0 | T27: =O27-AA27 -> 0 | X27: =I27 -> 0 | Z27: =N27 -> 0 | AA27: =O27 -> 0 | AD27: C044027_$pcodej01$
B28: $pname7$集中商业 | C28: ='05 成本测算明细'!M3211 -> 0 | D28: ='05 成本测算明细'!N3211 -> 0 | E28: =IF(D28=0,0,C28*10000/D28) -> 0 | F28: ='05 成本测算明细'!P3211 -> 0 | G28: =IF(F28=0,0,C28*10000/F28) -> 0 | H28: =D28 -> 0 | I28: =IF(H28=0,0,C28*10000/H28) -> 0 | K28: =SUMIF('05 成本测算明细'!$S3211:$S3438,'04 目标成本控制表'!K$7,'05 成本测算明细'!$M3211:$M3438) -> 0 | L28: =SUMIF('05 成本测算明细'!$S3211:$S3438,'04 目标成本控制表'!L$7,'05 成本测算明细'!$M3211:$M3438) -> 0 | N28: =IF(D28=0,0,K28/$D28*10000) -> 0 | O28: =IF($D28=0,0,L28/$D28*10000) -> 0 | Q28: =E28-W28 -> 0 | S28: =N28-Z28 -> 0 | T28: =O28-AA28 -> 0 | AD28: C044028_$pcode7$
B29: $pname8$写字楼 | C29: ='05 成本测算明细'!M3439 -> 0 | D29: ='05 成本测算明细'!N3439 -> 0 | E29: =IF(D29=0,0,C29*10000/D29) -> 0 | F29: ='05 成本测算明细'!P3439 -> 0 | G29: =IF(F29=0,0,C29*10000/F29) -> 0 | H29: =D29 -> 0 | I29: =IF(H29=0,0,C29*10000/H29) -> 0 | K29: =SUMIF('05 成本测算明细'!$S3439:$S3665,'04 目标成本控制表'!K$7,'05 成本测算明细'!$M3439:$M3665) -> 0 | L29: =SUMIF('05 成本测算明细'!$S3439:$S3665,'04 目标成本控制表'!L$7,'05 成本测算明细'!$M3439:$M3665) -> 0 | N29: =IF(D29=0,0,K29/$D29*10000) -> 0 | O29: =IF($D29=0,0,L29/$D29*10000) -> 0 | Q29: =E29-W29 -> 0 | S29: =N29-Z29 -> 0 | T29: =O29-AA29 -> 0 | AD29: C044029_$pcode8$
B30: $pname9$写字楼 | C30: ='05 成本测算明细'!M3666 -> 0 | D30: ='05 成本测算明细'!N3666 -> 0 | E30: =IF(D30=0,0,C30*10000/D30) -> 0 | F30: ='05 成本测算明细'!P3666 -> 0 | G30: =IF(F30=0,0,C30*10000/F30) -> 0 | H30: =D30 -> 0 | I30: =IF(H30=0,0,C30*10000/H30) -> 0 | K30: =SUMIF('05 成本测算明细'!$S3666:$S3892,'04 目标成本控制表'!K$7,'05 成本测算明细'!$M3666:$M3892) -> 0 | L30: =SUMIF('05 成本测算明细'!$S3666:$S3892,'04 目标成本控制表'!L$7,'05 成本测算明细'!$M3666:$M3892) -> 0 | N30: =IF(D30=0,0,K30/$D30*10000) -> 0 | O30: =IF($D30=0,0,L30/$D30*10000) -> 0 | Q30: =E30-W30 -> 0 | S30: =N30-Z30 -> 0 | T30: =O30-AA30 -> 0 | AD30: C044030_$pcode9$
B31: $pname10$酒店 | C31: ='05 成本测算明细'!M3893 -> 0 | D31: ='05 成本测算明细'!N3893 -> 0 | E31: =IF(D31=0,0,C31*10000/D31) -> 0 | F31: ='05 成本测算明细'!P3896 -> 0 | G31: =IF(F31=0,0,C31*10000/F31) -> 0 | H31: =D31 -> 0 | I31: =IF(H31=0,0,C31*10000/H31) -> 0 | K31: =SUMIF('05 成本测算明细'!$S3893:$S41717,'04 目标成本控制表'!K$7,'05 成本测算明细'!$M3893:$M4163) -> 0 | L31: =SUMIF('05 成本测算明细'!$S3893:$S4163,'04 目标成本控制表'!L$7,'05 成本测算明细'!$M3893:$M4163) -> 0 | N31: =IF(D31=0,0,K31/$D31*10000) -> 0 | O31: =IF($D31=0,0,L31/$D31*10000) -> 0 | Q31: =E31-W31 -> 0 | S31: =N31-Z31 -> 0 | T31: =O31-AA31 -> 0 | AD31: C044031_$pcode10$
A32: 配套工程 | C32: ='05 成本测算明细'!M4164 -> 3162.253 | D32: ='05 成本测算明细'!N4164 -> 74626.755 | E32: =IF(D32=0,0,C32*10000/D32) -> 423.74253 | F32: ='05 成本测算明细'!P4164 -> 74626.755 | G32: =IF(F32=0,0,C32*10000/F32) -> 423.74253 | H32: ='02 项目基础信息（输入）'!$E$69 -> 46191.065 | I32: =IF(H32=0,0,C32*10000/H32) -> 684.60275 | J32: =C32 -> 3162.253 | M32: =IFERROR(J32/$F$4*10000,0) -> 423.74253 | Q32: =E32-W32 -> 423.74253 | R32: =M32-Y32 -> 30.317855 | X32: 571.84658 | Y32: 393.42467 | AD32: C040032
A33: 室外工程 | C33: ='05 成本测算明细'!M4190 -> 1963.2039 | D33: ='05 成本测算明细'!N4190 -> 18786.64 | E33: =IF(D33=0,0,C33*10000/D33) -> 1045 | F33: =D33 -> 18786.64 | G33: =IF(F33=0,0,C33*10000/F33) -> 1045 | H33: ='02 项目基础信息（输入）'!$E$69 -> 46191.065 | I33: =IF(H33=0,0,C33*10000/H33) -> 425.01811 | L33: =C33 -> 1963.2039 | O33: =IFERROR(L33/$F$4*10000,0) -> 263.06971 | Q33: =E33-W33 -> 1045 | T33: =O33-AA33 -> 83.069708 | X33: 261.63175 | AA33: 180 | AD33: C040033
A34: 户内装饰工程 | B34: 小计 | C34: ='05 成本测算明细'!M4241 -> 13857.319 | D34: ='05 成本测算明细'!N4241 -> 46191.065 | E34: =IF(D34=0,0,C34*10000/D34) -> 3000 | F34: ='05 成本测算明细'!P4241 -> 46191.065 | G34: =IF(F34=0,0,C34*10000/F34) -> 3000 | H34: ='02 项目基础信息（输入）'!E69 -> 46191.065 | I34: =IF(H34=0,0,C34*10000/H34) -> 3000 | AD34: C046034
B35: $pname1$ | C35: ='05 成本测算明细'!M4242 -> 0 | D35: ='05 成本测算明细'!N4242 -> 0 | E35: =IF(D35=0,0,C35*10000/D35) -> 0 | F35: ='05 成本测算明细'!P4242 -> 0 | G35: =IF(F35=0,0,C35*10000/F35) -> 0 | H35: ='02 项目基础信息（输入）'!$E$36 -> 0 | I35: =IF(H35=0,0,C35*10000/H35) -> 0 | AD35: C046035_$pcode1$
B36: 普通多层 | C36: ='05 成本测算明细'!M4243 -> 0 | D36: ='05 成本测算明细'!N4243 -> 0 | E36: =IF(D36=0,0,C36*10000/D36) -> 0 | F36: ='05 成本测算明细'!P4243 -> 0 | G36: =IF(F36=0,0,C36*10000/F36) -> 0 | H36: ='02 项目基础信息（输入）'!$E$39 -> 0 | I36: =IF(H36=0,0,C36*10000/H36) -> 0 | AD36: C046036_12
B37: 小高层 | C37: ='05 成本测算明细'!M4244 -> 13857.319 | D37: ='05 成本测算明细'!N4244 -> 46191.065 | E37: =IF(D37=0,0,C37*10000/D37) -> 3000 | F37: ='05 成本测算明细'!P4244 -> 46191.065 | G37: =IF(F37=0,0,C37*10000/F37) -> 3000 | H37: ='02 项目基础信息（输入）'!$E$42 -> 46191.065 | I37: =IF(H37=0,0,C37*10000/H37) -> 3000 | AD37: C046037_13
B38: 高层 | C38: ='05 成本测算明细'!M4245 -> 0 | D38: ='05 成本测算明细'!N4245 -> 0 | E38: =IF(D38=0,0,C38*10000/D38) -> 0 | F38: ='05 成本测算明细'!P4245 -> 0 | G38: =IF(F38=0,0,C38*10000/F38) -> 0 | H38: ='02 项目基础信息（输入）'!$E$45 -> 0 | I38: =IF(H38=0,0,C38*10000/H38) -> 0 | AD38: C046038_14
B39: $pname2$ | C39: ='05 成本测算明细'!M4246 -> 0 | D39: ='05 成本测算明细'!N4246 -> 0 | E39: =IF(D39=0,0,C39*10000/D39) -> 0 | F39: ='05 成本测算明细'!P4246 -> 0 | G39: =IF(F39=0,0,C39*10000/F39) -> 0 | H39: ='02 项目基础信息（输入）'!$E$48 -> 0 | I39: =IF(H39=0,0,C39*10000/H39) -> 0 | AD39: C046039_$pcode2$
B40: $pname3$ | C40: ='05 成本测算明细'!M4247 -> 0 | D40: ='05 成本测算明细'!N4247 -> 0 | E40: =IF(D40=0,0,C40*10000/D40) -> 0 | F40: ='05 成本测算明细'!P4247 -> 0 | G40: =IF(F40=0,0,C40*10000/F40) -> 0 | H40: ='02 项目基础信息（输入）'!$E$51 -> 0 | I40: =IF(H40=0,0,C40*10000/H40) -> 0 | AD40: C046040_$pcode3$
B41: $pname4$ | C41: ='05 成本测算明细'!M4248 -> 0 | D41: ='05 成本测算明细'!N4248 -> 0 | E41: =IF(D41=0,0,C41*10000/D41) -> 0 | F41: ='05 成本测算明细'!P4248 -> 0 | G41: =IF(F41=0,0,C41*10000/F41) -> 0 | H41: ='02 项目基础信息（输入）'!$E$54 -> 0 | I41: =IF(H41=0,0,C41*10000/H41) -> 0 | AD41: C046041_$pcode4$
B42: $pname5$ | C42: ='05 成本测算明细'!M4249 -> 0 | D42: ='05 成本测算明细'!N4249 -> 0 | E42: =IF(D42=0,0,C42*10000/D42) -> 0 | F42: ='05 成本测算明细'!P4249 -> 0 | G42: =IF(F42=0,0,C42*10000/F42) -> 0 | H42: ='02 项目基础信息（输入）'!$E$57 -> 0 | I42: =IF(H42=0,0,C42*10000/H42) -> 0 | AD42: C046042_$pcode5$
B43: $pname6$ | C43: ='05 成本测算明细'!M4250 -> 0 | D43: ='05 成本测算明细'!N4250 -> 0 | E43: =IF(D43=0,0,C43*10000/D43) -> 0 | F43: ='05 成本测算明细'!P4250 -> 0 | G43: =IF(F43=0,0,C43*10000/F43) -> 0 | H43: ='02 项目基础信息（输入）'!$E$60 -> 0 | I43: =IF(H43=0,0,C43*10000/H43) -> 0 | AD43: C046043_$pcode6$
B44: 幼儿园 | C44: ='05 成本测算明细'!M4251 -> 0 | D44: ='05 成本测算明细'!N4251 -> 0 | E44: =IF(D44=0,0,C44*10000/D44) -> 0 | F44: ='05 成本测算明细'!P4251 -> 0 | G44: =IF(F44=0,0,C44*10000/F44) -> 0 | H44: ='02 项目基础信息（输入）'!$E$63 -> 0 | I44: =IF(H44=0,0,C44*10000/H44) -> 0 | AD44: C046044_33
A45: 其它 | B45: 基础设施工程 | C45: ='05 成本测算明细'!M4252 -> 228 | D45: ='05 成本测算明细'!N4252 -> 74626.755 | E45: =IFERROR(C45*10000/D45,0) -> 30.552045 | F45: ='05 成本测算明细'!P4252 -> 74626.755 | G45: =IFERROR(C45*10000/F45,0) -> 30.552045 | H45: ='02 项目基础信息（输入）'!$E$69 -> 46191.065 | I45: =IFERROR(C45*10000/H45,0) -> 49.360196 | AD45: C047045
B46: 卖场包装费用 | C46: ='05 成本测算明细'!M4281 -> 3207.05 | D46: ='05 成本测算明细'!N4281 -> 74626.755 | E46: =IFERROR(C46*10000/D46,0) -> 429.74534 | F46: ='05 成本测算明细'!P4281 -> 74626.755 | G46: =IFERROR(C46*10000/F46,0) -> 429.74534 | H46: ='02 项目基础信息（输入）'!$E$69 -> 46191.065 | I46: =IFERROR(C46*10000/H46,0) -> 694.30095 | AD46: C047046
B47: 专项设备设施费用 | C47: ='05 成本测算明细'!M4310 -> 0 | D47: ='05 成本测算明细'!N4310 -> 74626.755 | E47: =IFERROR(C47*10000/D47,0) -> 0 | F47: ='05 成本测算明细'!P4310 -> 74626.755 | G47: =IFERROR(C47*10000/F47,0) -> 0 | H47: ='02 项目基础信息（输入）'!$E$69 -> 46191.065 | I47: =IFERROR(C47*10000/H47,0) -> 0 | AD47: C047047
A48: 合计 | B48: 毛坯 | C48: =C8+C9+C10+C11+C32+C33 -> 36116.349 | D48: =D8 -> 74626.755 | E48: =IFERROR(C48*10000/D48,0) -> 4839.598 | F48: =F8 -> 74626.755 | G48: =IFERROR(C48*10000/F48,0) -> 4839.598 | H48: ='02 项目基础信息（输入）'!$E$69+'02 项目基础信息（输入）'!D7 -> 46191.065 | I48: =IFERROR(C48*10000/H48,0) -> 7818.9038 | J48: =J8+J9+J10+J11+J32+J33 -> 7598.1532 | K48: =K8+K9+K10+K11+K32+K33 -> 16816.793 | L48: =L8+L9+L10+L11+L32+L33 -> 11701.403 | M48: =IFERROR(J48*10000/D48,0) -> 1018.154 | N48: =IFERROR(K48*10000/D48,0) -> 2253.4536 | O48: =IFERROR(L48*10000/D48,0) -> 1567.9903 | Q48: =E48-W48 -> 1040.0084 | R48: =IFERROR(M48-Y48,0) -> 282.17415 | S48: =IFERROR(N48-Z48,0) -> 139.3166 | T48: =IFERROR(O48-AA48,0) -> 618.51761 | W48: 3799.5896 | X48: 5522.7404 | Y48: 735.9799 | Z48: 2114.137 | AA48: 949.4727 | AD48: C048048
B49: 总建安成本 | C49: =C48+C34+C45+C46+C47 -> 53408.719 | D49: =D8 -> 74626.755 | E49: =IFERROR(C49*10000/D49,0) -> 7156.7789 | F49: =F8 -> 74626.755 | G49: =IFERROR(C49*10000/F49,0) -> 7156.7789 | H49: ='02 项目基础信息（输入）'!$E$69+'02 项目基础信息（输入）'!D7 -> 46191.065 | I49: =IFERROR(C49*10000/H49,0) -> 11562.565 | AD49: C048049
A50: 物业类型_x000D_ 毛坯成本 | B50: $pname1$ | C50: =IFERROR($C13+$D13*SUM($C$8+$C$9+$C$10+$C$12+$C$24+$C$32+$C$33)/(SUM($D$13:$D$21)+SUM($D$25:$D$31)),0) -> 0 | D50: =IFERROR($D13+$D13*($D$12+$D$24)/(SUM($D$13:$D$21)+SUM($D$25:$D$31)),0) -> 0 | E50: =IF(D50=0,0,C50*10000/D50) -> 0 | F50: =IFERROR($F13+$F13*($F$12+$F$24)/(SUM($F$13:$F$21)+SUM($F$25:$F$31)),0) -> 0 | G50: =IF(F50=0,0,C50*10000/F50) -> 0 | H50: =H13 -> 0 | I50: =IF(H50=0,0,C50*10000/H50) -> 0 | J50: =IFERROR(J13+$D13*SUM(J$8+J$9+J$10+J$12+J$24+J$32+J$33)/(SUM($D$13:$D$21)+SUM($D$25:$D$31)),0) -> 0 | K50: =IFERROR(K13+$D13*SUM(K$8+K$9+K$10+K$12+K$24+K$32+K$33)/(SUM($D$13:$D$21)+SUM($D$25:$D$31)),0) -> 0 | L50: =IFERROR(L13+$D13*SUM(L$8+L$9+L$10+L$12+L$24+L$32+L$33)/(SUM($D$13:$D$21)+SUM($D$25:$D$31)),0) -> 0 | M50: =IF(D50=0,0,J50/$D50*10000) -> 0 | N50: =IF(D50=0,0,K50/$D50*10000) -> 0 | O50: =IF(D50=0,0,L50/$D50*10000) -> 0 | Q50: =E50-W50 -> 0 | R50: =M50-Y50 -> 0 | S50: =N50-Z50 -> 0 | T50: =O50-AA50 -> 0 | AD50: C049050_$pcode1$
B51: 普通多层 | C51: =IFERROR($C14+$D14*SUM($C$8+$C$9+$C$10+$C$12+$C$24+$C$32+$C$33)/(SUM($D$13:$D$21)+SUM($D$25:$D$31)),0) -> 0 | D51: =IFERROR($D14+$D14*($D$12+$D$24)/(SUM($D$13:$D$21)+SUM($D$25:$D$31)),0) -> 0 | E51: =IF(D51=0,0,C51*10000/D51) -> 0 | F51: =IFERROR($F14+$F14*($F$12+$F$24)/(SUM($F$13:$F$21)+SUM($F$25:$F$31)),0) -> 0 | G51: =IF(F51=0,0,C51*10000/F51) -> 0 | H51: =H14 -> 0 | I51: =IF(H51=0,0,C51*10000/H51) -> 0 | J51: =IFERROR(J14+$D14*SUM(J$8+J$9+J$10+J$12+J$24+J$32+J$33)/(SUM($D$13:$D$21)+SUM($D$25:$D$31)),0) -> 0 | K51: =IFERROR(K14+$D14*SUM(K$8+K$9+K$10+K$12+K$24+K$32+K$33)/(SUM($D$13:$D$21)+SUM($D$25:$D$31)),0) -> 0 | L51: =IFERROR(L14+$D14*SUM(L$8+L$9+L$10+L$12+L$24+L$32+L$33)/(SUM($D$13:$D$21)+SUM($D$25:$D$31)),0) -> 0 | M51: =IF(D51=0,0,J51/$D51*10000) -> 0 | N51: =IF(D51=0,0,K51/$D51*10000) -> 0 | O51: =IF(D51=0,0,L51/$D51*10000) -> 0 | Q51: =E51-W51 -> -3788.2081 | R51: =M51-Y51 -> -735.9799 | S51: =N51-Z51 -> -2094.5998 | T51: =O51-AA51 -> -957.62844 | W51: 3788.2081 | X51: 5506.1973 | Y51: 735.9799 | Z51: 2094.5998 | AA51: 957.62844 | AD51: C049051_12
B52: 小高层 | C52: =IFERROR($C15+$D15*SUM($C$8+$C$9+$C$10+$C$12+$C$24+$C$32+$C$33)/(SUM($D$13:$D$21)+SUM($D$25:$D$31)),0) -> 35662.324 | D52: =IFERROR($D15+$D15*($D$12+$D$24)/(SUM($D$13:$D$21)+SUM($D$25:$D$31)),0) -> 73811.755 | E52: =IF(D52=0,0,C52*10000/D52) -> 4831.5237 | F52: =IFERROR($F15+$F15*($F$12+$F$24)/(SUM($F$13:$F$21)+SUM($F$25:$F$31)),0) -> 73811.755 | G52: =IF(F52=0,0,C52*10000/F52) -> 4831.5237 | H52: =H15 -> 46191.065 | I52: =IF(H52=0,0,C52*10000/H52) -> 7720.611 | J52: =IFERROR(J15+$D15*SUM(J$8+J$9+J$10+J$12+J$24+J$32+J$33)/(SUM($D$13:$D$21)+SUM($D$25:$D$31)),0) -> 7598.1532 | K52: =IFERROR(K15+$D15*SUM(K$8+K$9+K$10+K$12+K$24+K$32+K$33)/(SUM($D$13:$D$21)+SUM($D$25:$D$31)),0) -> 16362.768 | L52: =IFERROR(L15+$D15*SUM(L$8+L$9+L$10+L$12+L$24+L$32+L$33)/(SUM($D$13:$D$21)+SUM($D$25:$D$31)),0) -> 11701.403 | M52: =IF(D52=0,0,J52/$D52*10000) -> 1029.3961 | N52: =IF(D52=0,0,K52/$D52*10000) -> 2216.8242 | O52: =IF(D52=0,0,L52/$D52*10000) -> 1585.3034 | Q52: =E52-W52 -> 991.87704 | R52: =M52-Y52 -> 293.4162 | S52: =N52-Z52 -> 60.753984 | T52: =O52-AA52 -> 637.70686 | W52: 3839.6467 | X52: 5580.9637 | Y52: 735.9799 | Z52: 2156.0702 | AA52: 947.59658 | AD52: C049052_13
B53: 高层 | C53: =IFERROR($C16+$D16*SUM($C$8+$C$9+$C$10+$C$12+$C$24+$C$32+$C$33)/(SUM($D$13:$D$21)+SUM($D$25:$D$31)),0) -> 0 | D53: =IFERROR($D16+$D16*($D$12+$D$24)/(SUM($D$13:$D$21)+SUM($D$25:$D$31)),0) -> 0 | E53: =IF(D53=0,0,C53*10000/D53) -> 0 | F53: =IFERROR($F16+$F16*($F$12+$F$24)/(SUM($F$13:$F$21)+SUM($F$25:$F$31)),0) -> 0 | G53: =IF(F53=0,0,C53*10000/F53) -> 0 | H53: =H16 -> 0 | I53: =IF(H53=0,0,C53*10000/H53) -> 0 | J53: =IFERROR(J16+$D16*SUM(J$8+J$9+J$10+J$12+J$24+J$32+J$33)/(SUM($D$13:$D$21)+SUM($D$25:$D$31)),0) -> 0 | K53: =IFERROR(K16+$D16*SUM(K$8+K$9+K$10+K$12+K$24+K$32+K$33)/(SUM($D$13:$D$21)+SUM($D$25:$D$31)),0) -> 0 | L53: =IFERROR(L16+$D16*SUM(L$8+L$9+L$10+L$12+L$24+L$32+L$33)/(SUM($D$13:$D$21)+SUM($D$25:$D$31)),0) -> 0 | M53: =IF(D53=0,0,J53/$D53*10000) -> 0 | N53: =IF(D53=0,0,K53/$D53*10000) -> 0 | O53: =IF(D53=0,0,L53/$D53*10000) -> 0 | Q53: =E53-W53 -> -3763.289 | R53: =M53-Y53 -> -735.9799 | S53: =N53-Z53 -> -2084.1568 | T53: =O53-AA53 -> -943.15234 | W53: 3763.289 | X53: 5469.9771 | Y53: 735.9799 | Z53: 2084.1568 | AA53: 943.15234 | AD53: C049054_14
B54: $pname2$ | C54: =IFERROR($C17+$D17*SUM($C$8+$C$9+$C$10+$C$12+$C$24+$C$32+$C$33)/(SUM($D$13:$D$21)+SUM($D$25:$D$31)),0) -> 0 | D54: =IFERROR($D17+$D17*($D$12+$D$24)/(SUM($D$13:$D$21)+SUM($D$25:$D$31)),0) -> 0 | E54: =IF(D54=0,0,C54*10000/D54) -> 0 | F54: =IFERROR($F17+$F17*($F$12+$F$24)/(SUM($F$13:$F$21)+SUM($F$25:$F$31)),0) -> 0 | G54: =IF(F54=0,0,C54*10000/F54) -> 0 | H54: =H17 -> 0 | I54: =IF(H54=0,0,C54*10000/H54) -> 0 | J54: =IFERROR(J17+$D17*SUM(J$8+J$9+J$10+J$12+J$24+J$32+J$33)/(SUM($D$13:$D$21)+SUM($D$25:$D$31)),0) -> 0 | K54: =IFERROR(K17+$D17*SUM(K$8+K$9+K$10+K$12+K$24+K$32+K$33)/(SUM($D$13:$D$21)+SUM($D$25:$D$31)),0) -> 0 | L54: =IFERROR(L17+$D17*SUM(L$8+L$9+L$10+L$12+L$24+L$32+L$33)/(SUM($D$13:$D$21)+SUM($D$25:$D$31)),0) -> 0 | M54: =IF(D54=0,0,J54/$D54*10000) -> 0 | N54: =IF(D54=0,0,K54/$D54*10000) -> 0 | O54: =IF(D54=0,0,L54/$D54*10000) -> 0 | Q54: =E54-W54 -> 0 | R54: =M54-Y54 -> 0 | S54: =N54-Z54 -> 0 | T54: =O54-AA54 -> 0 | AD54: C049055_$pcode2$
B55: $pname3$ | C55: =IFERROR($C18+$D18*SUM($C$8+$C$9+$C$10+$C$12+$C$24+$C$32+$C$33)/(SUM($D$13:$D$21)+SUM($D$25:$D$31)),0) -> 0 | D55: =IFERROR($D18+$D18*($D$12+$D$24)/(SUM($D$13:$D$21)+SUM($D$25:$D$31)),0) -> 0 | E55: =IF(D55=0,0,C55*10000/D55) -> 0 | F55: =IFERROR($F18+$F18*($F$12+$F$24)/(SUM($F$13:$F$21)+SUM($F$25:$F$31)),0) -> 0 | G55: =IF(F55=0,0,C55*10000/F55) -> 0 | H55: =H18 -> 0 | I55: =IF(H55=0,0,C55*10000/H55) -> 0 | J55: =IFERROR(J18+$D18*SUM(J$8+J$9+J$10+J$12+J$24+J$32+J$33)/(SUM($D$13:$D$21)+SUM($D$25:$D$31)),0) -> 0 | K55: =IFERROR(K18+$D18*SUM(K$8+K$9+K$10+K$12+K$24+K$32+K$33)/(SUM($D$13:$D$21)+SUM($D$25:$D$31)),0) -> 0 | L55: =IFERROR(L18+$D18*SUM(L$8+L$9+L$10+L$12+L$24+L$32+L$33)/(SUM($D$13:$D$21)+SUM($D$25:$D$31)),0) -> 0 | M55: =IF(D55=0,0,J55/$D55*10000) -> 0 | N55: =IF(D55=0,0,K55/$D55*10000) -> 0 | O55: =IF(D55=0,0,L55/$D55*10000) -> 0 | Q55: =E55-W55 -> 0 | R55: =M55-Y55 -> 0 | S55: =N55-Z55 -> 0 | T55: =O55-AA55 -> 0 | AD55: C049055_$pcode3$
B56: $pname4$ | C56: =IFERROR($C19+$D19*SUM($C$8+$C$9+$C$10+$C$12+$C$24+$C$32+$C$33)/(SUM($D$13:$D$21)+SUM($D$25:$D$31)),0) -> 0 | D56: =IFERROR($D19+$D19*($D$12+$D$24)/(SUM($D$13:$D$21)+SUM($D$25:$D$31)),0) -> 0 | E56: =IF(D56=0,0,C56*10000/D56) -> 0 | F56: =IFERROR($F19+$F19*($F$12+$F$24)/(SUM($F$13:$F$21)+SUM($F$25:$F$31)),0) -> 0 | G56: =IF(F56=0,0,C56*10000/F56) -> 0 | H56: =H19 -> 0 | I56: =IF(H56=0,0,C56*10000/H56) -> 0 | J56: =IFERROR(J19+$D19*SUM(J$8+J$9+J$10+J$12+J$24+J$32+J$33)/(SUM($D$13:$D$21)+SUM($D$25:$D$31)),0) -> 0 | K56: =IFERROR(K19+$D19*SUM(K$8+K$9+K$10+K$12+K$24+K$32+K$33)/(SUM($D$13:$D$21)+SUM($D$25:$D$31)),0) -> 0 | L56: =IFERROR(L19+$D19*SUM(L$8+L$9+L$10+L$12+L$24+L$32+L$33)/(SUM($D$13:$D$21)+SUM($D$25:$D$31)),0) -> 0 | M56: =IF(D56=0,0,J56/$D56*10000) -> 0 | N56: =IF(D56=0,0,K56/$D56*10000) -> 0 | O56: =IF(D56=0,0,L56/$D56*10000) -> 0 | Q56: =E56-W56 -> 0 | R56: =M56-Y56 -> 0 | S56: =N56-Z56 -> 0 | T56: =O56-AA56 -> 0 | AD56: C049056_$pcode4$
B57: $pname5$ | C57: =IFERROR($C20+$D20*SUM($C$8+$C$9+$C$10+$C$12+$C$24+$C$32+$C$33)/(SUM($D$13:$D$21)+SUM($D$25:$D$31)),0) -> 0 | D57: =IFERROR($D20+$D20*($D$12+$D$24)/(SUM($D$13:$D$21)+SUM($D$25:$D$31)),0) -> 0 | E57: =IF(D57=0,0,C57*10000/D57) -> 0 | F57: =IFERROR($F20+$F20*($F$12+$F$24)/(SUM($F$13:$F$21)+SUM($F$25:$F$31)),0) -> 0 | G57: =IF(F57=0,0,C57*10000/F57) -> 0 | H57: =H20 -> 0 | I57: =IF(H57=0,0,C57*10000/H57) -> 0 | J57: =IFERROR(J20+$D20*SUM(J$8+J$9+J$10+J$12+J$24+J$32+J$33)/(SUM($D$13:$D$21)+SUM($D$25:$D$31)),0) -> 0 | K57: =IFERROR(K20+$D20*SUM(K$8+K$9+K$10+K$12+K$24+K$32+K$33)/(SUM($D$13:$D$21)+SUM($D$25:$D$31)),0) -> 0 | L57: =IFERROR(L20+$D20*SUM(L$8+L$9+L$10+L$12+L$24+L$32+L$33)/(SUM($D$13:$D$21)+SUM($D$25:$D$31)),0) -> 0 | M57: =IF(D57=0,0,J57/$D57*10000) -> 0 | N57: =IF(D57=0,0,K57/$D57*10000) -> 0 | O57: =IF(D57=0,0,L57/$D57*10000) -> 0 | Q57: =E57-W57 -> 0 | R57: =M57-Y57 -> 0 | S57: =N57-Z57 -> 0 | T57: =O57-AA57 -> 0 | AD57: C049057_$pcode5$
B58: $pname6$ | C58: =IFERROR($C21+$D21*SUM($C$8+$C$9+$C$10+$C$12+$C$24+$C$32+$C$33)/(SUM($D$13:$D$21)+SUM($D$25:$D$31)),0) -> 0 | D58: =IFERROR($D21+$D21*($D$12+$D$24)/(SUM($D$13:$D$21)+SUM($D$25:$D$31)),0) -> 0 | E58: =IF(D58=0,0,C58*10000/D58) -> 0 | F58: =IFERROR($F21+$F21*($F$12+$F$24)/(SUM($F$13:$F$21)+SUM($F$25:$F$31)),0) -> 0 | G58: =IF(F58=0,0,C58*10000/F58) -> 0 | H58: =H21 -> 0 | I58: =IF(H58=0,0,C58*10000/H58) -> 0 | J58: =IFERROR(J21+$D21*SUM(J$8+J$9+J$10+J$12+J$24+J$32+J$33)/(SUM($D$13:$D$21)+SUM($D$25:$D$31)),0) -> 0 | K58: =IFERROR(K21+$D21*SUM(K$8+K$9+K$10+K$12+K$24+K$32+K$33)/(SUM($D$13:$D$21)+SUM($D$25:$D$31)),0) -> 0 | L58: =IFERROR(L21+$D21*SUM(L$8+L$9+L$10+L$12+L$24+L$32+L$33)/(SUM($D$13:$D$21)+SUM($D$25:$D$31)),0) -> 0 | M58: =IF(D58=0,0,J58/$D58*10000) -> 0 | N58: =IF(D58=0,0,K58/$D58*10000) -> 0 | O58: =IF(D58=0,0,L58/$D58*10000) -> 0 | Q58: =E58-W58 -> 0 | R58: =M58-Y58 -> 0 | S58: =N58-Z58 -> 0 | T58: =O58-AA58 -> 0 | AD58: C049058_$pcode5$
B59: 幼儿园 | C59: =C22 -> 0 | D59: =D22 -> 0 | E59: =IF(D59=0,0,C59*10000/D59) -> 0 | F59: =F22 -> 0 | G59: =IF(F59=0,0,C59*10000/F59) -> 0 | H59: =H22 -> 0 | I59: =IF(H59=0,0,C59*10000/H59) -> 0 | J59: =J22 -> 0 | K59: =K22 -> 0 | L59: =L22 -> 0 | M59: =IF(D59=0,0,J59/$D59*10000) -> 0 | N59: =IF(D59=0,0,K59/$D59*10000) -> 0 | O59: =IF(D59=0,0,L59/$D59*10000) -> 0 | Q59: =E59-W59 -> 0 | R59: =M59-Y59 -> 0 | S59: =N59-Z59 -> 0 | T59: =O59-AA59 -> 0 | AD59: C049059_33
B60: 其他公共配套 | C60: =C23 -> 454.02509 | D60: =D23 -> 815 | E60: =IF(D60=0,0,C60*10000/D60) -> 5570.86 | F60: =F23 -> 815 | G60: =IF(F60=0,0,C60*10000/F60) -> 5570.86 | H60: =H23 -> 0 | I60: =IF(H60=0,0,C60*10000/H60) -> 0 | J60: =J23 -> 0 | K60: =K23 -> 454.02509 | L60: =L23 -> 0 | M60: =IF(D60=0,0,J60/$D60*10000) -> 0 | N60: =IF(D60=0,0,K60/$D60*10000) -> 5570.86 | O60: =IF(D60=0,0,L60/$D60*10000) -> 0 | Q60: =E60-W60 -> 5570.86 | R60: =M60-Y60 -> 0 | S60: =N60-Z60 -> 5570.86 | T60: =O60-AA60 -> 0 | AD60: C049060_36
B61: =B25 -> $pnames01$集中商业 | C61: =IFERROR($C25+$D25*SUM($C$8+$C$9+$C$10+$C$12+$C$24+$C$32+$C$33)/(SUM($D$13:$D$21)+SUM($D$25:$D$31)),0) -> 0 | D61: =IFERROR($D25+$D25*($D$12+$D$24)/(SUM($D$13:$D$21)+SUM($D$25:$D$31)),0) -> 0 | E61: =IF(D61=0,0,C61*10000/D61) -> 0 | F61: =IFERROR($F25+$F25*($F$12+$F$24)/(SUM($F$13:$F$21)+SUM($F$25:$F$31)),0) -> 0 | G61: =IF(F61=0,0,C61*10000/F61) -> 0 | H61: =H25 -> 0 | I61: =IF(H61=0,0,C61*10000/H61) -> 0 | J61: =IFERROR(J25+$D25*SUM(J$8+J$9+J$10+J$12+J$24+J$32+J$33)/(SUM($D$13:$D$21)+SUM($D$25:$D$31)),0) -> 0 | K61: =IFERROR(K25+$D25*SUM(K$8+K$9+K$10+K$12+K$24+K$32+K$33)/(SUM($D$13:$D$21)+SUM($D$25:$D$31)),0) -> 0 | L61: =IFERROR(L25+$D25*SUM(L$8+L$9+L$10+L$12+L$24+L$32+L$33)/(SUM($D$13:$D$21)+SUM($D$25:$D$31)),0) -> 0 | M61: =IF(D61=0,0,J61/$D61*10000) -> 0 | N61: =IF(D61=0,0,K61/$D61*10000) -> 0 | O61: =IF(D61=0,0,L61/$D61*10000) -> 0 | W61: =E61 -> 0 | X61: =I61 -> 0 | Y61: =M61 -> 0 | Z61: =N61 -> 0 | AA61: =O61 -> 0 | AD61: C049061_$pcodes01$
B62: =B26 -> $pnamex01$写字楼 | C62: =IFERROR($C26+$D26*SUM($C$8+$C$9+$C$10+$C$12+$C$24+$C$32+$C$33)/(SUM($D$13:$D$21)+SUM($D$25:$D$31)),0) -> 0 | D62: =IFERROR($D26+$D26*($D$12+$D$24)/(SUM($D$13:$D$21)+SUM($D$25:$D$31)),0) -> 0 | E62: =IF(D62=0,0,C62*10000/D62) -> 0 | F62: =IFERROR($F26+$F26*($F$12+$F$24)/(SUM($F$13:$F$21)+SUM($F$25:$F$31)),0) -> 0 | G62: =IF(F62=0,0,C62*10000/F62) -> 0 | H62: =H26 -> 0 | I62: =IF(H62=0,0,C62*10000/H62) -> 0 | J62: =IFERROR(J26+$D26*SUM(J$8+J$9+J$10+J$12+J$24+J$32+J$33)/(SUM($D$13:$D$21)+SUM($D$25:$D$31)),0) -> 0 | K62: =IFERROR(K26+$D26*SUM(K$8+K$9+K$10+K$12+K$24+K$32+K$33)/(SUM($D$13:$D$21)+SUM($D$25:$D$31)),0) -> 0 | L62: =IFERROR(L26+$D26*SUM(L$8+L$9+L$10+L$12+L$24+L$32+L$33)/(SUM($D$13:$D$21)+SUM($D$25:$D$31)),0) -> 0 | M62: =IF(D62=0,0,J62/$D62*10000) -> 0 | N62: =IF(D62=0,0,K62/$D62*10000) -> 0 | O62: =IF(D62=0,0,L62/$D62*10000) -> 0 | W62: =E62 -> 0 | X62: =I62 -> 0 | Y62: =M62 -> 0 | Z62: =N62 -> 0 | AA62: =O62 -> 0 | AD62: C049062_$pcodex01$
B63: =B27 -> $pnamej01$酒店 | C63: =IFERROR($C27+$D27*SUM($C$8+$C$9+$C$10+$C$12+$C$24+$C$32+$C$33)/(SUM($D$13:$D$21)+SUM($D$25:$D$31)),0) -> 0 | D63: =IFERROR($D27+$D27*($D$12+$D$24)/(SUM($D$13:$D$21)+SUM($D$25:$D$31)),0) -> 0 | E63: =IF(D63=0,0,C63*10000/D63) -> 0 | F63: =IFERROR($F27+$F27*($F$12+$F$24)/(SUM($F$13:$F$21)+SUM($F$25:$F$31)),0) -> 0 | G63: =IF(F63=0,0,C63*10000/F63) -> 0 | H63: =H27 -> 0 | I63: =IF(H63=0,0,C63*10000/H63) -> 0 | J63: =IFERROR(J27+$D27*SUM(J$8+J$9+J$10+J$12+J$24+J$32+J$33)/(SUM($D$13:$D$21)+SUM($D$25:$D$31)),0) -> 0 | K63: =IFERROR(K27+$D27*SUM(K$8+K$9+K$10+K$12+K$24+K$32+K$33)/(SUM($D$13:$D$21)+SUM($D$25:$D$31)),0) -> 0 | L63: =IFERROR(L27+$D27*SUM(L$8+L$9+L$10+L$12+L$24+L$32+L$33)/(SUM($D$13:$D$21)+SUM($D$25:$D$31)),0) -> 0 | M63: =IF(D63=0,0,J63/$D63*10000) -> 0 | N63: =IF(D63=0,0,K63/$D63*10000) -> 0 | O63: =IF(D63=0,0,L63/$D63*10000) -> 0 | W63: =E63 -> 0 | X63: =I63 -> 0 | Y63: =M63 -> 0 | Z63: =N63 -> 0 | AA63: =O63 -> 0 | AD63: C049063_$pcodej01$
B64: =B28 -> $pname7$集中商业 | C64: =IFERROR($C28+$D28*SUM($C$8+$C$9+$C$10+$C$12+$C$24+$C$32+$C$33)/(SUM($D$13:$D$21)+SUM($D$25:$D$31)),0) -> 0 | D64: =IFERROR($D28+$D28*($D$12+$D$24)/(SUM($D$13:$D$21)+SUM($D$25:$D$31)),0) -> 0 | E64: =IF(D64=0,0,C64*10000/D64) -> 0 | F64: =IFERROR($F28+$F28*($F$12+$F$24)/(SUM($F$13:$F$21)+SUM($F$25:$F$31)),0) -> 0 | G64: =IF(F64=0,0,C64*10000/F64) -> 0 | H64: =H28 -> 0 | I64: =IF(H64=0,0,C64*10000/H64) -> 0 | J64: =IFERROR(J28+$D28*SUM(J$8+J$9+J$10+J$12+J$24+J$32+J$33)/(SUM($D$13:$D$21)+SUM($D$25:$D$31)),0) -> 0 | K64: =IFERROR(K28+$D28*SUM(K$8+K$9+K$10+K$12+K$24+K$32+K$33)/(SUM($D$13:$D$21)+SUM($D$25:$D$31)),0) -> 0 | L64: =IFERROR(L28+$D28*SUM(L$8+L$9+L$10+L$12+L$24+L$32+L$33)/(SUM($D$13:$D$21)+SUM($D$25:$D$31)),0) -> 0 | M64: =IF(D64=0,0,J64/$D64*10000) -> 0 | N64: =IF(D64=0,0,K64/$D64*10000) -> 0 | O64: =IF(D64=0,0,L64/$D64*10000) -> 0 | AD64: C049064_$pcode7$
B65: =B29 -> $pname8$写字楼 | C65: =IFERROR($C29+$D29*SUM($C$8+$C$9+$C$10+$C$12+$C$24+$C$32+$C$33)/(SUM($D$13:$D$21)+SUM($D$25:$D$31)),0) -> 0 | D65: =IFERROR($D29+$D29*($D$12+$D$24)/(SUM($D$13:$D$21)+SUM($D$25:$D$31)),0) -> 0 | E65: =IF(D65=0,0,C65*10000/D65) -> 0 | F65: =IFERROR($F29+$F29*($F$12+$F$24)/(SUM($F$13:$F$21)+SUM($F$25:$F$31)),0) -> 0 | G65: =IF(F65=0,0,C65*10000/F65) -> 0 | H65: =H29 -> 0 | I65: =IF(H65=0,0,C65*10000/H65) -> 0 | J65: =IFERROR(J29+$D29*SUM(J$8+J$9+J$10+J$12+J$24+J$32+J$33)/(SUM($D$13:$D$21)+SUM($D$25:$D$31)),0) -> 0 | K65: =IFERROR(K29+$D29*SUM(K$8+K$9+K$10+K$12+K$24+K$32+K$33)/(SUM($D$13:$D$21)+SUM($D$25:$D$31)),0) -> 0 | L65: =IFERROR(L29+$D29*SUM(L$8+L$9+L$10+L$12+L$24+L$32+L$33)/(SUM($D$13:$D$21)+SUM($D$25:$D$31)),0) -> 0 | M65: =IF(D65=0,0,J65/$D65*10000) -> 0 | N65: =IF(D65=0,0,K65/$D65*10000) -> 0 | O65: =IF(D65=0,0,L65/$D65*10000) -> 0 | AD65: C049065_$pcode8$
B66: =B30 -> $pname9$写字楼 | C66: =IFERROR($C30+$D30*SUM($C$8+$C$9+$C$10+$C$12+$C$24+$C$32+$C$33)/(SUM($D$13:$D$21)+SUM($D$25:$D$31)),0) -> 0 | D66: =IFERROR($D30+$D30*($D$12+$D$24)/(SUM($D$13:$D$21)+SUM($D$25:$D$31)),0) -> 0 | E66: =IF(D66=0,0,C66*10000/D66) -> 0 | F66: =IFERROR($F30+$F30*($F$12+$F$24)/(SUM($F$13:$F$21)+SUM($F$25:$F$31)),0) -> 0 | G66: =IF(F66=0,0,C66*10000/F66) -> 0 | H66: =H30 -> 0 | I66: =IF(H66=0,0,C66*10000/H66) -> 0 | J66: =IFERROR(J30+$D30*SUM(J$8+J$9+J$10+J$12+J$24+J$32+J$33)/(SUM($D$13:$D$21)+SUM($D$25:$D$31)),0) -> 0 | K66: =IFERROR(K30+$D30*SUM(K$8+K$9+K$10+K$12+K$24+K$32+K$33)/(SUM($D$13:$D$21)+SUM($D$25:$D$31)),0) -> 0 | L66: =IFERROR(L30+$D30*SUM(L$8+L$9+L$10+L$12+L$24+L$32+L$33)/(SUM($D$13:$D$21)+SUM($D$25:$D$31)),0) -> 0 | M66: =IF(D66=0,0,J66/$D66*10000) -> 0 | N66: =IF(D66=0,0,K66/$D66*10000) -> 0 | O66: =IF(D66=0,0,L66/$D66*10000) -> 0 | AD66: C049066_$pcode9$
B67: =B31 -> $pname10$酒店 | C67: =IFERROR($C31+$D31*SUM($C$8+$C$9+$C$10+$C$12+$C$24+$C$32+$C$33)/(SUM($D$13:$D$21)+SUM($D$25:$D$31)),0) -> 0 | D67: =IFERROR($D31+$D31*($D$12+$D$24)/(SUM($D$13:$D$21)+SUM($D$25:$D$31)),0) -> 0 | E67: =IF(D67=0,0,C67*10000/D67) -> 0 | F67: =IFERROR($F31+$F31*($F$12+$F$24)/(SUM($F$13:$F$21)+SUM($F$25:$F$31)),0) -> 0 | G67: =IF(F67=0,0,C67*10000/F67) -> 0 | H67: =H31 -> 0 | I67: =IF(H67=0,0,C67*10000/H67) -> 0 | J67: =IFERROR(J31+$D31*SUM(J$8+J$9+J$10+J$12+J$24+J$32+J$33)/(SUM($D$13:$D$21)+SUM($D$25:$D$31)),0) -> 0 | K67: =IFERROR(K31+$D31*SUM(K$8+K$9+K$10+K$12+K$24+K$32+K$33)/(SUM($D$13:$D$21)+SUM($D$25:$D$31)),0) -> 0 | L67: =IFERROR(L31+$D31*SUM(L$8+L$9+L$10+L$12+L$24+L$32+L$33)/(SUM($D$13:$D$21)+SUM($D$25:$D$31)),0) -> 0 | M67: =IF(D67=0,0,J67/$D67*10000) -> 0 | N67: =IF(D67=0,0,K67/$D67*10000) -> 0 | O67: =IF(D67=0,0,L67/$D67*10000) -> 0 | AD67: C049067_$pcode10$
A68: 商业_x000D_ 建安成本 | B68: =B61 -> $pnames01$集中商业 | C68: =IFERROR($C25+$D25*SUM($C$8+$C$9+$C$10+$C$12+$C$24+$C$32+$C$33+$C$45+$C$46+$C$47)/(SUM($D$13:$D$21)+SUM($D$25:$D$31)),0) -> 0 | D68: =IFERROR($D25+$D25*($D$12+$D$24)/(SUM($D$13:$D$21)+SUM($D$25:$D$31)),0) -> 0 | E68: =IF(D68=0,0,C68*10000/D68) -> 0 | F68: =IFERROR($D25+$D25*($D$12+$D$24)/(SUM($D$13:$D$21)+SUM($D$25:$D$31)),0) -> 0 | G68: =IF(F68=0,0,C68*10000/F68) -> 0 | H68: =H25 -> 0 | I68: =IF(H68=0,0,C68*10000/H68) -> 0 | AD68: C050068_$pcodes01$
B69: =B62 -> $pnamex01$写字楼 | C69: =IFERROR($C26+$D26*SUM($C$8+$C$9+$C$10+$C$12+$C$24+$C$32+$C$33+$C$45+$C$46+$C$47)/(SUM($D$13:$D$21)+SUM($D$25:$D$31)),0) -> 0 | D69: =IFERROR($D26+$D26*($D$12+$D$24)/(SUM($D$13:$D$21)+SUM($D$25:$D$31)),0) -> 0 | E69: =IF(D69=0,0,C69*10000/D69) -> 0 | F69: =IFERROR($D26+$D26*($D$12+$D$24)/(SUM($D$13:$D$21)+SUM($D$25:$D$31)),0) -> 0 | G69: =IF(F69=0,0,C69*10000/F69) -> 0 | H69: =H26 -> 0 | I69: =IF(H69=0,0,C69*10000/H69) -> 0 | AD69: C050069_$pcodex01$
B70: =B63 -> $pnamej01$酒店 | C70: =IFERROR($C27+$D27*SUM($C$8+$C$9+$C$10+$C$12+$C$24+$C$32+$C$33+$C$45+$C$46+$C$47)/(SUM($D$13:$D$21)+SUM($D$25:$D$31)),0) -> 0 | D70: =IFERROR($D27+$D27*($D$12+$D$24)/(SUM($D$13:$D$21)+SUM($D$25:$D$31)),0) -> 0 | E70: =IF(D70=0,0,C70*10000/D70) -> 0 | F70: =IFERROR($D27+$D27*($D$12+$D$24)/(SUM($D$13:$D$21)+SUM($D$25:$D$31)),0) -> 0 | G70: =IF(F70=0,0,C70*10000/F70) -> 0 | H70: =H27 -> 0 | I70: =IF(H70=0,0,C70*10000/H70) -> 0 | AD70: C050070_$pcodej01$
B71: =B64 -> $pname7$集中商业 | C71: =IFERROR($C28+$D28*SUM($C$8+$C$9+$C$10+$C$12+$C$24+$C$32+$C$33+$C$45+$C$46+$C$47)/(SUM($D$13:$D$21)+SUM($D$25:$D$31)),0) -> 0 | D71: =IFERROR($D28+$D28*($D$12+$D$24)/(SUM($D$13:$D$21)+SUM($D$25:$D$31)),0) -> 0 | E71: =IF(D71=0,0,C71*10000/D71) -> 0 | F71: =IFERROR($D28+$D28*($D$12+$D$24)/(SUM($D$13:$D$21)+SUM($D$25:$D$31)),0) -> 0 | G71: =IF(F71=0,0,C71*10000/F71) -> 0 | H71: =H28 -> 0 | I71: =IF(H71=0,0,C71*10000/H71) -> 0 | AD71: C050071_$pcode7$
B72: =B65 -> $pname8$写字楼 | C72: =IFERROR($C29+$D29*SUM($C$8+$C$9+$C$10+$C$12+$C$24+$C$32+$C$33+$C$45+$C$46+$C$47)/(SUM($D$13:$D$21)+SUM($D$25:$D$31)),0) -> 0 | D72: =IFERROR($D29+$D29*($D$12+$D$24)/(SUM($D$13:$D$21)+SUM($D$25:$D$31)),0) -> 0 | E72: =IF(D72=0,0,C72*10000/D72) -> 0 | F72: =IFERROR($D29+$D29*($D$12+$D$24)/(SUM($D$13:$D$21)+SUM($D$25:$D$31)),0) -> 0 | G72: =IF(F72=0,0,C72*10000/F72) -> 0 | H72: =H29 -> 0 | I72: =IF(H72=0,0,C72*10000/H72) -> 0 | AD72: C050072_$pcode8$
B73: =B66 -> $pname9$写字楼 | C73: =IFERROR($C30+$D30*SUM($C$8+$C$9+$C$10+$C$12+$C$24+$C$32+$C$33+$C$45+$C$46+$C$47)/(SUM($D$13:$D$21)+SUM($D$25:$D$31)),0) -> 0 | D73: =IFERROR($D30+$D30*($D$12+$D$24)/(SUM($D$13:$D$21)+SUM($D$25:$D$31)),0) -> 0 | E73: =IF(D73=0,0,C73*10000/D73) -> 0 | F73: =IFERROR($D30+$D30*($D$12+$D$24)/(SUM($D$13:$D$21)+SUM($D$25:$D$31)),0) -> 0 | G73: =IF(F73=0,0,C73*10000/F73) -> 0 | H73: =H30 -> 0 | I73: =IF(H73=0,0,C73*10000/H73) -> 0 | AD73: C050073_$pcode9$
B74: =B67 -> $pname10$酒店 | C74: =IFERROR($C31+$D31*SUM($C$8+$C$9+$C$10+$C$12+$C$24+$C$32+$C$33+$C$45+$C$46+$C$47)/(SUM($D$13:$D$21)+SUM($D$25:$D$31)),0) -> 0 | D74: =IFERROR($D31+$D31*($D$12+$D$24)/(SUM($D$13:$D$21)+SUM($D$25:$D$31)),0) -> 0 | E74: =IF(D74=0,0,C74*10000/D74) -> 0 | F74: =IFERROR($D31+$D31*($D$12+$D$24)/(SUM($D$13:$D$21)+SUM($D$25:$D$31)),0) -> 0 | G74: =IF(F74=0,0,C74*10000/F74) -> 0 | H74: =H31 -> 0 | I74: =IF(H74=0,0,C74*10000/H74) -> 0 | AD74: C050074_$pcode10$

Sheet 05 成本测算明细
A1: 成本科目/测算明细 | C1: 测算基础信息 | F1: 含量/系数 | I1: 工程量 | K1: 综合单价 | M1: 测算成本(E=C*D)_x000D_ (万元) | N1: 相对建筑_x000D_ 面积(I)_x000D_ (㎡) | O1: 相对建筑_x000D_ 面积单方_x000D_ (J=E/I)_x000D_ (元/㎡) | P1: 相对建造_x000D_ 面积(K)_x000D_ (㎡) | Q1: 相对建造_x000D_ 面积单方_x000D_ (L=E/K)_x000D_ (元/㎡) | R1: 备注 | S1: 成本属性
C2: 说明 | D2: 值(A) | E2: 单位 | F2: 说明 | G2: 值(B) | H2: 单位 | I2: 值(C=A*B) | J2: 单位 | K2: 值(D) | L2: 单位
A3: 03建安 | D3: ='02 项目基础信息（输入）'!$D$4 -> 74626.755 | M3: =ROUND(M4+M29+M47+M93+M4164+M4190+M4241+M4252+M4281+M4310,6) -> 53408.719 | N3: ='02 项目基础信息（输入）'!$D$4 -> 74626.755 | O3: =ROUND(IFERROR(M3*10000/N3,0),2) -> 7156.78 | P3: ='02 项目基础信息（输入）'!$H$69+$N$3 -> 74626.755 | Q3: =ROUND(IFERROR(M3*10000/P3,0),2) -> 7156.78 | U3: C03
A4: 03.01前期工程 | C4: 总建筑面积 | D4: ='02 项目基础信息（输入）'!$D$4 -> 74626.755 | E4: ㎡ | M4: =ROUND(M5+M7+M9+M11+M13+M15+M17+M19+M21+M23+M25+M27,6) -> 325.90753 | N4: ='02 项目基础信息（输入）'!$D$4 -> 74626.755 | O4: =ROUND(IFERROR(M4*10000/N4,0),2) -> 43.67 | P4: ='02 项目基础信息（输入）'!$H$69+$N$3 -> 74626.755 | Q4: =ROUND(IFERROR(M4*10000/P4,0),2) -> 43.67 | S4: 暂定 | U4: C03.01
A5: 03.01.01临时供水 | C5: 总建筑面积 | D5: ='02 项目基础信息（输入）'!$D$4 -> 74626.755 | E5: ㎡ | M5: =ROUND(SUM(M6),6) -> 1.492535 | N5: ='02 项目基础信息（输入）'!$D$4 -> 74626.755 | O5: =ROUND(IFERROR(M5*10000/N5,0),2) -> 0.2 | P5: ='02 项目基础信息（输入）'!$H$69+$N$3 -> 74626.755 | Q5: =ROUND(IFERROR(M5*10000/P5,0),2) -> 0.2 | U5: C03.01.01
A6: 03.01.01.01临时供水 | C6: 总建筑面积 | D6: ='02 项目基础信息（输入）'!$D$4 -> 74626.755 | E6: ㎡ | F6: 总建筑面积 | G6: 1 | H6: ㎡/㎡ | I6: ='02 项目基础信息（输入）'!$D$4 -> 74626.755 | J6: ㎡ | K6: 0.2 | L6: 元/㎡ | M6: =ROUND(K6*I6/10000,6) -> 1.492535 | N6: ='02 项目基础信息（输入）'!$D$4 -> 74626.755 | O6: =ROUND(IFERROR(M6*10000/N6,0),2) -> 0.2 | P6: ='02 项目基础信息（输入）'!$H$69+$N$3 -> 74626.755 | Q6: =ROUND(IFERROR(M6*10000/P6,0),2) -> 0.2 | U6: C03.01.01.01
A7: 03.01.02临时排水 | C7: 总建筑面积 | D7: ='02 项目基础信息（输入）'!$D$4 -> 74626.755 | E7: ㎡ | M7: =ROUND(SUM(M8),6) -> 0 | N7: ='02 项目基础信息（输入）'!$D$4 -> 74626.755 | O7: =ROUND(IFERROR(M7*10000/N7,0),2) -> 0 | P7: ='02 项目基础信息（输入）'!$H$69+$N$3 -> 74626.755 | Q7: =ROUND(IFERROR(M7*10000/P7,0),2) -> 0 | U7: C03.01.02
A8: 03.01.02.01临时排水 | C8: 总建筑面积 | D8: ='02 项目基础信息（输入）'!$D$4 -> 74626.755 | E8: ㎡ | F8: 总建筑面积 | G8: 1 | H8: ㎡/㎡ | I8: ='02 项目基础信息（输入）'!$D$4 -> 74626.755 | J8: ㎡ | L8: 元/㎡ | M8: =ROUND(K8*I8/10000,6) -> 0 | N8: ='02 项目基础信息（输入）'!$D$4 -> 74626.755 | O8: =ROUND(IFERROR(M8*10000/N8,0),2) -> 0 | P8: ='02 项目基础信息（输入）'!$H$69+$N$3 -> 74626.755 | Q8: =ROUND(IFERROR(M8*10000/P8,0),2) -> 0 | U8: C03.01.02.01
A9: 03.01.03临时供电 | C9: 总建筑面积 | D9: ='02 项目基础信息（输入）'!$D$4 -> 74626.755 | E9: ㎡ | M9: =ROUND(SUM(M10),6) -> 60 | N9: ='02 项目基础信息（输入）'!$D$4 -> 74626.755 | O9: =ROUND(IFERROR(M9*10000/N9,0),2) -> 8.04 | P9: ='02 项目基础信息（输入）'!$H$69+$N$3 -> 74626.755 | Q9: =ROUND(IFERROR(M9*10000/P9,0),2) -> 8.04 | U9: C03.01.03
A10: 03.01.03.01临时供电 | C10: 总建筑面积 | D10: ='02 项目基础信息（输入）'!$D$4 -> 74626.755 | E10: ㎡ | F10: 总建筑面积 | G10: 1 | H10: ㎡/㎡ | I10: ='02 项目基础信息（输入）'!$D$4 -> 74626.755 | J10: ㎡ | K10: =60*10000/I10 -> 8.040012 | L10: 元/㎡ | M10: =ROUND(K10*I10/10000,6) -> 60 | N10: ='02 项目基础信息（输入）'!$D$4 -> 74626.755 | O10: =ROUND(IFERROR(M10*10000/N10,0),2) -> 8.04 | P10: ='02 项目基础信息（输入）'!$H$69+$N$3 -> 74626.755 | Q10: =ROUND(IFERROR(M10*10000/P10,0),2) -> 8.04 | R10: 2台临电参考禧宸30万/台（售楼处一台，大区施工一台） | U10: C03.01.03.01
A11: 03.01.04临时设施 | C11: 总建筑面积 | D11: ='02 项目基础信息（输入）'!$D$4 -> 74626.755 | E11: ㎡ | M11: =ROUND(SUM(M12),6) -> 71.5 | N11: ='02 项目基础信息（输入）'!$D$4 -> 74626.755 | O11: =ROUND(IFERROR(M11*10000/N11,0),2) -> 9.58 | P11: ='02 项目基础信息（输入）'!$H$69+$N$3 -> 74626.755 | Q11: =ROUND(IFERROR(M11*10000/P11,0),2) -> 9.58 | U11: C03.01.04
A12: 03.01.04.01临时设施 | C12: 总建筑面积 | D12: ='02 项目基础信息（输入）'!$D$4 -> 74626.755 | E12: ㎡ | F12: 总建筑面积 | G12: 1 | H12: ㎡/㎡ | I12: ='02 项目基础信息（输入）'!$D$4 -> 74626.755 | J12: ㎡ | K12: =550*1300/I12 -> 9.5810143 | L12: 元/㎡ | M12: =ROUND(K12*I12/10000,6) -> 71.5 | N12: ='02 项目基础信息（输入）'!$D$4 -> 74626.755 | O12: =ROUND(IFERROR(M12*10000/N12,0),2) -> 9.58 | P12: ='02 项目基础信息（输入）'!$H$69+$N$3 -> 74626.755 | Q12: =ROUND(IFERROR(M12*10000/P12,0),2) -> 9.58 | R12: 年度标单价 1300 元/m2；临时办公区面积暂估 550m2； | U12: C03.01.04.01
A13: 03.01.05临时道路 | C13: 总建筑面积 | D13: ='02 项目基础信息（输入）'!$D$4 -> 74626.755 | E13: ㎡ | M13: =ROUND(SUM(M14),6) -> 16.915 | N13: ='02 项目基础信息（输入）'!$D$4 -> 74626.755 | O13: =ROUND(IFERROR(M13*10000/N13,0),2) -> 2.27 | P13: ='02 项目基础信息（输入）'!$H$69+$N$3 -> 74626.755 | Q13: =ROUND(IFERROR(M13*10000/P13,0),2) -> 2.27 | U13: C03.01.05
A14: 03.01.05.01临时道路 | C14: 总建筑面积 | D14: ='02 项目基础信息（输入）'!$D$4 -> 74626.755 | E14: ㎡ | F14: 总建筑面积 | G14: 1 | H14: ㎡/㎡ | I14: ='02 项目基础信息（输入）'!$D$4 -> 74626.755 | J14: ㎡ | K14: 2.2666134 | L14: 元/㎡ | M14: =ROUND(K14*I14/10000,6) -> 16.915 | N14: ='02 项目基础信息（输入）'!$D$4 -> 74626.755 | O14: =ROUND(IFERROR(M14*10000/N14,0),2) -> 2.27 | P14: ='02 项目基础信息（输入）'!$H$69+$N$3 -> 74626.755 | Q14: =ROUND(IFERROR(M14*10000/P14,0),2) -> 2.27 | U14: C03.01.05.01
A15: 03.01.06临时围墙 | C15: 总建筑面积 | D15: ='02 项目基础信息（输入）'!$D$4 -> 74626.755 | E15: ㎡ | M15: =ROUND(SUM(M16),6) -> 119 | N15: ='02 项目基础信息（输入）'!$D$4 -> 74626.755 | O15: =ROUND(IFERROR(M15*10000/N15,0),2) -> 15.95 | P15: ='02 项目基础信息（输入）'!$H$69+$N$3 -> 74626.755 | Q15: =ROUND(IFERROR(M15*10000/P15,0),2) -> 15.95 | U15: C03.01.06
A16: 03.01.06.01临时围墙 | C16: 总建筑面积 | D16: ='02 项目基础信息（输入）'!$D$4 -> 74626.755 | E16: ㎡ | F16: 总建筑面积 | G16: 1 | H16: ㎡/㎡ | I16: ='02 项目基础信息（输入）'!$D$4 -> 74626.755 | J16: ㎡ | K16: =850*1400/I16 -> 15.946024 | L16: 元/㎡ | M16: =ROUND(K16*I16/10000,6) -> 119 | N16: ='02 项目基础信息（输入）'!$D$4 -> 74626.755 | O16: =ROUND(IFERROR(M16*10000/N16,0),2) -> 15.95 | P16: ='02 项目基础信息（输入）'!$H$69+$N$3 -> 74626.755 | Q16: =ROUND(IFERROR(M16*10000/P16,0),2) -> 15.95 | R16: 高度4m,延米长度850,参考年度标单价1400一延米 | U16: C03.01.06.01
A17: 03.01.07场地平整清理工程 | C17: 总建筑面积 | D17: ='02 项目基础信息（输入）'!$D$4 -> 74626.755 | E17: ㎡ | M17: =ROUND(SUM(M18),6) -> 0 | N17: ='02 项目基础信息（输入）'!$D$4 -> 74626.755 | O17: =ROUND(IFERROR(M17*10000/N17,0),2) -> 0 | P17: ='02 项目基础信息（输入）'!$H$69+$N$3 -> 74626.755 | Q17: =ROUND(IFERROR(M17*10000/P17,0),2) -> 0 | U17: C03.01.07
A18: 03.01.07.01场地平整清理工程 | C18: 总建筑面积 | D18: ='02 项目基础信息（输入）'!$D$4 -> 74626.755 | E18: ㎡ | F18: 总建筑面积 | G18: 1 | H18: ㎡/㎡ | I18: ='02 项目基础信息（输入）'!$D$4 -> 74626.755 | J18: ㎡ | L18: 元/㎡ | M18: =ROUND(K18*I18/10000,6) -> 0 | N18: ='02 项目基础信息（输入）'!$D$4 -> 74626.755 | O18: =ROUND(IFERROR(M18*10000/N18,0),2) -> 0 | P18: ='02 项目基础信息（输入）'!$H$69+$N$3 -> 74626.755 | Q18: =ROUND(IFERROR(M18*10000/P18,0),2) -> 0 | U18: C03.01.07.01
A19: 03.01.08白蚁防治工程 | C19: 总建筑面积 | D19: ='02 项目基础信息（输入）'!$D$4 -> 74626.755 | E19: ㎡ | M19: =ROUND(SUM(M20),6) -> 0 | N19: ='02 项目基础信息（输入）'!$D$4 -> 74626.755 | O19: =ROUND(IFERROR(M19*10000/N19,0),2) -> 0 | P19: ='02 项目基础信息（输入）'!$H$69+$N$3 -> 74626.755 | Q19: =ROUND(IFERROR(M19*10000/P19,0),2) -> 0 | U19: C03.01.08
A20: 03.01.08.01白蚁防治工程 | C20: 总建筑面积 | D20: ='02 项目基础信息（输入）'!$D$4 -> 74626.755 | E20: ㎡ | F20: 总建筑面积 | G20: 1 | H20: ㎡/㎡ | I20: ='02 项目基础信息（输入）'!$D$4 -> 74626.755 | J20: ㎡ | L20: 元/㎡ | M20: =ROUND(K20*I20/10000,6) -> 0 | N20: ='02 项目基础信息（输入）'!$D$4 -> 74626.755 | O20: =ROUND(IFERROR(M20*10000/N20,0),2) -> 0 | P20: ='02 项目基础信息（输入）'!$H$69+$N$3 -> 74626.755 | Q20: =ROUND(IFERROR(M20*10000/P20,0),2) -> 0 | U20: C03.01.08.01
A21: 03.01.09临时看护工程 | C21: 总建筑面积 | D21: ='02 项目基础信息（输入）'!$D$4 -> 74626.755 | E21: ㎡ | M21: =ROUND(SUM(M22),6) -> 0 | N21: ='02 项目基础信息（输入）'!$D$4 -> 74626.755 | O21: =ROUND(IFERROR(M21*10000/N21,0),2) -> 0 | P21: ='02 项目基础信息（输入）'!$H$69+$N$3 -> 74626.755 | Q21: =ROUND(IFERROR(M21*10000/P21,0),2) -> 0 | U21: C03.01.09
A22: 03.01.09.01临时看护工程 | C22: 总建筑面积 | D22: ='02 项目基础信息（输入）'!$D$4 -> 74626.755 | E22: ㎡ | F22: 总建筑面积 | G22: 1 | H22: ㎡/㎡ | I22: ='02 项目基础信息（输入）'!$D$4 -> 74626.755 | J22: ㎡ | L22: 元/㎡ | M22: =ROUND(K22*I22/10000,6) -> 0 | N22: ='02 项目基础信息（输入）'!$D$4 -> 74626.755 | O22: =ROUND(IFERROR(M22*10000/N22,0),2) -> 0 | P22: ='02 项目基础信息（输入）'!$H$69+$N$3 -> 74626.755 | Q22: =ROUND(IFERROR(M22*10000/P22,0),2) -> 0 | U22: C03.01.09.01
A23: 03.01.10红线内管道改造 | C23: 总建筑面积 | D23: ='02 项目基础信息（输入）'!$D$4 -> 74626.755 | E23: ㎡ | M23: =ROUND(SUM(M24),6) -> 0 | N23: ='02 项目基础信息（输入）'!$D$4 -> 74626.755 | O23: =ROUND(IFERROR(M23*10000/N23,0),2) -> 0 | P23: ='02 项目基础信息（输入）'!$H$69+$N$3 -> 74626.755 | Q23: =ROUND(IFERROR(M23*10000/P23,0),2) -> 0 | U23: C03.01.10
A24: 03.01.10.01红线内管道改造 | C24: 总建筑面积 | D24: ='02 项目基础信息（输入）'!$D$4 -> 74626.755 | E24: ㎡ | F24: 总建筑面积 | G24: 1 | H24: ㎡/㎡ | I24: ='02 项目基础信息（输入）'!$D$4 -> 74626.755 | J24: ㎡ | L24: 元/㎡ | M24: =ROUND(K24*I24/10000,6) -> 0 | N24: ='02 项目基础信息（输入）'!$D$4 -> 74626.755 | O24: =ROUND(IFERROR(M24*10000/N24,0),2) -> 0 | P24: ='02 项目基础信息（输入）'!$H$69+$N$3 -> 74626.755 | Q24: =ROUND(IFERROR(M24*10000/P24,0),2) -> 0 | U24: C03.01.10.01
A25: 03.01.11人防军事设施清除 | C25: 总建筑面积 | D25: ='02 项目基础信息（输入）'!$D$4 -> 74626.755 | E25: ㎡ | M25: =ROUND(SUM(M26),6) -> 0 | N25: ='02 项目基础信息（输入）'!$D$4 -> 74626.755 | O25: =ROUND(IFERROR(M25*10000/N25,0),2) -> 0 | P25: ='02 项目基础信息（输入）'!$H$69+$N$3 -> 74626.755 | Q25: =ROUND(IFERROR(M25*10000/P25,0),2) -> 0 | U25: C03.01.11
A26: 03.01.11.01人防军事设施清除 | C26: 总建筑面积 | D26: ='02 项目基础信息（输入）'!$D$4 -> 74626.755 | E26: ㎡ | F26: 总建筑面积 | G26: 1 | H26: ㎡/㎡ | I26: ='02 项目基础信息（输入）'!$D$4 -> 74626.755 | J26: ㎡ | L26: 元/㎡ | M26: =ROUND(K26*I26/10000,6) -> 0 | N26: ='02 项目基础信息（输入）'!$D$4 -> 74626.755 | O26: =ROUND(IFERROR(M26*10000/N26,0),2) -> 0 | P26: ='02 项目基础信息（输入）'!$H$69+$N$3 -> 74626.755 | Q26: =ROUND(IFERROR(M26*10000/P26,0),2) -> 0 | U26: C03.01.11.01
A27: 03.01.12其他前期工程 | C27: 总建筑面积 | D27: ='02 项目基础信息（输入）'!$D$4 -> 74626.755 | E27: ㎡ | M27: =ROUND(SUM(M28),6) -> 57 | N27: ='02 项目基础信息（输入）'!$D$4 -> 74626.755 | O27: =ROUND(IFERROR(M27*10000/N27,0),2) -> 7.64 | P27: ='02 项目基础信息（输入）'!$H$69+$N$3 -> 74626.755 | Q27: =ROUND(IFERROR(M27*10000/P27,0),2) -> 7.64 | U27: C03.01.12
A28: 03.01.12.01其他前期工程 | C28: 总建筑面积 | D28: ='02 项目基础信息（输入）'!$D$4 -> 74626.755 | E28: ㎡ | F28: 总建筑面积 | G28: 1 | H28: ㎡/㎡ | I28: ='02 项目基础信息（输入）'!$D$4 -> 74626.755 | J28: ㎡ | K28: =570000/I28 -> 7.6380114 | L28: 元/㎡ | M28: =ROUND(K28*I28/10000,6) -> 57 | N28: ='02 项目基础信息（输入）'!$D$4 -> 74626.755 | O28: =ROUND(IFERROR(M28*10000/N28,0),2) -> 7.64 | P28: ='02 项目基础信息（输入）'!$H$69+$N$3 -> 74626.755 | Q28: =ROUND(IFERROR(M28*10000/P28,0),2) -> 7.64 | R28: 临时/正式道口开挖涉及绿化、管线、道路等迁改补偿费 30万；临时用地 4.5 亩，第一年租金 9 万，第二年 18 万，合计租金 27 万；生活区租地在总包范围，不考虑 | U28: C03.01.12.01
A29: 03.02桩基础工程 | C29: 总建筑面积 | D29: ='02 项目基础信息（输入）'!$D$4 -> 74626.755 | E29: ㎡ | M29: =ROUND(M30+M41+M43+M45,6) -> 1599.5578 | N29: ='02 项目基础信息（输入）'!$D$4 -> 74626.755 | O29: =ROUND(IFERROR(M29*10000/N29,0),2) -> 214.34 | P29: ='02 项目基础信息（输入）'!$H$69+$N$3 -> 74626.755 | Q29: =ROUND(IFERROR(M29*10000/P29,0),2) -> 214.34 | S29: 暂定 | U29: C03.02
A30: 03.02.01桩基工程 | C30: 总建筑面积 | D30: ='02 项目基础信息（输入）'!$D$4 -> 74626.755 | E30: ㎡ | M30: =ROUND(SUM(M31:M40),6) -> 1476.8522 | N30: ='02 项目基础信息（输入）'!$D$4 -> 74626.755 | O30: =ROUND(IFERROR(M30*10000/N30,0),2) -> 197.9 | P30: ='02 项目基础信息（输入）'!$H$69+$N$3 -> 74626.755 | Q30: =ROUND(IFERROR(M30*10000/P30,0),2) -> 197.9 | U30: C03.02.01
A31: 03.02.01.01试桩工程 | C31: 总建筑面积 | D31: ='02 项目基础信息（输入）'!$D$4 -> 74626.755 | E31: ㎡ | F31: 桩长含量 | G31: =IFERROR(I31/D31,0) -> 0.25937079 | H31: m/㎡ | I31: =桩基!M15 -> 19356 | J31: m | K31: =桩基!H15 -> 762.99453 | L31: 元/m | M31: =ROUND(K31*I31/10000,6) -> 1476.8522 | N31: ='02 项目基础信息（输入）'!$D$4 -> 74626.755 | O31: =ROUND(IFERROR(M31*10000/N31,0),2) -> 197.9 | P31: ='02 项目基础信息（输入）'!$H$69+$N$3 -> 74626.755 | Q31: =ROUND(IFERROR(M31*10000/P31,0),2) -> 197.9 | U31: C03.02.01.01
A32: 03.02.01.02预制混凝土方桩 | C32: 总建筑面积 | D32: ='02 项目基础信息（输入）'!$D$4 -> 74626.755 | E32: ㎡ | F32: 桩长含量 | G32: =IFERROR(I32/D32,0) -> 0 | H32: m/㎡ | J32: m | L32: 元/m | M32: =ROUND(K32*I32/10000,6) -> 0 | N32: ='02 项目基础信息（输入）'!$D$4 -> 74626.755 | O32: =ROUND(IFERROR(M32*10000/N32,0),2) -> 0 | P32: ='02 项目基础信息（输入）'!$H$69+$N$3 -> 74626.755 | Q32: =ROUND(IFERROR(M32*10000/P32,0),2) -> 0 | U32: C03.02.01.02
A33: 03.02.01.03预应力混凝土管桩 | C33: 总建筑面积 | D33: ='02 项目基础信息（输入）'!$D$4 -> 74626.755 | E33: ㎡ | F33: 桩长含量 | G33: =IFERROR(I33/D33,0) -> 0 | H33: m/㎡ | J33: m | L33: 元/m | M33: =ROUND(K33*I33/10000,6) -> 0 | N33: ='02 项目基础信息（输入）'!$D$4 -> 74626.755 | O33: =ROUND(IFERROR(M33*10000/N33,0),2) -> 0 | P33: ='02 项目基础信息（输入）'!$H$69+$N$3 -> 74626.755 | Q33: =ROUND(IFERROR(M33*10000/P33,0),2) -> 0 | U33: C03.02.01.03
A34: 03.02.01.04钢桩 | C34: 总建筑面积 | D34: ='02 项目基础信息（输入）'!$D$4 -> 74626.755 | E34: ㎡ | F34: 桩长含量 | G34: =IFERROR(I34/D34,0) -> 0 | H34: m/㎡ | J34: m | L34: 元/m | M34: =ROUND(K34*I34/10000,6) -> 0 | N34: ='02 项目基础信息（输入）'!$D$4 -> 74626.755 | O34: =ROUND(IFERROR(M34*10000/N34,0),2) -> 0 | P34: ='02 项目基础信息（输入）'!$H$69+$N$3 -> 74626.755 | Q34: =ROUND(IFERROR(M34*10000/P34,0),2) -> 0 | U34: C03.02.01.04
A35: 03.02.01.05钢管桩 | C35: 总建筑面积 | D35: ='02 项目基础信息（输入）'!$D$4 -> 74626.755 | E35: ㎡ | F35: 桩长含量 | G35: =IFERROR(I35/D35,0) -> 0 | H35: m/㎡ | J35: m | L35: 元/m | M35: =ROUND(K35*I35/10000,6) -> 0 | N35: ='02 项目基础信息（输入）'!$D$4 -> 74626.755 | O35: =ROUND(IFERROR(M35*10000/N35,0),2) -> 0 | P35: ='02 项目基础信息（输入）'!$H$69+$N$3 -> 74626.755 | Q35: =ROUND(IFERROR(M35*10000/P35,0),2) -> 0 | U35: C03.02.01.05
A36: 03.02.01.06干作业成孔灌注桩 | C36: 总建筑面积 | D36: ='02 项目基础信息（输入）'!$D$4 -> 74626.755 | E36: ㎡ | F36: 桩长含量 | G36: =IFERROR(I36/D36,0) -> 0 | H36: m/㎡ | J36: m | L36: 元/m | M36: =ROUND(K36*I36/10000,6) -> 0 | N36: ='02 项目基础信息（输入）'!$D$4 -> 74626.755 | O36: =ROUND(IFERROR(M36*10000/N36,0),2) -> 0 | P36: ='02 项目基础信息（输入）'!$H$69+$N$3 -> 74626.755 | Q36: =ROUND(IFERROR(M36*10000/P36,0),2) -> 0 | U36: C03.02.01.06
A37: 03.02.01.07泥浆护壁成孔灌注桩 | C37: 总建筑面积 | D37: ='02 项目基础信息（输入）'!$D$4 -> 74626.755 | E37: ㎡ | F37: 桩长含量 | G37: =IFERROR(I37/D37,0) -> 0 | H37: m/㎡ | J37: m | L37: 元/m | M37: =ROUND(K37*I37/10000,6) -> 0 | N37: ='02 项目基础信息（输入）'!$D$4 -> 74626.755 | O37: =ROUND(IFERROR(M37*10000/N37,0),2) -> 0 | P37: ='02 项目基础信息（输入）'!$H$69+$N$3 -> 74626.755 | Q37: =ROUND(IFERROR(M37*10000/P37,0),2) -> 0 | U37: C03.02.01.07
A38: 03.02.01.08人工挖孔灌注桩 | C38: 总建筑面积 | D38: ='02 项目基础信息（输入）'!$D$4 -> 74626.755 | E38: ㎡ | F38: 桩长含量 | G38: =IFERROR(I38/D38,0) -> 0 | H38: m/㎡ | J38: m | L38: 元/m | M38: =ROUND(K38*I38/10000,6) -> 0 | N38: ='02 项目基础信息（输入）'!$D$4 -> 74626.755 | O38: =ROUND(IFERROR(M38*10000/N38,0),2) -> 0 | P38: ='02 项目基础信息（输入）'!$H$69+$N$3 -> 74626.755 | Q38: =ROUND(IFERROR(M38*10000/P38,0),2) -> 0 | U38: C03.02.01.08
A39: 03.02.01.09抗拔锚杆/抗拔桩 | C39: 总建筑面积 | D39: ='02 项目基础信息（输入）'!$D$4 -> 74626.755 | E39: ㎡ | F39: 桩长含量 | G39: =IFERROR(I39/D39,0) -> 0 | H39: m/㎡ | J39: m | L39: 元/m | M39: =ROUND(K39*I39/10000,6) -> 0 | N39: ='02 项目基础信息（输入）'!$D$4 -> 74626.755 | O39: =ROUND(IFERROR(M39*10000/N39,0),2) -> 0 | P39: ='02 项目基础信息（输入）'!$H$69+$N$3 -> 74626.755 | Q39: =ROUND(IFERROR(M39*10000/P39,0),2) -> 0 | U39: C03.02.01.09
A40: 03.02.01.10其他类型桩基 | C40: 总建筑面积 | D40: ='02 项目基础信息（输入）'!$D$4 -> 74626.755 | E40: ㎡ | F40: 桩长含量 | G40: =IFERROR(I40/D40,0) -> 0 | H40: m/㎡ | J40: m | L40: 元/m | M40: =ROUND(K40*I40/10000,6) -> 0 | N40: ='02 项目基础信息（输入）'!$D$4 -> 74626.755 | O40: =ROUND(IFERROR(M40*10000/N40,0),2) -> 0 | P40: ='02 项目基础信息（输入）'!$H$69+$N$3 -> 74626.755 | Q40: =ROUND(IFERROR(M40*10000/P40,0),2) -> 0 | U40: C03.02.01.10
A41: 03.02.02桩基检测 | C41: 总建筑面积 | D41: ='02 项目基础信息（输入）'!$D$4 -> 74626.755 | E41: ㎡ | M41: =ROUND(SUM(M42),6) -> 111.51159 | N41: ='02 项目基础信息（输入）'!$D$4 -> 74626.755 | O41: =ROUND(IFERROR(M41*10000/N41,0),2) -> 14.94 | P41: ='02 项目基础信息（输入）'!$H$69+$N$3 -> 74626.755 | Q41: =ROUND(IFERROR(M41*10000/P41,0),2) -> 14.94 | U41: C03.02.02
A42: 03.02.02.01桩基检测 | C42: 总建筑面积 | D42: ='02 项目基础信息（输入）'!$D$4 -> 74626.755 | E42: ㎡ | F42: 总建筑面积 | G42: 1 | H42: ㎡/㎡ | I42: =ROUND(G42*D42,2) -> 74626.75 | J42: ㎡ | K42: =桩基!K28 -> 14.942577 | L42: 元/㎡ | M42: =ROUND(K42*I42/10000,6) -> 111.51159 | N42: ='02 项目基础信息（输入）'!$D$4 -> 74626.755 | O42: =ROUND(IFERROR(M42*10000/N42,0),2) -> 14.94 | P42: ='02 项目基础信息（输入）'!$H$69+$N$3 -> 74626.755 | Q42: =ROUND(IFERROR(M42*10000/P42,0),2) -> 14.94 | U42: C03.02.02.01
A43: 03.02.03沉降观测工程 | C43: 总建筑面积 | D43: ='02 项目基础信息（输入）'!$D$4 -> 74626.755 | E43: ㎡ | M43: =ROUND(SUM(M44),6) -> 11.194013 | N43: ='02 项目基础信息（输入）'!$D$4 -> 74626.755 | O43: =ROUND(IFERROR(M43*10000/N43,0),2) -> 1.5 | P43: ='02 项目基础信息（输入）'!$H$69+$N$3 -> 74626.755 | Q43: =ROUND(IFERROR(M43*10000/P43,0),2) -> 1.5 | U43: C03.02.03
A44: 03.02.03.01沉降观测工程 | C44: 总建筑面积 | D44: ='02 项目基础信息（输入）'!$D$4 -> 74626.755 | E44: ㎡ | F44: 总建筑面积 | G44: 1 | H44: ㎡/㎡ | I44: =ROUND(G44*D44,2) -> 74626.75 | J44: ㎡ | K44: =桩基!K30 -> 1.5 | L44: 元/㎡ | M44: =ROUND(K44*I44/10000,6) -> 11.194013 | N44: ='02 项目基础信息（输入）'!$D$4 -> 74626.755 | O44: =ROUND(IFERROR(M44*10000/N44,0),2) -> 1.5 | P44: ='02 项目基础信息（输入）'!$H$69+$N$3 -> 74626.755 | Q44: =ROUND(IFERROR(M44*10000/P44,0),2) -> 1.5 | U44: C03.02.03.01
A45: 03.02.04其他 | C45: 总建筑面积 | D45: ='02 项目基础信息（输入）'!$D$4 -> 74626.755 | E45: ㎡ | M45: =ROUND(SUM(M46),6) -> 0 | N45: ='02 项目基础信息（输入）'!$D$4 -> 74626.755 | O45: =ROUND(IFERROR(M45*10000/N45,0),2) -> 0 | P45: ='02 项目基础信息（输入）'!$H$69+$N$3 -> 74626.755 | Q45: =ROUND(IFERROR(M45*10000/P45,0),2) -> 0 | U45: C03.02.04
A46: 03.02.04.01其他桩基工程 | C46: 总建筑面积 | D46: ='02 项目基础信息（输入）'!$D$4 -> 74626.755 | E46: ㎡ | F46: 总建筑面积 | G46: 1 | H46: ㎡/㎡ | I46: =ROUND(G46*D46,2) -> 74626.75 | J46: ㎡ | L46: 元/㎡ | M46: =ROUND(K46*I46/10000,6) -> 0 | N46: ='02 项目基础信息（输入）'!$D$4 -> 74626.755 | O46: =ROUND(IFERROR(M46*10000/N46,0),2) -> 0 | P46: ='02 项目基础信息（输入）'!$H$69+$N$3 -> 74626.755 | Q46: =ROUND(IFERROR(M46*10000/P46,0),2) -> 0 | U46: C03.02.04.01
A47: 03.03岩土工程 | C47: 总建筑面积 | D47: ='02 项目基础信息（输入）'!$D$4 -> 74626.755 | E47: ㎡ | M47: =ROUND(M48+M61+M76+M84+M91,6) -> 2510.4349 | N47: ='02 项目基础信息（输入）'!$D$4 -> 74626.755 | O47: =ROUND(IFERROR(M47*10000/N47,0),2) -> 336.4 | P47: ='02 项目基础信息（输入）'!$H$69+$N$3 -> 74626.755 | Q47: =ROUND(IFERROR(M47*10000/P47,0),2) -> 336.4 | S47: 暂定 | U47: C03.03
A48: 03.03.01土方工程 | C48: 总建筑面积 | D48: ='02 项目基础信息（输入）'!$D$4 -> 74626.755 | E48: ㎡ | M48: =ROUND(SUM(M49:M60),6) -> 1577.1158 | N48: ='02 项目基础信息（输入）'!$D$4 -> 74626.755 | O48: =ROUND(IFERROR(M48*10000/N48,0),2) -> 211.33 | P48: ='02 项目基础信息（输入）'!$H$69+$N$3 -> 74626.755 | Q48: =ROUND(IFERROR(M48*10000/P48,0),2) -> 211.33 | U48: C03.03.01
A49: 03.03.01.01基坑土方开挖及外运 | C49: 基坑面积 | D49: ='02 项目基础信息（输入）'!$D$15 -> 24661 | E49: ㎡ | F49: 土方含量 | G49: =IFERROR(I49/D49,0) -> 5.6324399 | H49: m3/㎡ | I49: =土方!G9 -> 138901.6 | J49: m3 | K49: =土方!H9 -> 110 | L49: 元/m3 | M49: =ROUND(K49*I49/10000,6) -> 1527.9176 | N49: ='02 项目基础信息（输入）'!$D$4 -> 74626.755 | O49: =ROUND(IFERROR(M49*10000/N49,0),2) -> 204.74 | P49: ='02 项目基础信息（输入）'!$H$69+$N$3 -> 74626.755 | Q49: =ROUND(IFERROR(M49*10000/P49,0),2) -> 204.74 | U49: C03.03.01.01
A50: 03.03.01.02地库侧墙土方回填 | C50: 基坑面积 | D50: ='02 项目基础信息（输入）'!$D$15 -> 24661 | E50: ㎡ | F50: 土方含量 | G50: =IFERROR(I50/D50,0) -> 0.26708771 | H50: m3/m2 | I50: =土方!G11 -> 6586.65 | J50: m3 | K50: =土方!H11 -> 50 | L50: 元/m3 | M50: =ROUND(K50*I50/10000,6) -> 32.93325 | N50: ='02 项目基础信息（输入）'!$D$4 -> 74626.755 | O50: =ROUND(IFERROR(M50*10000/N50,0),2) -> 4.41 | P50: ='02 项目基础信息（输入）'!$H$69+$N$3 -> 74626.755 | Q50: =ROUND(IFERROR(M50*10000/P50,0),2) -> 4.41 | U50: C03.03.01.02
A51: 03.03.01.03地库顶板土方回填 | C51: 基坑面积 | D51: ='02 项目基础信息（输入）'!$D$15 -> 24661 | E51: ㎡ | F51: 土方含量 | G51: =IFERROR(I51/D51,0) -> 1.3190852 | H51: m3/m2 | I51: =土方!G12 -> 32529.96 | J51: m3 | K51: =土方!H12 -> 5 | L51: 元/m3 | M51: =ROUND(K51*I51/10000,6) -> 16.26498 | N51: ='02 项目基础信息（输入）'!$D$4 -> 74626.755 | O51: =ROUND(IFERROR(M51*10000/N51,0),2) -> 2.18 | P51: ='02 项目基础信息（输入）'!$H$69+$N$3 -> 74626.755 | Q51: =ROUND(IFERROR(M51*10000/P51,0),2) -> 2.18 | U51: C03.03.01.03
A52: 03.03.01.04地下障碍物清除 | C52: 基坑面积 | D52: ='02 项目基础信息（输入）'!$D$15 -> 24661 | E52: ㎡ | F52: 基坑面积 | G52: =IFERROR(I52/D52,0) -> 0 | H52: m3/m2 | J52: m3 | L52: 元/m3 | M52: =ROUND(K52*I52/10000,6) -> 0 | N52: ='02 项目基础信息（输入）'!$D$4 -> 74626.755 | O52: =ROUND(IFERROR(M52*10000/N52,0),2) -> 0 | P52: ='02 项目基础信息（输入）'!$H$69+$N$3 -> 74626.755 | Q52: =ROUND(IFERROR(M52*10000/P52,0),2) -> 0 | U52: C03.03.01.04
A53: 03.03.01.05其他土方工程 | C53: 基坑面积 | D53: ='02 项目基础信息（输入）'!$D$15 -> 24661 | E53: ㎡ | F53: 土方含量 | G53: =IFERROR(I53/D53,0) -> 0 | H53: m3/m2 | J53: m3 | L53: 元/m3 | M53: =ROUND(K53*I53/10000,6) -> 0 | N53: ='02 项目基础信息（输入）'!$D$4 -> 74626.755 | O53: =ROUND(IFERROR(M53*10000/N53,0),2) -> 0 | P53: ='02 项目基础信息（输入）'!$H$69+$N$3 -> 74626.755 | Q53: =ROUND(IFERROR(M53*10000/P53,0),2) -> 0 | U53: C03.03.01.05
A54: 03.03.01.06基坑土方开挖及内倒回填 | C54: 基坑面积 | D54: ='02 项目基础信息（输入）'!$D$15 -> 24661 | E54: ㎡ | F54: 土方含量 | G54: =IFERROR(I54/D54,0) -> 0 | H54: m3/㎡ | J54: m3 | L54: 元/m3 | M54: =ROUND(K54*I54/10000,6) -> 0 | N54: ='02 项目基础信息（输入）'!$D$4 -> 74626.755 | O54: =ROUND(IFERROR(M54*10000/N54,0),2) -> 0 | P54: ='02 项目基础信息（输入）'!$H$69+$N$3 -> 74626.755 | Q54: =ROUND(IFERROR(M54*10000/P54,0),2) -> 0 | U54: C03.03.01.06
A55: 03.03.01.07基坑土方开挖及外运（商业） | C55: 总建筑面积 | D55: =N55 -> 74626.755 | E55: ㎡ | F55: 土方含量 | G55: =IFERROR(I55/D55,0) -> 0 | H55: m³/㎡ | J55: m³ | L55: 元/m³ | M55: =ROUND(K55*I55/10000,6) -> 0 | N55: =N$3 -> 74626.755 | O55: =ROUND(IFERROR(M55*10000/N55,0),2) -> 0 | P55: ='02 项目基础信息（输入）'!$H$69+$N$3 -> 74626.755 | Q55: =ROUND(IFERROR(M55*10000/P55,0),2) -> 0 | U55: C03.03.01.07
A56: 03.03.01.08地库侧墙土方回填（商业） | C56: 总建筑面积 | D56: =N56 -> 74626.755 | E56: ㎡ | F56: 土方含量 | G56: =IFERROR(I56/D56,0) -> 0 | H56: m³/㎡ | J56: m³ | L56: 元/m³ | M56: =ROUND(K56*I56/10000,6) -> 0 | N56: =N$3 -> 74626.755 | O56: =ROUND(IFERROR(M56*10000/N56,0),2) -> 0 | P56: ='02 项目基础信息（输入）'!$H$69+$N$3 -> 74626.755 | Q56: =ROUND(IFERROR(M56*10000/P56,0),2) -> 0 | U56: C03.03.01.08
A57: 03.03.01.09地库顶板土方回填（商业） | C57: 总建筑面积 | D57: =N57 -> 74626.755 | E57: ㎡ | F57: 土方含量 | G57: =IFERROR(I57/D57,0) -> 0 | H57: m³/㎡ | J57: m³ | L57: 元/m³ | M57: =ROUND(K57*I57/10000,6) -> 0 | N57: =N$3 -> 74626.755 | O57: =ROUND(IFERROR(M57*10000/N57,0),2) -> 0 | P57: ='02 项目基础信息（输入）'!$H$69+$N$3 -> 74626.755 | Q57: =ROUND(IFERROR(M57*10000/P57,0),2) -> 0 | U57: C03.03.01.09
A58: 03.03.01.10地下障碍物清除（商业） | C58: 总建筑面积 | D58: =N58 -> 74626.755 | E58: ㎡ | F58: 地下障碍物含量 | G58: =IFERROR(I58/D58,0) -> 0 | H58: m³/㎡ | J58: m³ | L58: 元/m³ | M58: =ROUND(K58*I58/10000,6) -> 0 | N58: =N$3 -> 74626.755 | O58: =ROUND(IFERROR(M58*10000/N58,0),2) -> 0 | P58: ='02 项目基础信息（输入）'!$H$69+$N$3 -> 74626.755 | Q58: =ROUND(IFERROR(M58*10000/P58,0),2) -> 0 | U58: C03.03.01.10
A59: 03.03.01.11基坑土方开挖及内倒回填（商业） | C59: 总建筑面积 | D59: =N59 -> 74626.755 | E59: ㎡ | F59: 土方含量 | G59: =IFERROR(I59/D59,0) -> 0 | H59: m³/㎡ | J59: m³ | L59: 元/m³ | M59: =ROUND(K59*I59/10000,6) -> 0 | N59: =N$3 -> 74626.755 | O59: =ROUND(IFERROR(M59*10000/N59,0),2) -> 0 | P59: ='02 项目基础信息（输入）'!$H$69+$N$3 -> 74626.755 | Q59: =ROUND(IFERROR(M59*10000/P59,0),2) -> 0 | U59: C03.03.01.11
A60: 03.03.01.12其他土方工程（商业） | C60: 总建筑面积 | D60: =N60 -> 74626.755 | E60: ㎡ | F60: 土方含量 | G60: =IFERROR(I60/D60,0) -> 0 | H60: m³/㎡ | J60: m³ | L60: 元/m³ | M60: =ROUND(K60*I60/10000,6) -> 0 | N60: =N$3 -> 74626.755 | O60: =ROUND(IFERROR(M60*10000/N60,0),2) -> 0 | P60: ='02 项目基础信息（输入）'!$H$69+$N$3 -> 74626.755 | Q60: =ROUND(IFERROR(M60*10000/P60,0),2) -> 0 | U60: C03.03.01.12
A61: 03.03.02支护工程 | C61: 总建筑面积 | D61: ='02 项目基础信息（输入）'!$D$4 -> 74626.755 | E61: ㎡ | M61: =ROUND(SUM(M62:M75),6) -> 933.31909 | N61: ='02 项目基础信息（输入）'!$D$4 -> 74626.755 | O61: =ROUND(IFERROR(M61*10000/N61,0),2) -> 125.06 | P61: ='02 项目基础信息（输入）'!$H$69+$N$3 -> 74626.755 | Q61: =ROUND(IFERROR(M61*10000/P61,0),2) -> 125.06 | U61: C03.03.02
A62: 03.03.02.01钢筋混凝土挡墙 | C62: 基坑延米长度 | D62: ='02 项目基础信息（输入）'!$D$16 -> 861 | E62: 延米 | F62: 支护延米长度占比 | G62: =IFERROR(I62/D62,0) -> 1 | H62: m/m | I62: =D62 -> 861 | J62: m | K62: =支护!P23 -> 9513.8023 | L62: 元/m | M62: =ROUND(K62*I62/10000,6) -> 819.13838 | N62: ='02 项目基础信息（输入）'!$D$4 -> 74626.755 | O62: =ROUND(IFERROR(M62*10000/N62,0),2) -> 109.76 | P62: ='02 项目基础信息（输入）'!$H$69+$N$3 -> 74626.755 | Q62: =ROUND(IFERROR(M62*10000/P62,0),2) -> 109.76 | U62: C03.03.02.01
A63: 03.03.02.02咬合灌注桩 | C63: 基坑延米长度 | D63: ='02 项目基础信息（输入）'!$D$16 -> 861 | E63: 延米 | F63: 支护延米长度占比 | G63: =IFERROR(I63/D63,0) -> 0 | H63: m/m | J63: m | L63: 元/m | M63: =ROUND(K63*I63/10000,6) -> 0 | N63: ='02 项目基础信息（输入）'!$D$4 -> 74626.755 | O63: =ROUND(IFERROR(M63*10000/N63,0),2) -> 0 | P63: ='02 项目基础信息（输入）'!$H$69+$N$3 -> 74626.755 | Q63: =ROUND(IFERROR(M63*10000/P63,0),2) -> 0 | U63: C03.03.02.02
A64: 03.03.02.03圆木桩 | C64: 基坑延米长度 | D64: ='02 项目基础信息（输入）'!$D$16 -> 861 | E64: 延米 | F64: 支护延米长度占比 | G64: =IFERROR(I64/D64,0) -> 0 | H64: m/m | J64: m | L64: 元/m | M64: =ROUND(K64*I64/10000,6) -> 0 | N64: ='02 项目基础信息（输入）'!$D$4 -> 74626.755 | O64: =ROUND(IFERROR(M64*10000/N64,0),2) -> 0 | P64: ='02 项目基础信息（输入）'!$H$69+$N$3 -> 74626.755 | Q64: =ROUND(IFERROR(M64*10000/P64,0),2) -> 0 | U64: C03.03.02.03
A65: 03.03.02.04预制混凝土板桩 | C65: 基坑延米长度 | D65: ='02 项目基础信息（输入）'!$D$16 -> 861 | E65: 延米 | F65: 支护延米长度占比 | G65: =IFERROR(I65/D65,0) -> 0 | H65: m/m | J65: m | L65: 元/m | M65: =ROUND(K65*I65/10000,6) -> 0 | N65: ='02 项目基础信息（输入）'!$D$4 -> 74626.755 | O65: =ROUND(IFERROR(M65*10000/N65,0),2) -> 0 | P65: ='02 项目基础信息（输入）'!$H$69+$N$3 -> 74626.755 | Q65: =ROUND(IFERROR(M65*10000/P65,0),2) -> 0 | U65: C03.03.02.04
A66: 03.03.02.05型钢桩 | C66: 基坑延米长度 | D66: ='02 项目基础信息（输入）'!$D$16 -> 861 | E66: 延米 | F66: 支护延米长度占比 | G66: =IFERROR(I66/D66,0) -> 0 | H66: m/m | J66: m | L66: 元/m | M66: =ROUND(K66*I66/10000,6) -> 0 | N66: ='02 项目基础信息（输入）'!$D$4 -> 74626.755 | O66: =ROUND(IFERROR(M66*10000/N66,0),2) -> 0 | P66: ='02 项目基础信息（输入）'!$H$69+$N$3 -> 74626.755 | Q66: =ROUND(IFERROR(M66*10000/P66,0),2) -> 0 | U66: C03.03.02.05
A67: 03.03.02.06钢板桩 | C67: 基坑延米长度 | D67: ='02 项目基础信息（输入）'!$D$16 -> 861 | E67: 延米 | F67: 支护延米长度占比 | G67: =IFERROR(I67/D67,0) -> 0 | H67: m/m | J67: m | L67: 元/m | M67: =ROUND(K67*I67/10000,6) -> 0 | N67: ='02 项目基础信息（输入）'!$D$4 -> 74626.755 | O67: =ROUND(IFERROR(M67*10000/N67,0),2) -> 0 | P67: ='02 项目基础信息（输入）'!$H$69+$N$3 -> 74626.755 | Q67: =ROUND(IFERROR(M67*10000/P67,0),2) -> 0 | U67: C03.03.02.06
A68: 03.03.02.07锚杆（锚索）、土钉 | C68: 基坑延米长度 | D68: ='02 项目基础信息（输入）'!$D$16 -> 861 | E68: 延米 | F68: 支护延米长度占比 | G68: =IFERROR(I68/D68,0) -> 0 | H68: m/m | J68: m | L68: 元/m | M68: =ROUND(K68*I68/10000,6) -> 0 | N68: ='02 项目基础信息（输入）'!$D$4 -> 74626.755 | O68: =ROUND(IFERROR(M68*10000/N68,0),2) -> 0 | P68: ='02 项目基础信息（输入）'!$H$69+$N$3 -> 74626.755 | Q68: =ROUND(IFERROR(M68*10000/P68,0),2) -> 0 | U68: C03.03.02.07
A69: 03.03.02.08喷射混凝土 | C69: 基坑延米长度 | D69: ='02 项目基础信息（输入）'!$D$16 -> 861 | E69: 延米 | F69: 支护延米长度占比 | G69: =IFERROR(I69/D69,0) -> 0 | H69: m/m | J69: m | L69: 元/m | M69: =ROUND(K69*I69/10000,6) -> 0 | N69: ='02 项目基础信息（输入）'!$D$4 -> 74626.755 | O69: =ROUND(IFERROR(M69*10000/N69,0),2) -> 0 | P69: ='02 项目基础信息（输入）'!$H$69+$N$3 -> 74626.755 | Q69: =ROUND(IFERROR(M69*10000/P69,0),2) -> 0 | U69: C03.03.02.08
A70: 03.03.02.09喷射水泥砂浆 | C70: 基坑延米长度 | D70: ='02 项目基础信息（输入）'!$D$16 -> 861 | E70: 延米 | F70: 支护延米长度占比 | G70: =IFERROR(I70/D70,0) -> 0 | H70: m/m | J70: m | L70: 元/m | M70: =ROUND(K70*I70/10000,6) -> 0 | N70: ='02 项目基础信息（输入）'!$D$4 -> 74626.755 | O70: =ROUND(IFERROR(M70*10000/N70,0),2) -> 0 | P70: ='02 项目基础信息（输入）'!$H$69+$N$3 -> 74626.755 | Q70: =ROUND(IFERROR(M70*10000/P70,0),2) -> 0 | U70: C03.03.02.09
A71: 03.03.02.10钢筋混凝土支撑 | C71: 基坑延米长度 | D71: ='02 项目基础信息（输入）'!$D$16 -> 861 | E71: 延米 | F71: 支护延米长度占比 | G71: =IFERROR(I71/D71,0) -> 0 | H71: m/m | J71: m | L71: 元/m | M71: =ROUND(K71*I71/10000,6) -> 0 | N71: ='02 项目基础信息（输入）'!$D$4 -> 74626.755 | O71: =ROUND(IFERROR(M71*10000/N71,0),2) -> 0 | P71: ='02 项目基础信息（输入）'!$H$69+$N$3 -> 74626.755 | Q71: =ROUND(IFERROR(M71*10000/P71,0),2) -> 0 | U71: C03.03.02.10
A72: 03.03.02.11钢支撑 | C72: 基坑延米长度 | D72: ='02 项目基础信息（输入）'!$D$16 -> 861 | E72: 延米 | F72: 支护延米长度占比 | G72: =IFERROR(I72/D72,0) -> 0 | H72: m/m | J72: m | L72: 元/m | M72: =ROUND(K72*I72/10000,6) -> 0 | N72: ='02 项目基础信息（输入）'!$D$4 -> 74626.755 | O72: =ROUND(IFERROR(M72*10000/N72,0),2) -> 0 | P72: ='02 项目基础信息（输入）'!$H$69+$N$3 -> 74626.755 | Q72: =ROUND(IFERROR(M72*10000/P72,0),2) -> 0 | U72: C03.03.02.11
A73: 03.03.02.12基坑降水 | C73: 总建筑面积 | D73: ='02 项目基础信息（输入）'!$D$4 -> 74626.755 | E73: ㎡ | F73: 总建筑面积 | G73: 1 | H73: ㎡/㎡ | J73: ㎡ | L73: 元/㎡ | M73: =ROUND(K73*I73/10000,6) -> 0 | N73: ='02 项目基础信息（输入）'!$D$4 -> 74626.755 | O73: =ROUND(IFERROR(M73*10000/N73,0),2) -> 0 | P73: ='02 项目基础信息（输入）'!$H$69+$N$3 -> 74626.755 | Q73: =ROUND(IFERROR(M73*10000/P73,0),2) -> 0 | U73: C03.03.02.12
A74: 03.03.02.13基坑监测/检测 | C74: 总建筑面积 | D74: ='02 项目基础信息（输入）'!$D$4 -> 74626.755 | E74: ㎡ | F74: 总建筑面积 | G74: 1 | H74: ㎡/㎡ | I74: =D74 -> 74626.755 | J74: ㎡ | K74: =支护!D29 -> 15.300238 | L74: 元/㎡ | M74: =ROUND(K74*I74/10000,6) -> 114.18071 | N74: ='02 项目基础信息（输入）'!$D$4 -> 74626.755 | O74: =ROUND(IFERROR(M74*10000/N74,0),2) -> 15.3 | P74: ='02 项目基础信息（输入）'!$H$69+$N$3 -> 74626.755 | Q74: =ROUND(IFERROR(M74*10000/P74,0),2) -> 15.3 | U74: C03.03.02.13
A75: 03.03.02.14其他支护工程 | C75: 总建造面积 | D75: ='02 项目基础信息（输入）'!$D$4 -> 74626.755 | E75: ㎡ | F75: 总建筑面积 | G75: 1 | H75: ㎡/㎡ | J75: ㎡ | L75: 元/㎡ | M75: =ROUND(K75*I75/10000,6) -> 0 | N75: ='02 项目基础信息（输入）'!$D$4 -> 74626.755 | O75: =ROUND(IFERROR(M75*10000/N75,0),2) -> 0 | P75: ='02 项目基础信息（输入）'!$H$69+$N$3 -> 74626.755 | Q75: =ROUND(IFERROR(M75*10000/P75,0),2) -> 0 | U75: C03.03.02.14
A76: 03.03.03挡墙工程 | C76: 总建筑面积 | D76: ='02 项目基础信息（输入）'!$D$4 -> 74626.755 | E76: ㎡ | M76: =ROUND(SUM(M77:M83),6) -> 0 | N76: ='02 项目基础信息（输入）'!$D$4 -> 74626.755 | O76: =ROUND(IFERROR(M76*10000/N76,0),2) -> 0 | P76: ='02 项目基础信息（输入）'!$H$69+$N$3 -> 74626.755 | Q76: =ROUND(IFERROR(M76*10000/P76,0),2) -> 0 | U76: C03.03.03
A77: 03.03.03.01毛石挡墙 | C77: 基坑延米长度 | D77: ='02 项目基础信息（输入）'!$D$16 -> 861 | E77: 延米 | F77: 挡墙延米长度占比 | G77: =IFERROR(I77/D77,0) -> 0 | H77: m/㎡ | J77: m | L77: 元/m | M77: =ROUND(K77*I77/10000,6) -> 0 | N77: ='02 项目基础信息（输入）'!$D$4 -> 74626.755 | O77: =ROUND(IFERROR(M77*10000/N77,0),2) -> 0 | P77: ='02 项目基础信息（输入）'!$H$69+$N$3 -> 74626.755 | Q77: =ROUND(IFERROR(M77*10000/P77,0),2) -> 0 | U77: C03.03.03.01
A78: 03.03.03.02钢筋混凝土挡墙 | C78: 基坑延米长度 | D78: ='02 项目基础信息（输入）'!$D$16 -> 861 | E78: 延米 | F78: 挡墙延米长度占比 | G78: =IFERROR(I78/D78,0) -> 0 | H78: m/㎡ | J78: m | L78: 元/m | M78: =ROUND(K78*I78/10000,6) -> 0 | N78: ='02 项目基础信息（输入）'!$D$4 -> 74626.755 | O78: =ROUND(IFERROR(M78*10000/N78,0),2) -> 0 | P78: ='02 项目基础信息（输入）'!$H$69+$N$3 -> 74626.755 | Q78: =ROUND(IFERROR(M78*10000/P78,0),2) -> 0 | U78: C03.03.03.02
A79: 03.03.03.03格构梁挡墙 | C79: 基坑延米长度 | D79: ='02 项目基础信息（输入）'!$D$16 -> 861 | E79: 延米 | F79: 挡墙延米长度占比 | G79: =IFERROR(I79/D79,0) -> 0 | H79: m/㎡ | J79: m | L79: 元/m | M79: =ROUND(K79*I79/10000,6) -> 0 | N79: ='02 项目基础信息（输入）'!$D$4 -> 74626.755 | O79: =ROUND(IFERROR(M79*10000/N79,0),2) -> 0 | P79: ='02 项目基础信息（输入）'!$H$69+$N$3 -> 74626.755 | Q79: =ROUND(IFERROR(M79*10000/P79,0),2) -> 0 | U79: C03.03.03.03
A80: 03.03.03.04砌块挡墙 | C80: 基坑延米长度 | D80: ='02 项目基础信息（输入）'!$D$16 -> 861 | E80: 延米 | F80: 挡墙延米长度占比 | G80: =IFERROR(I80/D80,0) -> 0 | H80: m/㎡ | J80: m | L80: 元/m | M80: =ROUND(K80*I80/10000,6) -> 0 | N80: ='02 项目基础信息（输入）'!$D$4 -> 74626.755 | O80: =ROUND(IFERROR(M80*10000/N80,0),2) -> 0 | P80: ='02 项目基础信息（输入）'!$H$69+$N$3 -> 74626.755 | Q80: =ROUND(IFERROR(M80*10000/P80,0),2) -> 0 | U80: C03.03.03.04
A81: 03.03.03.05边坡工程 | C81: 基坑延米长度 | D81: ='02 项目基础信息（输入）'!$D$16 -> 861 | E81: 延米 | F81: 挡墙延米长度占比 | G81: =IFERROR(I81/D81,0) -> 0 | H81: m/㎡ | J81: m | L81: 元/m | M81: =ROUND(K81*I81/10000,6) -> 0 | N81: ='02 项目基础信息（输入）'!$D$4 -> 74626.755 | O81: =ROUND(IFERROR(M81*10000/N81,0),2) -> 0 | P81: ='02 项目基础信息（输入）'!$H$69+$N$3 -> 74626.755 | Q81: =ROUND(IFERROR(M81*10000/P81,0),2) -> 0 | U81: C03.03.03.05
A82: 03.03.03.06挡墙监测/检测 | C82: 总建筑面积 | D82: ='02 项目基础信息（输入）'!$D$4 -> 74626.755 | E82: ㎡ | F82: 总建筑面积 | G82: 1 | H82: ㎡/㎡ | J82: ㎡ | L82: 元/㎡ | M82: =ROUND(K82*I82/10000,6) -> 0 | N82: ='02 项目基础信息（输入）'!$D$4 -> 74626.755 | O82: =ROUND(IFERROR(M82*10000/N82,0),2) -> 0 | P82: ='02 项目基础信息（输入）'!$H$69+$N$3 -> 74626.755 | Q82: =ROUND(IFERROR(M82*10000/P82,0),2) -> 0 | U82: C03.03.03.06
A83: 03.03.03.07其他挡墙、边坡工程 | C83: 总建筑面积 | D83: ='02 项目基础信息（输入）'!$D$4 -> 74626.755 | E83: ㎡ | F83: 总建筑面积 | G83: 1 | H83: ㎡/㎡ | J83: ㎡ | L83: 元/㎡ | M83: =ROUND(K83*I83/10000,6) -> 0 | N83: ='02 项目基础信息（输入）'!$D$4 -> 74626.755 | O83: =ROUND(IFERROR(M83*10000/N83,0),2) -> 0 | P83: ='02 项目基础信息（输入）'!$H$69+$N$3 -> 74626.755 | Q83: =ROUND(IFERROR(M83*10000/P83,0),2) -> 0 | U83: C03.03.03.07
A84: 03.03.04地基处理 | C84: 总建筑面积 | D84: ='02 项目基础信息（输入）'!$D$4 -> 74626.755 | E84: ㎡ | M84: =ROUND(SUM(M85:M88),6) -> 0 | N84: ='02 项目基础信息（输入）'!$D$4 -> 74626.755 | O84: =ROUND(IFERROR(M84*10000/N84,0),2) -> 0 | P84: ='02 项目基础信息（输入）'!$H$69+$N$3 -> 74626.755 | Q84: =ROUND(IFERROR(M84*10000/P84,0),2) -> 0 | U84: C03.03.04
A85: 03.03.04.01强夯地基 | C85: 总建筑面积 | D85: ='02 项目基础信息（输入）'!$D$4 -> 74626.755 | E85: ㎡ | F85: 总建筑面积 | G85: 1 | H85: ㎡/㎡ | I85: =G85*D85 -> 74626.755 | J85: ㎡ | L85: 元/㎡ | M85: =ROUND(K85*I85/10000,6) -> 0 | N85: ='02 项目基础信息（输入）'!$D$4 -> 74626.755 | O85: =ROUND(IFERROR(M85*10000/N85,0),2) -> 0 | P85: ='02 项目基础信息（输入）'!$H$69+$N$3 -> 74626.755 | Q85: =ROUND(IFERROR(M85*10000/P85,0),2) -> 0 | U85: C03.03.04.01
A86: 03.03.04.02注浆地基 | C86: 总建筑面积 | D86: ='02 项目基础信息（输入）'!$D$4 -> 74626.755 | E86: ㎡ | F86: 总建筑面积 | G86: 1 | H86: ㎡/㎡ | I86: =G86*D86 -> 74626.755 | J86: ㎡ | L86: 元/㎡ | M86: =ROUND(K86*I86/10000,6) -> 0 | N86: ='02 项目基础信息（输入）'!$D$4 -> 74626.755 | O86: =ROUND(IFERROR(M86*10000/N86,0),2) -> 0 | P86: ='02 项目基础信息（输入）'!$H$69+$N$3 -> 74626.755 | Q86: =ROUND(IFERROR(M86*10000/P86,0),2) -> 0 | U86: C03.03.04.02
A87: 03.03.04.03深层搅拌桩 | C87: 总建筑面积 | D87: ='02 项目基础信息（输入）'!$D$4 -> 74626.755 | E87: ㎡ | F87: 总建筑面积 | G87: 1 | H87: ㎡/㎡ | I87: =G87*D87 -> 74626.755 | J87: ㎡ | L87: 元/㎡ | M87: =ROUND(K87*I87/10000,6) -> 0 | N87: ='02 项目基础信息（输入）'!$D$4 -> 74626.755 | O87: =ROUND(IFERROR(M87*10000/N87,0),2) -> 0 | P87: ='02 项目基础信息（输入）'!$H$69+$N$3 -> 74626.755 | Q87: =ROUND(IFERROR(M87*10000/P87,0),2) -> 0 | U87: C03.03.04.03
A88: 03.03.04.04其他地基处理 | D88: 0 | M88: =ROUND(SUM(M89:M90),6) -> 0 | N88: ='02 项目基础信息（输入）'!$D$4 -> 74626.755 | O88: =ROUND(IFERROR(M88*10000/N88,0),2) -> 0 | P88: ='02 项目基础信息（输入）'!$H$69+$N$3 -> 74626.755 | Q88: =ROUND(IFERROR(M88*10000/P88,0),2) -> 0 | U88: C03.03.04.04
A89: 03.03.04.04.01CFG桩 | C89: 总建筑面积 | D89: ='02 项目基础信息（输入）'!$D$4 -> 74626.755 | E89: ㎡ | F89: 总建筑面积 | G89: 1 | H89: 元/㎡ | I89: =G89*D89 -> 74626.755 | J89: m3 | L89: 元/m3 | M89: =ROUND(K89*I89/10000,6) -> 0 | N89: ='02 项目基础信息（输入）'!$D$4 -> 74626.755 | O89: =ROUND(IFERROR(M89*10000/N89,0),2) -> 0 | P89: ='02 项目基础信息（输入）'!$H$69+$N$3 -> 74626.755 | Q89: =ROUND(IFERROR(M89*10000/P89,0),2) -> 0 | U89: C03.03.04.04.01
A90: 03.03.04.04.02CFG桩检测 | C90: 总建筑面积 | D90: ='02 项目基础信息（输入）'!$D$4 -> 74626.755 | E90: ㎡ | F90: 总建筑面积 | G90: 1 | H90: 元/㎡ | I90: =G90*D90 -> 74626.755 | J90: 项 | L90: 元/项 | M90: =ROUND(K90*I90/10000,6) -> 0 | N90: ='02 项目基础信息（输入）'!$D$4 -> 74626.755 | O90: =ROUND(IFERROR(M90*10000/N90,0),2) -> 0 | P90: ='02 项目基础信息（输入）'!$H$69+$N$3 -> 74626.755 | Q90: =ROUND(IFERROR(M90*10000/P90,0),2) -> 0 | U90: C03.03.04.04.02
A91: 03.03.05其他 | C91: 总建筑面积 | D91: ='02 项目基础信息（输入）'!$D$4 -> 74626.755 | E91: ㎡ | M91: =ROUND(SUM(M92),6) -> 0 | N91: ='02 项目基础信息（输入）'!$D$4 -> 74626.755 | O91: =ROUND(IFERROR(M91*10000/N91,0),2) -> 0 | P91: ='02 项目基础信息（输入）'!$H$69+$N$3 -> 74626.755 | Q91: =ROUND(IFERROR(M91*10000/P91,0),2) -> 0 | U91: C03.03.05
A92: 03.03.05.01其他岩土工程 | C92: 总建筑面积 | D92: ='02 项目基础信息（输入）'!$D$4 -> 74626.755 | E92: ㎡ | F92: 总建筑面积 | G92: 1 | H92: ㎡/㎡ | I92: =ROUND(G92*D92,2) -> 74626.75 | J92: ㎡ | L92: 元/㎡ | M92: =ROUND(K92*I92/10000,6) -> 0 | N92: ='02 项目基础信息（输入）'!$D$4 -> 74626.755 | O92: =ROUND(IFERROR(M92*10000/N92,0),2) -> 0 | P92: ='02 项目基础信息（输入）'!$H$69+$N$3 -> 74626.755 | Q92: =ROUND(IFERROR(M92*10000/P92,0),2) -> 0 | U92: C03.03.05.01
A93: 03.04单体工程 | C93: 总建筑面积 | D93: ='02 项目基础信息（输入）'!$D$4 -> 74626.755 | E93: ㎡ | M93: =ROUND(M94+M255+M448+M641+M834+M1027+M1220+M1413+M1606+M1799+M1992+M2185+M2378+M2485+M2713+M2940+M3211+M3439+M3666+M3893,6) -> 26554.992 | N93: ='02 项目基础信息（输入）'!$D$4 -> 74626.755 | O93: =ROUND(IFERROR(M93*10000/N93,0),2) -> 3558.37 | P93: ='02 项目基础信息（输入）'!$H$69+$N$3 -> 74626.755 | Q93: =ROUND(IFERROR(M93*10000/P93,0),2) -> 3558.37 | U93: C03.04 | V93: 姑苏第V4 | W93: 禧宸V3F | X93: 狮山云起V3F
A94: 地下室其他(住宅) | C94: 建筑面积（业态） | D94: ='02 项目基础信息（输入）'!$C$32 -> 21931.92 | E94: ㎡ | M94: =ROUND(M95+M116+M119+M128+M131+M134+M153+M165+M167+M169+M171+M176+M193+M196+M208+M210+M214+M216+M222+M229+M233+M236+M238+M239+M240+M241+M244+M246+M251+M253,6) -> 6146.9459 | N94: ='02 项目基础信息（输入）'!$C$32 -> 21931.92 | O94: =ROUND(IFERROR(M94*10000/N94,0),2) -> 2802.74 | P94: ='02 项目基础信息（输入）'!$I$32 -> 21931.92 | Q94: =ROUND(IFERROR(M94*10000/P94,0),2) -> 2802.74 | U94: C03.04_21 | V94: 3347.7808 | W94: 3211.5796 | X94: 2535.0409
A95: 03.04.01建筑工程 | C95: 建筑面积（业态） | D95: ='02 项目基础信息（输入）'!$C$32 -> 21931.92 | E95: ㎡ | M95: =ROUND(M96+M99+M100+M105+M106+M111+M112+M115,6) -> 4256.7178 | N95: ='02 项目基础信息（输入）'!$C$32 -> 21931.92 | O95: =ROUND(IFERROR(M95*10000/N95,0),2) -> 1940.88 | P95: ='02 项目基础信息（输入）'!$I$32 -> 21931.92 | Q95: =ROUND(IFERROR(M95*10000/P95,0),2) -> 1940.88 | S95: 固定 | U95: C03.04.01_21 | V95: 2569.4375 | W95: 2292.3426 | X95: 2013.5234 | Z95: 1979.82 | AB95: =O95-Z95 -> -38.94
A96: 03.04.01.01钢筋工程 | D96: ='02 项目基础信息（输入）'!$C$32 -> 21931.92 | I96: 0 | M96: =ROUND(SUM(M97:M98),6) -> 1311.5305 | N96: ='02 项目基础信息（输入）'!$C$32 -> 21931.92 | O96: =ROUND(IFERROR(M96*10000/N96,0),2) -> 598 | P96: ='02 项目基础信息（输入）'!$I$32 -> 21931.92 | Q96: =ROUND(IFERROR(M96*10000/P96,0),2) -> 598 | U96: C03.04.01.01_21 | V96: 738.3421 | W96: 659.4752 | X96: 664.9107 | Z96: 643.11 | AB96: =O96-Z96 -> -45.11
A97: 03.04.01.01.01钢筋主材 | C97: 建筑面积（业态） | D97: ='02 项目基础信息（输入）'!$C$32 -> 21931.92 | E97: ㎡ | F97: 钢筋含量 | G97: ='03 成本测算（输入）'!D14 -> 117.94887 | H97: kg/㎡ | I97: =G97*D97 -> 2586845.2 | J97: kg | K97: ='03 成本测算（输入）'!$D$11 -> 3.36 | L97: 元/kg | M97: =ROUND(K97*I97/10000,6) -> 869.18 | N97: ='02 项目基础信息（输入）'!$C$32 -> 21931.92 | O97: =ROUND(IFERROR(M97*10000/N97,0),2) -> 396.31 | P97: ='02 项目基础信息（输入）'!$I$32 -> 21931.92 | Q97: =ROUND(IFERROR(M97*10000/P97,0),2) -> 396.31 | U97: C03.04.01.01.01_21 | V97: 495.1085 | W97: 466.8383 | X97: 474.2591 | Z97: 445.52 | AB97: =O97-Z97 -> -49.21
A98: 03.04.01.01.02钢筋制安 | C98: 建筑面积（业态） | D98: ='02 项目基础信息（输入）'!$C$32 -> 21931.92 | E98: ㎡ | F98: 钢筋含量 | G98: =G97 -> 117.94887 | H98: kg/㎡ | I98: =G98*D98 -> 2586845.2 | J98: kg | K98: 1.71 | L98: 元/kg | M98: =ROUND(K98*I98/10000,6) -> 442.35053 | N98: ='02 项目基础信息（输入）'!$C$32 -> 21931.92 | O98: =ROUND(IFERROR(M98*10000/N98,0),2) -> 201.69 | P98: ='02 项目基础信息（输入）'!$I$32 -> 21931.92 | Q98: =ROUND(IFERROR(M98*10000/P98,0),2) -> 201.69 | U98: C03.04.01.01.02_21 | V98: 243.2335 | W98: 192.6368 | X98: 190.6515 | Z98: 197.58 | AB98: =O98-Z98 -> 4.11
A99: 03.04.01.02模板工程 | C99: 建筑面积（业态） | D99: ='02 项目基础信息（输入）'!$C$32 -> 21931.92 | E99: ㎡ | F99: 模版含量 | G99: 2.21 | H99: ㎡/㎡ | I99: =G99*D99 -> 48469.543 | J99: ㎡ | K99: 97.51 | L99: 元/㎡ | M99: =ROUND(K99*I99/10000,6) -> 472.62652 | N99: ='02 项目基础信息（输入）'!$C$32 -> 21931.92 | O99: =ROUND(IFERROR(M99*10000/N99,0),2) -> 215.5 | P99: ='02 项目基础信息（输入）'!$I$32 -> 21931.92 | Q99: =ROUND(IFERROR(M99*10000/P99,0),2) -> 215.5 | U99: C03.04.01.02_21 | V99: 268.8983 | W99: 264.2609 | X99: 218.8726 | Z99: 215.5 | AB99: =O99-Z99 -> 0
A100: 03.04.01.03混凝土工程 | D100: ='02 项目基础信息（输入）'!$C$32 -> 21931.92 | I100: 0 | M100: =ROUND(SUM(M101:M104),6) -> 1225.6319 | N100: ='02 项目基础信息（输入）'!$C$32 -> 21931.92 | O100: =ROUND(IFERROR(M100*10000/N100,0),2) -> 558.83 | P100: ='02 项目基础信息（输入）'!$I$32 -> 21931.92 | Q100: =ROUND(IFERROR(M100*10000/P100,0),2) -> 558.83 | U100: C03.04.01.03_21 | V100: 738.662 | W100: 533.6951 | X100: 557.2809 | Z100: 552.68 | AB100: =O100-Z100 -> 6.15
...

Sheet 06 分析汇报表（住宅）
A1: 一、 | B1: 项目基础信息复核表（手动输入） | L1: C060001
A2: 序号 | B2: 子目名称 | C2: 比照尺度 | E2: 本次情况描述 | G2: 是否优化完成 | L2: C060002
A3: 1 | B3: 可售比 | C3: - | E3: 本项目可售比XX% | L3: C060003
A4: 2 | B4: 地库面积占比 | C4: - | E4: 本项目地库占比XX% | L4: C060004
A5: 3 | B5: 车位个数 | C5: 当地规范对车位个数的设置要求描述：YYY | E5: 按规范应设XX个，实际设置XX个，车户比XX个/户。无差异/有差异，差异原因： | G5: 是/仍需优化，建议： | L5: C060005
A6: 4 | B6: 地上车位数 | C6: 当地规范或出让条件对地上停车比例要求描述：YYY | E6: 按规范可设XX个地上车位，实际设置XX个地上车位。无差异/有差异，差异原因： | G6: 是/仍需优化，建议： | L6: C060006
A7: 5 | B7: 停车效率 | C7: 标准成本刻度XXm2/个 | E7: 本项目XXm2/个（内部类似项目XXm2/个；外部对标项目XXm2/个），无差异/偏高偏低原因： | G7: 是/仍需优化，建议： | L7: C060007
A8: 6 | B8: 配套设置用房 | C8: 社区组织用房、物业用房标准描述 | E8: 未超标设置/有超标设置，原因简述： | G8: 是/仍需优化，建议： | L8: C060008
A9: 7 | B9: 大堂面积 | C9: 标准成本刻度XXm2/大堂 | E9: 本项目大堂面积XXm2/个（内部类似项目XXm2/个；外部对标项目XXm2/个），偏大偏小原因： | G9: 是/仍需优化，建议： | L9: C060009
A10: 8 | B10: 外墙装饰 | C10: - | E10: 外墙门窗窗积比XXm2/m2，墙积比XXm2/m2，外墙、屋面造型是否异形、繁琐，有待简化 | G10: 是/仍需优化，建议： | L10: C060010
A11: 9 | B11: 代征道路/景观 | C11: - | E11: 本项目代征情况，来源依据： | G11: 是/仍需优化，建议： | L11: C060011
A12: 10 | B12: 补充。。。 | L12: C060012
A13: 二、 | B13: 毛坯单方差异展示（本次测算-项目标准刻度）（单位：元/m2）（自动链接） | L13: C060013
A14: 序号 | B14: 类别 | C14: 物业类型 | D14: 小计 | E14: 暂定 | F14: 固定 | G14: 弹性 | L14: C060014
A15: 1 | B15: 单方差异 | C15: 高层毛坯单方 | D15: =D19-D22 -> -3763.289 | E15: =E19-E22 -> -735.9799 | F15: =F19-F22 -> -2084.1568 | G15: =G19-G22 -> -943.15234 | L15: C060015
A17: 2 | B17: 单方差异 | C17: 小高层毛坯单方 | D17: =D20-D23 -> 991.87704 | E17: =E20-E23 -> 293.4162 | F17: =F20-F23 -> 60.753984 | G17: =G20-G23 -> 637.70686 | L17: C060016
A18: 3 | B18: 单方差异 | C18: 多层毛坯单方 | D18: =D21-D24 -> -3788.2081 | E18: =E21-E24 -> -735.9799 | F18: =F21-F24 -> -2094.5998 | G18: =G21-G24 -> -957.62844 | L18: C060017
A19: 4 | B19: 本次项目测算 | C19: 高层毛坯单方 | D19: ='04 目标成本控制表'!E53 -> 0 | E19: ='04 目标成本控制表'!M53 -> 0 | F19: ='04 目标成本控制表'!N53 -> 0 | G19: ='04 目标成本控制表'!O53 -> 0 | L19: C060018
A20: 5 | B20: 本次项目测算 | C20: 小高层毛坯单方 | D20: ='04 目标成本控制表'!E52 -> 4831.5237 | E20: ='04 目标成本控制表'!M52 -> 1029.3961 | F20: ='04 目标成本控制表'!N52 -> 2216.8242 | G20: ='04 目标成本控制表'!O52 -> 1585.3034 | L20: C060019
A21: 6 | B21: 本次项目测算 | C21: 多层毛坯单方 | D21: ='04 目标成本控制表'!E51 -> 0 | E21: ='04 目标成本控制表'!M51 -> 0 | F21: ='04 目标成本控制表'!N51 -> 0 | G21: ='04 目标成本控制表'!O51 -> 0 | L21: C060020
A22: 7 | B22: 项目标准刻度 | C22: 高层毛坯单方 | D22: ='04 目标成本控制表'!W53 -> 3763.289 | E22: ='04 目标成本控制表'!Y53 -> 735.9799 | F22: ='04 目标成本控制表'!Z53 -> 2084.1568 | G22: ='04 目标成本控制表'!AA53 -> 943.15234 | L22: C060021
A23: 8 | B23: 项目标准刻度 | C23: 小高层毛坯单方 | D23: ='04 目标成本控制表'!W52 -> 3839.6467 | E23: ='04 目标成本控制表'!Y52 -> 735.9799 | F23: ='04 目标成本控制表'!Z52 -> 2156.0702 | G23: ='04 目标成本控制表'!AA52 -> 947.59658 | L23: C060022
A24: 9 | B24: 项目标准刻度 | C24: 多层毛坯单方 | D24: ='04 目标成本控制表'!W51 -> 3788.2081 | E24: ='04 目标成本控制表'!Y51 -> 735.9799 | F24: ='04 目标成本控制表'!Z51 -> 2094.5998 | G24: ='04 目标成本控制表'!AA51 -> 957.62844 | L24: C060023
A25: 三、 | B25: 暂定成本差异分析（具体项目，地区）（单位：元/m2） | L25: C060024
A26: 序号 | B26: 科目 | C26: 本次测算单方A | D26: 标准刻度单方B | E26: 差异A-B | F26: 差异原因说明 | L26: C060025
A27: 1 | B27: 桩基础工程 | C27: ='05 成本测算明细'!$O$29 -> 214.34 | D27: ='04 目标成本控制表'!$W$9 -> 0 | E27: =C27-D27 -> 214.34 | L27: C060026
A28: 2 | B28: 岩土工程 | C28: ='05 成本测算明细'!$O$47 -> 336.4 | D28: ='04 目标成本控制表'!$W$10 -> 0 | E28: =C28-D28 -> 336.4 | L28: C060027
A29: 3 | B29: 配套工程 | C29: ='05 成本测算明细'!$O$4164 -> 423.74 | D29: ='04 目标成本控制表'!$W$32 -> 0 | E29: =C29-D29 -> 423.74 | L29: C060028
A30: 四、 | B30: 弹性成本差异分析（相对业态面积单方，单位：元/m2） | L30: C060029
A31: 序号 | B31: 业态 | C31: 弹性成本科目 | D31: 本次项目测算A | E31: 项目标准成本刻度B | F31: 差异A-B | G31: 配置差异 | H31: 含量差异 | I31: 价格差异 | J31: 差异简述，及优化与控制 | L31: C060030
A32: 1.1 | B32: 高层 | C32: 入户门工程 | D32: ='05 成本测算明细'!O912 -> 0 | E32: 60.31 | F32: =D32-E32 -> -60.31 | L32: C03.04.09_14
A33: 1.2 | B33: 高层 | C33: 外立面门窗工程 | D33: ='05 成本测算明细'!O918 -> 0 | E33: 212.59 | F33: =D33-E33 -> -212.59 | L33: C03.04.10_14
A34: 1.3 | B34: 高层 | C34: 外立面装饰工程 | D34: ='05 成本测算明细'!O929 -> 0 | E34: 515.9 | F34: =D34-E34 -> -515.9 | L34: C03.04.12_14
A35: 1.4 | B35: 高层 | C35: 栏杆工程 | D35: ='05 成本测算明细'!O946 -> 0 | E35: 65.49 | F35: =D35-E35 -> -65.49 | L35: C03.04.13_14
A36: 1.5 | B36: 高层 | C36: 公共部位装饰工程 | D36: ='05 成本测算明细'!O951 -> 0 | E36: 160.17 | F36: =D36-E36 -> -160.17 | L36: C03.04.14_14
A37: 1.6 | B37: 高层 | C37: 安防工程 | D37: ='05 成本测算明细'!O989 -> 0 | E37: 38.14 | F37: =D37-E37 -> -38.14 | L37: C03.04.20_14
A38: 1.7 | B38: 高层 | C38: 电梯工程 | D38: ='05 成本测算明细'!O1000 -> 0 | E38: 56.65 | F38: =D38-E38 -> -56.65 | L38: C03.04.23_14
A39: 1.8 | B39: 高层 | C39: 小计 | D39: =SUM(D32:D38) -> 0 | E39: =SUM(E32:E38) -> 1109.25 | F39: =D39-E39 -> -1109.25 | G39: =SUM(G32:G38) -> 0 | H39: =SUM(H32:H38) -> 0 | I39: =SUM(I32:I38) -> 0 | L39: C060038
A40: 2.1 | B40: 小高层 | C40: 入户门工程 | D40: ='05 成本测算明细'!O719 -> 90.06 | E40: 48.57 | F40: =D40-E40 -> 41.49 | L40: C03.04.09_13
A41: 2.2 | B41: 小高层 | C41: 外立面门窗工程 | D41: ='05 成本测算明细'!O725 -> 284.44 | E41: 203.35 | F41: =D41-E41 -> 81.09 | L41: C03.04.10_13
A42: 2.3 | B42: 小高层 | C42: 外立面装饰工程 | D42: ='05 成本测算明细'!O736 -> 814.35 | E42: 512.81 | F42: =D42-E42 -> 301.54 | L42: C03.04.12_13
A43: 2.4 | B43: 小高层 | C43: 栏杆工程 | D43: ='05 成本测算明细'!O753 -> 47.82 | E43: 64.48 | F43: =D43-E43 -> -16.66 | L43: C03.04.13_13
A44: 2.5 | B44: 小高层 | C44: 公共部位装饰工程 | D44: ='05 成本测算明细'!O758 -> 541.07 | E44: 171.33 | F44: =D44-E44 -> 369.74 | L44: C03.04.14_13
A45: 2.6 | B45: 小高层 | C45: 安防工程 | D45: ='05 成本测算明细'!O796 -> 31.23 | E45: 34.78 | F45: =D45-E45 -> -3.55 | L45: C03.04.20_13
A46: 2.7 | B46: 小高层 | C46: 电梯工程 | D46: ='05 成本测算明细'!O807 -> 68.1 | E46: 80.38 | F46: =D46-E46 -> -12.28 | L46: C03.04.23_13
A47: 2.8 | B47: 小高层 | C47: 小计 | D47: =SUM(D40:D46) -> 1877.07 | E47: =SUM(E40:E46) -> 1115.7 | F47: =D47-E47 -> 761.37 | G47: =SUM(G40:G46) -> 0 | H47: =SUM(H40:H46) -> 0 | I47: =SUM(I40:I46) -> 0 | L47: C060046
A48: 3.1 | B48: 多层 | C48: 入户门工程 | D48: ='05 成本测算明细'!O526 -> 0 | E48: 43.83 | F48: =D48-E48 -> -43.83 | L48: C03.04.09_12
A49: 3.2 | B49: 多层 | C49: 外立面门窗工程 | D49: ='05 成本测算明细'!O532 -> 0 | E49: 240.32 | F49: =D49-E49 -> -240.32 | L49: C03.04.10_12
A50: 3.3 | B50: 多层 | C50: 外立面装饰工程 | D50: ='05 成本测算明细'!O543 -> 0 | E50: 491.15 | F50: =D50-E50 -> -491.15 | L50: C03.04.12_12
A51: 3.4 | B51: 多层 | C51: 栏杆工程 | D51: ='05 成本测算明细'!O560 -> 0 | E51: 62.42 | F51: =D51-E51 -> -62.42 | L51: C03.04.13_12
A52: 3.5 | B52: 多层 | C52: 公共部位装饰工程 | D52: ='05 成本测算明细'!O565 -> 0 | E52: 176.23 | F52: =D52-E52 -> -176.23 | L52: C03.04.14_12
A53: 3.6 | B53: 多层 | C53: 安防工程 | D53: ='05 成本测算明细'!O603 -> 0 | E53: 43.46 | F53: =D53-E53 -> -43.46 | L53: C03.04.20_12
A54: 3.7 | B54: 多层 | C54: 电梯工程 | D54: ='05 成本测算明细'!O614 -> 0 | E54: 72.89 | F54: =D54-E54 -> -72.89 | L54: C03.04.23_12
A55: 3.8 | B55: 多层 | C55: 小计 | D55: =SUM(D48:D54) -> 0 | E55: =SUM(E48:E54) -> 1130.3 | F55: =D55-E55 -> -1130.3 | G55: =SUM(G48:G54) -> 0 | H55: =SUM(H48:H54) -> 0 | I55: =SUM(I48:I54) -> 0 | L55: C060054
A56: 4 | B56: 室外 | C56: 室外工程 | D56: ='05 成本测算明细'!O4190 -> 1045 | F56: =D56-E56 -> 1045 | L56: C03.06
A57: 五、 | B57: 固定成本差异分析 | L57: C060056
A58: ① | B58: 地库固定成本差异分析 | E58: 差异小计（元./m2）： | F58: =SUM(F60:F69) -> 134.72568 | G58: 差异简述，及优化与控制 | L58: C060057
A59: 序号 | B59: 类型 | C59: 固定成本科目 | D59: 本次项目测算A | E59: 本次项目测算A | F59: 影响单方差异 | L59: C060058
A60: 1.1 | B60: 含量差异 | C60: 钢筋 | D60: ='03 成本测算（输入）'!$D$14 -> 117.94887 | E60: 115.544 | F60: =(D60-E60)*(E62+'05 成本测算明细'!K98) -> 13.385255 | L60: C060059
A61: 1.2 | B61: 含量差异 | C61: 砼 | D61: ='03 成本测算（输入）'!D15 -> 1.224269 | E61: 1.03 | F61: =(D61-E61)*(E63+'05 成本测算明细'!K102) -> 104.24088 | L61: C060060
A62: 2.1 | B62: 主材价格差异 | C62: 钢筋 | D62: ='03 成本测算（输入）'!$D$11 -> 3.36 | E62: 3.85589 | F62: =(D62-E62)*'03 成本测算（输入）'!D14 -> -58.489666 | L62: C060061
A63: 2.2 | B63: 主材价格差异 | C63: 砼 | D63: ='03 成本测算（输入）'!$D$12 -> 367.074 | E63: 447.19 | F63: =(D63-E63)*'03 成本测算（输入）'!D15 -> -98.083539 | L63: C060062
A64: 3.1 | B64: 其他差异 | C64: 土建改造工程 | D64: ='03 成本测算（输入）'!D16 -> 0 | E64: 0 | F64: =(D64-E64) -> 0 | L64: C060063
A65: 3.2 | B65: 其他差异 | C65: 人防工程 | D65: ='05 成本测算明细'!$O$116 -> 18.63 | E65: 57.09 | F65: =D65-E65 -> -38.46 | L65: C060064
A66: 3.3 | B66: 其他差异 | C66: 充电桩 | D66: ='05 成本测算明细'!O151 -> 7.15 | E66: 0 | F66: =D66-E66 -> 7.15 | L66: C060065
A67: 3.4 | B67: 其他差异 | C67: 停车场出入口 | D67: ='05 成本测算明细'!O241 -> 4.56 | E67: 1.11 | F67: =D67-E67 -> 3.45 | L67: C060066
A68: 3.5 | B68: 其他差异 | C68: 机械停车位 | D68: ='05 成本测算明细'!O244 -> 0 | E68: 0 | F68: =D68-E68 -> 0 | L68: C060067
A69: 3.6 | B69: 其他差异 | C69: 其他单体工程 | D69: ='03 成本测算（输入）'!$D$21 -> 216.53274 | E69: ='03 成本测算（输入）'!H21 -> 15 | F69: =D69-E69 -> 201.53274 | L69: C060068
A70: ② | B70: 高层固定成本差异分析 | E70: 差异小计（元./m2）： | F70: =SUM(F72:F78) -> -211.30959 | G70: 差异简述，及优化与控制 | L70: C060069
A71: 序号 | B71: 类型 | C71: 固定成本科目 | D71: 本次项目测算A | E71: 本次项目测算A | F71: 影响单方差异 | L71: C060070
A72: 1.1 | B72: 主材价格差异 | C72: 钢筋 | D72: ='03 成本测算（输入）'!$D$11 -> 3.36 | E72: 3.85589 | F72: =(D72-E72)*'05 成本测算明细'!$G$837 -> 0 | L72: C060071
A73: 1.2 | B73: 主材价格差异 | C73: 砼 | D73: ='03 成本测算（输入）'!$D$12 -> 367.074 | E73: 447.19 | F73: =(D73-E73)*'05 成本测算明细'!$G$841 -> 0 | L73: C060072
A74: 2.1 | B74: 其他差异 | C74: 预制构件影响 | D74: ='03 成本测算（输入）'!D115 -> 0 | E74: 94.5 | F74: =(D74-E74) -> -94.5 | L74: C060073
A75: 2.2 | B75: 其他差异 | C75: 土建改造 | D75: ='03 成本测算（输入）'!D118 -> 0 | E75: 0 | F75: =(D75-E75) -> 0 | L75: C060074
A76: 2.3 | B76: 其他差异 | C76: 外墙保温 | D76: ='05 成本测算明细'!$O$925 -> 0 | E76: 99.56 | F76: =D76-E76 -> -99.56 | L76: C060075
A77: 2.4 | B77: 其他差异 | C77: 太阳能热水器 | D77: =IFERROR('03 成本测算（输入）'!D119*'05 成本测算明细'!$D$1011/'05 成本测算明细'!$N$1011,0) -> 0 | E77: 17.249594 | F77: =D77-E77 -> -17.249594 | L77: C060076
A78: 2.5 | B78: 其他差异 | C78: 其他单体工程 | D78: ='03 成本测算（输入）'!D120 -> 0 | E78: ='03 成本测算（输入）'!H120 -> 0 | F78: =D78-E78 -> 0 | L78: C060077
A79: ③ | B79: 小高层固定成本差异分析 | E79: 差异小计（元./m2）： | F79: =IFERROR(SUM(F81:F87),0) -> 62.904464 | G79: 差异简述，及优化与控制 | L79: C060078
A80: 序号 | B80: 类型 | C80: 固定成本科目 | D80: 本次项目测算A | E80: 本次项目测算A | F80: 影响单方差异 | L80: C060079
A81: 1.1 | B81: 主材价格差异 | C81: 钢筋 | D81: ='03 成本测算（输入）'!$D$11 -> 3.36 | E81: 3.85589 | F81: =(D81-E81)*'05 成本测算明细'!$G$644 -> -22.390929 | L81: C060080
A82: 1.2 | B82: 主材价格差异 | C82: 砼 | D82: ='03 成本测算（输入）'!$D$12 -> 367.074 | E82: 447.19 | F82: =(D82-E82)*'05 成本测算明细'!$G$648 -> -32.809693 | L82: C060081
A83: 2.1 | B83: 其他差异 | C83: 预制构件影响 | D83: ='03 成本测算（输入）'!$D$69 -> 152.91589 | E83: 94.5 | F83: =(D83-E83) -> 58.415888 | L83: C060082
A84: 2.2 | B84: 其他差异 | C84: 土建改造 | D84: ='03 成本测算（输入）'!$D$72 -> 43.369452 | E84: 0 | F84: =(D84-E84) -> 43.369452 | L84: C060083
A85: 2.3 | B85: 其他差异 | C85: 外墙保温 | D85: ='05 成本测算明细'!$O$731 -> 85.08 | E85: 93.23 | F85: =D85-E85 -> -8.15 | L85: C060084
A86: 2.4 | B86: 其他差异 | C86: 太阳能热水器 | D86: =IFERROR('03 成本测算（输入）'!$D$73*'05 成本测算明细'!$D$818/'05 成本测算明细'!$N$818,0) -> 31.675119 | E86: 19.205373 | F86: =D86-E86 -> 12.469746 | L86: C060085
A87: 2.5 | B87: 其他差异 | C87: 其他单体工程 | D87: ='03 成本测算（输入）'!$D$74 -> 12 | E87: ='03 成本测算（输入）'!H74 -> 0 | F87: =D87-E87 -> 12 | L87: C060086
A88: ④ | B88: 多层固定成本差异分析 | E88: 差异小计（元./m2）： | F88: =IFERROR(SUM(F90:F96),0) -> -244.26335 | G88: 差异简述，及优化与控制 | L88: C060087
A89: 序号 | B89: 类型 | C89: 固定成本科目 | D89: 本次项目测算A | E89: 本次项目测算A | F89: 影响单方差异 | L89: C060088
A90: 1.1 | B90: 主材价格差异 | C90: 钢筋 | D90: ='03 成本测算（输入）'!$D$11 -> 3.36 | E90: 3.85589 | F90: =(D90-E90)*'05 成本测算明细'!$G$451 -> 0 | L90: C060089
A91: 1.2 | B91: 主材价格差异 | C91: 砼 | D91: ='03 成本测算（输入）'!$D$12 -> 367.074 | E91: 447.19 | F91: =(D91-E91)*'05 成本测算明细'!$G$455 -> 0 | L91: C060090
A92: 2.1 | B92: 其他差异 | C92: 预制构件影响 | D92: ='03 成本测算（输入）'!$D$23 -> 0 | E92: 94.5 | F92: =(D92-E92) -> -94.5 | L92: C060091
A93: 2.2 | B93: 其他差异 | C93: 土建改造 | D93: ='03 成本测算（输入）'!$D$26 -> 0 | E93: 0 | F93: =(D93-E93) -> 0 | L93: C060092
A94: 2.3 | B94: 其他差异 | C94: 外墙保温 | D94: ='05 成本测算明细'!$O$538 -> 0 | E94: 104.99 | F94: =D94-E94 -> -104.99 | L94: C060093
A95: 2.4 | B95: 其他差异 | C95: 太阳能热水器 | D95: =IFERROR('03 成本测算（输入）'!$D$27*'05 成本测算明细'!$D$625/'05 成本测算明细'!$N$625,0) -> 0 | E95: 44.773353 | F95: =D95-E95 -> -44.773353 | L95: C060094
A96: 2.5 | B96: 其他差异 | C96: 其他单体工程 | D96: ='03 成本测算（输入）'!$D$28 -> 0 | E96: ='03 成本测算（输入）'!H28 -> 0 | F96: =D96-E96 -> 0 | L96: C060095
A97: 六、 | C97: 汇报PPT所需表格 | L97: C060096
A98: 表1 | B98: 各阶段建安成本汇总表 | L98: C060097
B99: 成本阶段 | C99: 建筑面积(㎡) | D99: 可售面积(㎡) | E99: 总建安(万元) | F99: 毛坯建安(万元) | G99: 总建面单方 | H99: 毛坯建面单方 | I99: 总可售单方 | J99: 毛坯可售单方 | L99: C060098
B100: 可研阶段 | L100: C060099
B101: 启动阶段 | C101: ='04 目标成本控制表'!F4 -> 74626.755 | D101: ='04 目标成本控制表'!J4 -> 46191.065 | E101: ='04 目标成本控制表'!C49 -> 53408.719 | F101: ='04 目标成本控制表'!C48 -> 36116.349 | G101: ='04 目标成本控制表'!E49 -> 7156.7789 | H101: ='04 目标成本控制表'!E48 -> 4839.598 | I101: ='04 目标成本控制表'!I49 -> 11562.565 | J101: ='04 目标成本控制表'!I48 -> 7818.9038 | L101: C060100
...

Sheet 投资会简述
A1: 投资会成本简述
A2: 城市 | B2: 项目名称 | C2: 总建面 | D2: 计容面积 | E2: 土地 | F2: 档次 | G2: 交付 | H2: 售价 | I2: 起拍可售楼面价 | J2: 可售单方 | K2: 起拍成本利润率 | L2: 精装标准 | M2: 景观单方 | N2: 卖场成本 | O2: 是否 | P2: 建议
C3: (万㎡) | D3: （万㎡） | E3: 属性 | G3: 标准 | H3: (万元/㎡) | I3: (元/㎡) | J3: (元/㎡) | L3: (元/㎡) | M3: (元/㎡) | N3: （万元） | O3: 竞自持
A4: 苏州 | B4: 园区永旺北地块 | C4: ='02 项目基础信息（输入）'!I69 -> 74626.755 | D4: ='02 项目基础信息（输入）'!K5 -> 46561.065 | E4: C1 | F4: U3+ | G4: 精装 | H4: 5.28 | I4: 26800 | J4: ='04 目标成本控制表'!I49 -> 11562.565 | K4: 0.17 | L4: 3000 | M4: 1045 | N4: ='04 目标成本控制表'!C46 -> 3207.05 | O4: 否 | P4: U3+
A6: 一、项目概况
A7: 建筑面积（㎡） | B7: 可售面积（㎡） | C7: 总建安 （万元） | D7: 毛坯建安 （万元） | E7: 总建面单方 （元/㎡） | F7: 毛坯建面单方 （元/㎡） | G7: 总可售单方 （元/㎡） | H7: 毛坯可售单方 （元/㎡） | I7: 配置分级
A8: =C4 -> 74626.755 | B8: ='02 项目基础信息（输入）'!K11 -> 46191.065 | C8: ='04 目标成本控制表'!C49 -> 53408.719 | D8: ='04 目标成本控制表'!C48 -> 36116.349 | E8: =C8/A8*10000 -> 7156.7789 | F8: =D8/A8*10000 -> 4839.598 | G8: =C8/B8*10000 -> 11562.565 | H8: =D8/B8*10000 -> 7818.9038 | I8: U3+
A9: 物业类型 | B9: 售价 | C9: 建筑面积 （㎡） | D9: 面积占比 （%） | E9: 精装修标准 （元/㎡） | F9: 备注
A10: 地库 | B10: 11万/个 | C10: ='02 项目基础信息（输入）'!C32 -> 21931.92 | D10: =C10/$A$8 -> 0.29388817 | E10: / | F10: 地下1层，车库层高3.8，人防占比8%
A11: 小高层 | B11: 2.25万/m2 | C11: =B8 -> 46191.065 | D11: =C11/A8 -> 0.61896119 | E11: 3000 | F11: 精装交付，小高层，层高 3.1，预制装配率 50%
A12: 商铺及其他公共配套 | B12: - | C12: ='02 项目基础信息（输入）'!C66 -> 815 | D12: =C12/$A$8 -> 0.010921016 | E12: / | F12: 物业配套用房单独设置
A13: 二、基础数据复核
A14: 校核项 | B14: 可售比 | C14: 地下占比 | D14: 停车效率 | E14: 车位配比 | F14: 地下建造面积比 | G14: 室外面积占比 | H14: 业态1地上赠送率 | I14: 业态2地上赠送率
A15: 计算方式 | B15: 可售面积/ 总建筑面积 | C15: 地下建筑面积/ 总建筑面积 | D15: 地下车库面积/ 地下车位数 | E15: 地下车位数/ 户数 | F15: 地下建造面积/ 地下建筑面积 | G15: 室外工程面积/ 占地面积 | H15: 塔楼建造面积/ 建筑面积 | I15: 塔楼建造面积/ 建筑面积
A16: 本次指标 | B16: =B8/A8 -> 0.61896119 | C16: =C10/A8 -> 0.29388817 | D16: =(总指标!E18-总指标!E21)/总指标!E40 -> 40.461532 | E16: =总指标!E40/总指标!L26 -> 1.675 | F16: 1 | G16: =总指标!E55/总指标!E4 -> 0.81168269 | H16: 1 | I16: 1
A17: 常规指标 | B17: 0.64 | C17: 0.36 | D17: 39.42 | E17: 1.22 | F17: 1 | G17: 0.8 | H17: 1 | I17: 1
A18: 差异说明 | B18: 业态差异：本项目主要为11层小高，单车位指标提升，户均车位配比较刻度+0.46

Sheet 总指标
B1: 表2
B2: ="地块经济技术指标" -> 地块经济技术指标 | J2: 计容配套用房面积
B3: 序号 | C3: 名称 | D3: 单位 | E3: 规划指标 | F3: 备注 | G3: 规划容积率 | H3: 1.6 | J3: 物业管理用房 | K3: 370 | L3: =(E26+E23)*0.7% -> 368.86384 | M3: =K3-L3 -> 1.1361578 | N3: =E18*0.4% -> 87.72768
B4: 1 | C4: 占地面积 | D4: m2 | E4: =E5 -> 28812.54 | F4: =E4/666.67 -> 43.218594 | G4: 理论计容
B5: 1.1 | C5: 建设用地占地 | D5: m2 | E5: 28812.54 | F5: =E5/666.67 -> 43.218594 | G5: =E5*H3 -> 46100.064
B6: 2 | C6: 可销售面积 | D6: m2 | E6: =SUM(E7:E13) -> 46191.065 | F6: 物业类型比例
A7: 普通住宅 | B7: 2.1 | C7: 精装洋房143㎡（普宅） | D7: m2 | E7: =N24 -> 28600 | F7: =E7/$E$6 -> 0.61916737 | G7: =P24 -> 3146 | H7: =SUM(G7:G17) -> 5425.9 | I7: =E7/$E$26 -> 0.61424712 | J7: 合计 | K7: =SUM(K3:K6) -> 370
B8: 2.2 | C8: 精装小高层（普宅） | D8: m2 | F8: =E8/$E$6 -> 0
A9: 非普通住宅 | B9: 2.3 | C9: 精装洋房（非普） | D9: m2 | F9: =E9/$E$6 -> 0 | J9: 消防控制室 | K9: 50
B10: 2.4 | C10: 精装洋房（非普） | D10: m2 | F10: =E10/$E$6 -> 0 | J10: 门卫 | K10: 25
B11: 2.5 | C11: 精装洋房（非普） | D11: m2 | F11: =E11/$E$6 -> 0 | I11: =E11/$E$26 -> 0 | J11: 垃圾房 | K11: 50
B12: 2.6 | C12: 精装洋房176㎡（非普） | D12: m2 | E12: =N25 -> 17591.065 | F12: =E12/$E$6 -> 0.38083263 | G12: =P25 -> 1934.9 | I12: =E12/$E$26 -> 0.37780632 | J12: 配电房 | K12: 320
A13: 其他 | B13: 2.7 | C13: 可售商业（其他） | D13: m2 | F13: =E13/$E$6 -> 0
B14: 2.8 | D14: m2 | J14: 闷顶 | K14: 1370 | L14: 封闭架空层 | M14: 700 | N14: 6000 | O14: =M14*N14 -> 4200000
B15: 3 | C15: 公建配套面积 | D15: m2 | E15: =SUM(E16:E17) -> 370 | F15: 公建设施占总建筑比例 | I15: =E16/E26 -> 0.0079465537 | J15: 架空层 | K15: 4318.77 | L15: 非封闭 | M15: =K15-M14 -> 3618.77 | N15: 2000 | O15: =M15*N15 -> 7237540
B16: 3.1 | C16: 居委会及配套 | D16: m2 | E16: =K7 -> 370 | F16: =E16/E25 -> 0.0049580074 | G16: =P27 -> 345 | J16: 不计容合计 | K16: =SUM(K9:K15) -> 6133.77 | O16: =SUM(O14:O15)/K15 -> 2648.3327
B17: 3.2 | C17: 配套商业 | D17: m2 | E17: 0 | F17: =E17/E25 -> 0
B18: 4 | C18: 地库建筑面积 | D18: m2 | E18: =SUM(E19:E22) -> 21931.92 | F18: =SUM(F19:F21) -> 502.5 | G18: 最少人防面积
B19: 4.1 | C19: 人防地库 | D19: m2 | E19: 1776.54 | F19: =E47 -> 41 | G19: =E6*0.04/1.04 -> 1776.5794
B20: 4.2 | C20: 非人防地库 | D20: m2 | E20: =21931.92-E19-E21 -> 18555.38 | F20: =E50 -> 461.5 | G20: 差异
B21: 4.3 | C21: 地下会所+地下庭院 | D21: m2 | E21: 1600 | G21: =E19-G19 -> -0.039407692
B22: 4.4 | C22: 地下可售（储藏室） | D22: m2 | G22: 省规应建人防面积 | I22: 户型详细技术指标
B23: 5 | C23: 架空层+闷顶+不计容配套 | D23: m2 | E23: =K16 -> 6133.77 | G23: =E25*0.08/1.08 -> 5527.9077 | I23: 户型 | J23: 面积段 | K23: 户型描述 | L23: 户数 | M23: 户数比 | N23: 面积 | O23: 面积比 | P23: 占地面积 | Q23: 有效车位 | R23: 计容面积占比
B24: 6 | C24: 可销售建筑面积 | D24: m2 | E24: =E6+E13+E14 -> 46191.065 | I24: 11F洋房 | J24: 143 | K24: 4房2卫 | L24: 200 | M24: =L24/$L$26 -> 0.66666667 | N24: =ROUND(J24*L24,2) -> 28600 | O24: =N24/$N$26 -> 0.61916737 | P24: 3146 | Q24: =L24*1 -> 200 | R24: =N24/$E$26 -> 0.61424712
B25: 7 | C25: 总建筑面积 | D25: m2 | E25: =E6+E15+E18+E23 -> 74626.755 | F25: (2)+(3)+(4)+(5) | G25: 容积率校核（应为0） | I25: 11F洋房 | J25: 176 | K25: 4房3卫 | L25: 100 | M25: =L25/$L$26 -> 0.33333333 | N25: =ROUND(J25*L25,2)-8.9354 -> 17591.065 | O25: =N25/$N$26 -> 0.38083263 | P25: 1934.9 | Q25: =L25*1.2 -> 120 | R25: =N25/$E$26 -> 0.37780632
B26: 8 | C26: 容积率面积 | D26: m2 | E26: =E6+E15 -> 46561.065 | F26: (2)+(3) | G26: =E26-G5-H27 -> -7.9012352e-12 | L26: =SUM(L24:L25) -> 300 | M26: =SUM(M24:M25) -> 1 | N26: =SUM(N24:N25) -> 46191.065 | O26: =SUM(O24:O25) -> 1 | P26: =SUM(P24:P25) -> 5080.9 | Q26: =SUM(Q24:Q25) -> 320 | R26: =SUM(R24:R25) -> 0.99205345
B27: 9 | C27: 容积率 | D27: R | E27: =E26/E4 -> 1.616 | F27: (7)/(1) | G27: 容积率奖励 | H27: =ROUND(G5*1%,4) -> 461.0006 | O27: 商业配套占地 | P27: 345 | Q27: =Q26/L26 -> 1.0666667 | R27: =E13/E26 -> 0
O28: 其它 | R28: =E16/E26 -> 0.0079465537
A29: 注： | B29: 面积汇总 | C29: 住宅面积 | D29: m2 | E29: =E6 -> 46191.065 | F29: =E29/$E$26 -> 0.99205345 | O29: 总占地面积 | P29: =SUM(P26:P28) -> 5425.9 | R29: =R26+R28 -> 1
C30: 商业面积 | D30: m2 | E30: =E13 -> 0 | F30: =E30/$E$26 -> 0
C31: 配套面积 | D31: m2 | E31: =E16 -> 370 | F31: =E31/$E$26 -> 0.0079465537
B32: 户数 | C32: 住宅 | D32: 户 | E32: =L26 -> 300
C33: 其他 | D33: 户
C34: 总户数 | D34: 户 | E34: =E32 -> 300 | O34: 项目 | S34: 面积 | T34: 单位 | V34: 本项目车位配比方案
B35: 车位总数 | C35: 住宅车位数(roundup公式） | D35: 个 | E35: =ROUNDUP(MAX(E6/100*1.2,E32/1.2),0)*90% -> 499.5 | F35: 1.2个/户且1.2个/100㎡ | O35: 用地面积 | S35: =E5 -> 28812.54 | T35: ㎡ | V35: 类目 | Y35: 面积/个数 | Z35: 备注
C36: 商业车位数(roundup公式） | D36: 个 | E36: =ROUNDUP((E30)/100*0.6,0) -> 0 | F36: 0.6个/100平米计容面积 | O36: 可售面积 | S36: =S40 -> 46191 | T36: ㎡ | V36: 住宅建筑面积 | Y36: =S40 -> 46191
C37: 配套车位数(roundup公式） | D37: 个 | E37: =ROUNDUP(E31/100*0.8,0) -> 3 | F37: 0.8个/100平米计容面积 | O37: 总建筑面积 | S37: =S38+S51 -> 73257 | T37: ㎡ | V37: 公建配套面积 | Y37: =S42+S46 -> 815 | Z37: 配套设施
C38: 访客车位 | D38: 个 | E38: 20 | F38: 总停车位数*4%且≤30 | G38: =E39*4% -> 20.9 | O38: 地上建筑面积 | S38: =S39+S44 -> 51325 | T38: ㎡ | V38: 住宅总户数 | Y38: =S60 -> 300
C39: 总车位数 | D39: 个 | E39: =E35+E36+E37+E38 -> 522.5 | G39: =E38/E39 -> 0.038277512 | O39: 其中 | P39: 地上计容建筑面积 | S39: =S40+S42 -> 46561 | T39: ㎡ | V39: 指标计算 | W39: 住宅车位 | Y39: =E35 -> 499.5 | Z39: 1.2个/户且1.2个/100平
C40: 地下车位数 | D40: 个 | E40: =E39-E38 -> 502.5 | F40: 地面停车位占比 | G40: =(E39-E40)/E39 -> 0.038277512 | P40: 其中 | Q40: 住宅 | S40: =SUM(S41:S41) -> 46191 | T40: ㎡ | W40: 配套车位 | Y40: =E37 -> 3 | Z40: 0.8个/100平米建筑面积
C41: 其中：住宅用地地下车位数 | D41: 个 | E41: =E40-E42 -> 502.5 | Q41: 其中 | R41: 精装洋房 | S41: =ROUND(E6,0) -> 46191 | T41: ㎡ | W41: 访客车位 | Y41: =E38 -> 20 | Z41: 4%*总停车位且≤30
C42: 商业用地地下车位数 | D42: 个 | E42: 0 | F42: =E18/E41 -> 43.645612 | Q42: 红线内配建及配套 | S42: =SUM(S43:S43) -> 370 | T42: ㎡ | V42: 总车位数 | Y42: =SUM(Y39:Y41) -> 522.5 | AA42: =Y42/Y38 -> 1.7416667
C43: 人防面积 | D43: m2 | E43: =E44+E45 -> 1776.54 | Q43: 其中 | R43: 物业管理用房 | S43: =ROUND(K3,0) -> 370 | T43: ㎡ | V43: 其中 | W43: 地下车位 | Y43: =Y44+Y45 -> 502.5
C44: 其中：住宅用地人防面积 | D44: m2 | E44: =E19 -> 1776.54 | P44: 地上不计容建筑面积 | S44: =S45+S46 -> 4764 | T44: ㎡ | W44: 其中 | X44: 人防车位 | Y44: =E47 -> 41 | Z44: 人防车位44㎡/个
C45: 商业用地人防面积 | D45: m2 | P45: 其中 | Q45: 其中 | R45: 架空层 | S45: =ROUND(K15,0) -> 4319 | T45: ㎡ | X45: 非人防车位 | Y45: =E50 -> 461.5
C46: 人防停车位 | D46: 个 | E46: =E47+E48 -> 41 | Q46: 地上不计容配套面积 | S46: =SUM(S47:S50) -> 445 | T46: ㎡ | W46: 地上车位 | Y46: =Y42-Y43 -> 20
C47: 其中：住宅用地人防车位 | D47: 个 | E47: 41 | F47: =E19/40 -> 44.4135 | Q47: 其中 | R47: =J9 -> 消防控制室 | S47: =ROUND(K9,0) -> 50 | T47: ㎡ | V47: 可售车位比 | Y47: =Y45/Y38 -> 1.5383333
C48: 商业用地人防车位 | D48: 个 | E48: =ROUNDUP(E45/37,0) -> 0 | R48: =J10 -> 门卫 | S48: =ROUND(K10,0) -> 25 | T48: ㎡ | AA48: =Y45-161 -> 300.5
C49: 非人防地下停车位 | D49: 个 | E49: =E50+E51+E52 -> 461.5 | F49: =F50+F51+F52 -> 18187.91 | R49: =J11 -> 垃圾房 | S49: =ROUND(K11,0) -> 50 | T49: ㎡
C50: 其中：住宅用地非人防停车位 | D50: 个 | E50: =E41-E47 -> 461.5 | F50: 18187.91 | G50: =E20/E50 -> 40.206674 | R50: =J12 -> 配电房 | S50: =ROUND(K12,0) -> 320 | T50: ㎡
C51: 商业用地非人防车位 | D51: 个 | E51: =E42-E48 -> 0 | F51: =E51*37 -> 0 | O51: 地下建筑面积 | S51: =SUM(S52:S54) -> 21932 | T51: ㎡
C52: 别墅部分消化高层车位数 | D52: 个 | E52: =E33*2 -> 0 | O52: 其中 | P52: 人防地库 | S52: =ROUND(E19,0) -> 1777 | T52: ㎡
C53: 配电房计算 | E53: =ROUNDUP(E26/50000,0)*180 -> 180 | F53: 每5万m2计容面积配180m2 | P53: 非人防地库 | S53: =ROUND(E20,0) -> 18555 | T53: ㎡
C54: 建筑占地面积 | E54: =H7 -> 5425.9 | P54: =C21 -> 地下会所+地下庭院 | S54: =ROUND(E21,0) -> 1600 | T54: ㎡
C55: 绿化园建面积 | E55: =E5-E54 -> 23386.64 | O55: 首层面积 | S55: =SUM(S56:S57) -> 5426 | T55: ㎡
O56: 其中 | P56: 住宅首层 | S56: =ROUND(P26,0) -> 5081 | T56: ㎡
P57: 其他 | S57: =ROUND(P27,0) -> 345 | T57: ㎡
O58: 覆盖率 | S58: =S55/S35*100 -> 18.832078 | T58: %
O59: 容积率 | S59: =S39/S35 -> 1.6159978 | T59: /
O60: 户数 | S60: =E32 -> 300 | T60: 户
O61: 机动车停车位 | S61: =E39 -> 522.5 | T61: 辆
O62: 其中 | P62: 地上 | S62: =S61-S63 -> 20 | T62: 辆
P63: 地下 | S63: =E41 -> 502.5 | T63: 辆
P64: 其中 | Q64: 非人防车位 | S64: =E50 -> 461.5 | T64: 辆

Sheet 含量测算
A1: 姑苏项目地下室用钢量统计 | I1: 本地块地下室用钢量统计
A2: 构件 | B2: 部位 | C2: 地下室 | G2: 总计 | H2: 姑苏第人防地库占比 | I2: 构件 | J2: 部位 | K2: 地下室 | O2: 总计
C3: 非人防塔楼 | D3: 非人防塔楼外 | E3: 人防塔楼 | F3: 人防塔楼外 | H3: 0.254 | K3: 非人防塔楼 | L3: 非人防塔楼外 | M3: 人防塔楼 | N3: 人防塔楼外
A4: 面积 | C4: 1550 | D4: 7862 | E4: =506 -> 506 | F4: 2794 | G4: =SUM(C4:F4) -> 12712 | I4: 面积 | K4: =总指标!E54 -> 5425.9 | L4: =总指标!E18-总指标!E19-总指标!E54 -> 14729.48 | M4: =总指标!E19 -> 1776.54 | N4: 0 | O4: =SUM(K4:N4) -> 21931.92
A5: 集团刻度 | C5: =150-3 -> 147 | D5: =105-3 -> 102 | E5: =180-3 -> 177 | F5: =140-3 -> 137 | H5: 本地块 | I5: 集团刻度 | K5: =150-3 -> 147 | L5: =105-3 -> 102 | M5: =180-3 -> 177 | N5: =140-3 -> 137
A6: 集团限额 | C6: =160 -> 160 | D6: 120 | E6: 190 | F6: 160 | H6: ='03 成本测算（输入）'!D17 -> 0.081002484 | I6: 集团限额 | K6: =160 -> 160 | L6: 120 | M6: 190 | N6: 160
A7: 钢筋 | B7: 基础 | C7: =58.24+16.83-3 -> 72.07 | D7: =356.35 -> 356.35 | E7: =134.3+8.54+40.62+24.38+7.5-5 -> 210.34 | I7: 钢筋 | J7: 基础
B8: 柱、墙 | C8: =7.3+11.2+15.7+20.74+21.9+26.4 -> 103.24 | D8: =33.14+52.2 -> 85.34 | E8: =30.9+25.4+90.7+23.96 -> 170.96 | J8: 柱、墙
B9: 梁 | C9: =1.05+1.66+3.64+5.02+5.6+5.83 -> 22.8 | D9: 135.34 | E9: =76.63+2.99 -> 79.62 | J9: 梁
B10: 板 | C10: =2.4+2.23+3.34+4.99+4.56+5.3 -> 22.82 | D10: =218+0.8+6.58+3.43 -> 228.81 | E10: 103.25 | J10: 板
B14: 小计 | C14: =SUM(C7:C13) -> 220.93 | D14: =SUM(D7:D13) -> 805.84 | E14: =SUM(E7:F13) -> 564.17 | J14: 小计 | K14: =K15*K4 -> 773383.28 | L14: =L15*L4 -> 1509743.6 | M14: =M15*M4 -> 303718.36
B15: 含量指标KG/m2 | C15: =C14*1000/C4 -> 142.53548 | D15: =D14*1000/D4 -> 102.49809 | E15: =E14*1000/(E4+F4) -> 170.96061 | G15: =SUM(C14:F14)/SUM(C4:F4)*1000 -> 125.15261 | J15: 含量指标KG/m2 | K15: =C15 -> 142.53548 | L15: =D15 -> 102.49809 | M15: =E15 -> 170.96061 | O15: =SUM(K14:N14)/SUM(K4:N4) -> 117.94887
A19: 姑苏项目地下室用砼量统计 | I19: 本地块地下室用砼量统计
A20: 构件 | B20: 部位 | C20: 地下室 | G20: 总计 | H20: 姑苏第人防地库占比 | I20: 构件 | J20: 部位 | K20: 地下室 | O20: 总计
C21: 非人防塔楼 | D21: 非人防塔楼外 | E21: 人防塔楼 | F21: 人防塔楼外 | H21: 0.254 | K21: 非人防塔楼 | L21: 非人防塔楼外 | M21: 人防塔楼 | N21: 人防塔楼外
A22: 面积 | C22: 1550 | D22: 7862 | E22: =506 -> 506 | F22: 2794 | G22: =SUM(C22:F22) -> 12712 | I22: 面积 | K22: 5558.774 | L22: 16081.224 | M22: 1760.0023 | N22: 0 | O22: =SUM(K22:N22) -> 23400
A23: 集团刻度 | C23: 1.37 | D23: 1 | E23: 1.67 | F23: 1.2 | H23: 本地块 | I23: 集团刻度 | K23: 1.37 | L23: 1 | M23: 1.67 | N23: 1.2
A24: 集团限额 | C24: 1.47 | D24: 1.05 | E24: 1.77 | F24: 1.28 | H24: =H6 -> 0.081002484 | I24: 集团限额 | K24: 1.47 | L24: 1.05 | M24: 1.77 | N24: 1.28
A25: 钢筋 | B25: 垫层 | I25: 钢筋 | J25: 垫层
B26: 基础 | C26: 1905.15 | D26: 4567 | E26: 2020.16 | J26: 基础
B27: 柱、墙 | C27: 562.13 | D27: 608.52 | E27: 852.41 | J27: 柱、墙
B28: 梁 | C28: 327.07 | D28: 2831.75 | E28: 1133.09 | J28: 梁
B29: 板 | J29: 板
B30: 其他 | C30: 24.81 | D30: 11.15 | J30: 其他
B31: 小计 | C31: =SUM(C25:C30) -> 2819.16 | D31: =SUM(D25:D30) -> 8018.42 | E31: =SUM(E25:E30) -> 4005.66 | J31: 小计 | K31: =K32*K22 -> 10110.37 | L31: =L32*L22 -> 16401.171 | M31: =M32*M22 -> 2136.3548
A32: 含量指标m3/m2 | C32: =C31/C22 -> 1.8188129 | D32: =D31/D22 -> 1.0198957 | E32: =E31/(E22+F22) -> 1.2138364 | G32: =SUM(C31:F31)/SUM(C22:F22) -> 1.1676558 | I32: 含量指标m3/m2 | K32: =C32 -> 1.8188129 | L32: =D32 -> 1.0198957 | M32: =E32 -> 1.2138364 | O32: =SUM(K31:N31)/SUM(K22:N22) -> 1.224269
A36: 地上钢筋指标修正
C37: 面积 | D37: 钢筋刻度 | E37: 混凝土刻度
B38: 建筑面积 | C38: ='02 项目基础信息（输入）'!C43 -> 51879.835 | D38: 43 | E38: 0.39
B39: 无闷顶理论钢筋及砼总量 | D39: =C38*D38 -> 2230832.9 | E39: =C38*E38 -> 20233.135
B40: 闷顶建造面积（不计容） | C40: =总指标!P26-总指标!K14 -> 3710.9
B41: 闷顶钢筋及砼增量，含量按照标准层含量刻度的0.7倍折算 | D41: =C40*D38*0.7 -> 111698.09 | E41: =C40*E38*0.7 -> 1013.0757
B42: 按照面积折算后修正刻度 | D42: {=SUM(D39:D41/C38)} -> 45.153016 | E42: =SUM(E39:E41)/C38 -> 0.40952735
D44: =D42-D38 -> 2.1530155 | E44: =E42-E38 -> 0.01952735
D45: ='05 成本测算明细'!K644+'05 成本测算明细'!K645 -> 5.6022 | E45: ='05 成本测算明细'!K648+'05 成本测算明细'!K649 -> 481.594
D47: =D45*D41 -> 625755.04 | E47: =E45*E41 -> 487891.18
D49: ='05 成本测算明细'!M657*10000 -> 1956146.5

Sheet PC 增量测算
A1: 装配整体式剪力墙结构预制装配率计算统计表（住宅）
A2: 技术配置选项 | D2: 项目实施情况 | E2: 体积或者面积 | F2: 对应部分总体积或面积 | G2: 权重 | H2: 比值
A3: 主体结构和 外围护结构 预制构件 Z1 | B3: 预制外剪力墙板
B4: 预制夹心保温外墙板
B5: 预制双层叠合剪力墙板
B6: 预制内剪力墙板（含外墙） | D6: 采用 | E6: 184.54
B7: 预制梁
B8: 预制叠合板 | D8: 采用
B9: 预制楼梯板
B10: 预制阳台板
B11: 预制空调板
B12: PCF 混凝土外墙模板
B13: 混凝土外挂墙板
B14: 预制混凝土飘窗墙板
B15: 预制女儿墙
B16: 合计（X1/Y1） | E16: 合计 X1 | F16: 合计 Y1
A17: 装配式内外围护构件 Z2 | B17: 蒸压轻质加气混凝土外墙系统
B18: 轻钢龙骨石膏板隔墙
B19: 蒸压轻质加气混凝土墙板
B20: 钢筋陶粒混凝土轻质墙板
B21: 合计（X2/Y2） | E21: 合计 X2 | F21: 合计 Y2
A22: 内装建筑部品 Z3 | B22: 集成式厨房
B23: 集成式卫生间
B24: 装配式吊顶
B25: 楼地面干式铺装
B26: 装配式墙板（带饰面）
C27: 装配式栏杆
B28: 合计（X3/Y3） | E28: 合计 X3 | F28: 合计 Y3
A29: 创新加分项- S | B29: 标准化、 模块化、 集约化设 计 | C29: 标准化的居住户型单元和公共建筑基本功 能单元 | D29: 采用 | G29: 0.01 | H29: 不超过5%
C30: 标准化门窗 | D30: 采用 | G30: 0.005
C31: 设备管线与结构相分离 | G31: 0.005
B32: 绿色建筑 技术集成 应用 | C32: 绿色建筑二星 | D32: 采用 | G32: 0.005
C33: 绿色建筑三星 | G33: 0.01
B34: 被动式超低能耗技术集成应用 | G34: 0.005
B35: 隔震减震技术集成应用 | G35: 0.005
B36: 以 BIM 为核心的信息化技术集成 应用 | D36: 采用 | G36: 0.01
B37: 工业化施 工技术集 成应用 | C37: 工地预制围墙（道路 板） | D37: 采用 | G37: 0.005
C38: 封闭式板式木组件 | G38: 0.005
C39: 预制空间模块木组件 | G39: 0.005
A40: 预制装配率 =Z1+Z2+Z3+S
I41: 劳动路含量 | N41: 劳动路含量 | S41: 劳动路含量 | X41: 劳动路含量
A42: 项目 | B42: 业态 | C42: 楼栋编号 | D42: 地上楼栋面积 | E42: 预制装配式总体积 | F42: 新三板总体积 | G42: 预制装配率50%单方价差 | H42: 预制装配率约30%单方价差 | I42: PC叠合板板含阳台板工程量 | J42: PC板单价 | K42: 传统现浇板单价 | L42: PC板价单价差 | M42: PC板单方差 | N42: PC楼梯工程量 | O42: PC楼梯单价 | P42: 传统现浇楼梯单价 | Q42: PC楼梯单价差 | R42: PC楼梯单方差 | S42: ALC隔墙工程量 | T42: ALC隔墙单价 | U42: 原对应砌体墙单价 | V42: ALC内隔墙单价差 | W42: ALC内隔墙单方差 | X42: PC剪力墙工程量 | Y42: PC剪力墙单价 | Z42: 原剪力墙做法单价 | AA42: PC剪力墙单价差 | AB42: PC剪力墙单方差
A43: 劳动路项目 | B43: 小高层 | C43: 2#、6#、7#（150户型、小高） | D43: =5206*3 -> 15618 | E43: =F43+X43 -> 3875.8744 | F43: =G43+Y43 -> 3442.4844 | G43: =M43+R43+W43+AB43 -> 142.91589 | I43: 603.65 | J43: 3060 | K43: =M50 -> 1156.9712 | L43: =J43-K43 -> 1903.0288 | M43: =L43*I43/$D43 -> 73.553805 | N43: 0 | O43: 3100 | P43: =R50 -> 1187.5704 | Q43: =O43-P43 -> 1912.4296 | R43: =Q43*N43/$D43 -> 0 | S43: 1269.64 | T43: 1000 | U43: 830 | V43: =T43-U43 -> 170 | W43: =V43*S43/$D43 -> 13.819875 | X43: 433.39 | Y43: 3299.5685 | Z43: =0.24*580+Z51*AA51+Z52*AA52 -> 1298.0036 | AA43: =Y43-Z43 -> 2001.5649 | AB43: =AA43*X43/$D43 -> 55.542209
C44: 1#、3#（130小高） | D44: 7108 | E44: =F44+X44 -> 3299.5685 | F44: =G44+Y44 -> 3299.5685 | H44: =M44+R44+W44+AB44 -> 42.596698 | I44: 107.28 | J44: 3060 | K44: =M50 -> 1156.9712 | L44: =J44-K44 -> 1903.0288 | M44: =L44*I44/$D44 -> 28.722134 | N44: 0 | O44: 3100 | P44: =R50 -> 1187.5704 | Q44: =O44-P44 -> 1912.4296 | R44: =Q44*N44/$D44 -> 0 | S44: 580.12 | T44: 1000 | U44: 830 | V44: =T44-U44 -> 170 | W44: =V44*S44/$D44 -> 13.874564 | X44: 0 | Y44: 3299.5685 | Z44: =0.24*580+Z51*AA51+Z52*AA52 -> 1298.0036 | AA44: =Y44-Z44 -> 2001.5649 | AB44: =AA44*X44/$D44 -> 0
C45: 小计 | D45: =SUM(D43:D43) -> 15618 | E45: =SUM(E43:E43) -> 3875.8744 | F45: =SUM(F43:F43) -> 3442.4844 | G45: =G43 -> 142.91589 | H45: =H44 -> 42.596698
F46: 塔吊运输，开办费影响单方 | G46: 10
A48: 出让条件 | B48: 其中45%的面积做到预制装配率50%（即 45% 的楼栋按照预制装配率 50%），剩余面积按30%装配率（江苏省规不低于30%） | G48: =G45*0.4+H45*0.6+G46 -> 92.724374
A49: 本次测算 | B49: 考虑 1% 的容积率奖励（+500 的计容面积），预制装配面积做到 100%（即全部楼栋） | G49: =G45+G46 -> 152.91589 | H49: 链接至 03 表
I50: 现浇板含量参考 | K50: 含量 | L50: 单价 | M50: =SUM(M51:M53) -> 1156.9712 | N50: 现浇楼梯含量 | Q50: 单价 | R50: =SUM(R51:R53) -> 1187.5704 | S50: 砌体墙单价参考 | U50: 单价 | V50: 单价来源 | X50: 剪力墙含量参考 | AA50: 单价 | AB50: =SUM(AB51:AB53) -> 1298.0036
J51: 钢筋含量kg/m3 | K51: 80.33 | L51: 6.02 | M51: =K51*L51 -> 483.5866 | O51: 钢筋含量kg/m3 | P51: 72.52 | Q51: 6.02 | R51: =P51*Q51 -> 436.5704 | T51: 砌体墙 | U51: 830 | V51: 劳动路总包合同 | Y51: 钢筋含量kg/m3 | Z51: 86.18 | AA51: 6.02 | AB51: =Z51*AA51 -> 518.8036
J52: 模板含量m2/m3 | K52: =1/0.13 -> 7.6923077 | L52: 80 | M52: =K52*L52 -> 615.38462 | O52: 模板含量m2/m3 | P52: 8.3 | Q52: 80 | R52: =P52*Q52 -> 664 | T52: ALC 隔墙 | U52: 1000 | V52: 劳动路总包合同 | Y52: 模板含量m2/m3 | Z52: =2/(0.25*1*1) -> 8 | AA52: 80 | AB52: =Z52*AA52 -> 640
J53: 混凝土 | K53: 0.1 | L53: 580 | M53: =K53*L53 -> 58 | O53: 混凝土 | P53: 0.15 | Q53: 580 | R53: =P53*Q53 -> 87 | Y53: 混凝土 | Z53: 0.24 | AA53: 580 | AB53: =Z53*AA53 -> 139.2

Sheet 苏州园区配套参考
A1: 序号 | B1: 单位工程名称 | C1: 金额(元) | D1: 总面积 | E1: 单方 | F1: 本次测算考虑
A2: 自来水（垄断） | B2: 室外给水工程 | C2: 351553.35 | D2: 57541 | E2: =C2/D2 -> 6.1096149
B3: 立管给水工程 | C3: 657588.98 | D3: 57541 | E3: =C3/D3 -> 11.428181
B4: 地库给水工程 | C4: 1823201.9 | D4: 57541 | E4: =C4/D4 -> 31.685267
B5: 泵房工程 | C5: 1497515.8 | D5: 57541 | E5: =C5/D5 -> 26.025196
A6: 合计 | E6: =SUM(E2:E5) -> 75.248258 | F6: =E6 -> 75.248258
A7: 雨污水（垄断） | B7: 雨水工程 | C7: 1031804.5 | D7: 57541 | E7: =C7/D7 -> 17.931639
B8: 污水工程 | C8: 1087689.6 | D8: 57541 | E8: =C8/D8 -> 18.902862
A9: 合计 | E9: =SUM(E7:E8) -> 36.834501 | F9: =E9 -> 36.834501
A10: 电力配套（自采） | B10: 苏州园区DK20230010号地块居配工程(居配自建) | C10: 14587068 | D10: 57541 | E10: =C10/D10 -> 253.50738
B11: 苏州园区DK20230010地块（车坊）项目居配工程（外部工程） | C11: 可退费不考虑 | D11: 57541 | E11: /
B12: 苏州园区DK20230010地块项目供电高可靠性费用 | C12: 报建费 | D12: 57541 | E12: /
B13: 苏州园区DK20230010地块项目配电房除湿防凝露系统安装工程 | C13: 297000 | D13: 57541 | E13: =C13/D13 -> 5.161537
B14: 苏州园区DK20230010地块住宅项目供电监理合同（内部） | C14: 174900 | D14: 57541 | E14: =C14/D14 -> 3.0395718
B15: 苏州园区DK20230010地块住宅项目供电监理合同（外部） | C15: 25000 | D15: 57541 | E15: =C15/D15 -> 0.43447281
B16: 苏州园区DK20230010地块（车坊）项目电缆通道工程合同 | C16: 1793428.8 | D16: 57541 | E16: =C16/D16 -> 31.167842
B17: 苏州园区DK20230010地块（车坊）项目外线接入工程及内线配电工程委托设计合同 | C17: 185000 | D17: 57541 | E17: =C17/D17 -> 3.2150988
B18: 苏州园区DK20230010地块小区雨污水工程 | C18: 212386.37 | D18: 57541 | E18: =C18/D18 -> 3.6910441
B19: 苏州园区DK20230010地块（车坊）项目矿物绝缘电缆设备采购合同 | C19: 272366.36 | D19: 57541 | E19: =C19/D19 -> 4.7334311 | F19: 考虑自采我司大总包成本优势下浮
A20: 合计 | E20: =SUM(E10:E19) -> 304.95038 | F20: =E20*0.94 -> 286.65335

Sheet 桩基单价
A1: 序号 | B1: 说明 | C1: 特征值 | D1: 设计桩径 （㎜） | E1: 桩长（m） | F1: 空孔（m） | G1: 混凝土强度 | H1: 混凝土方量 （m³） | I1: Φ6钢筋重量（kg） | K1: Φ12钢筋重量（kg） | L1: Φ18钢筋重量（kg） | N1: 钢筋汇总重量（kg） | O1: 每米含量
I2: 加密区 | J2: 非加密区 | K2: 间距2m加强筋 | L2: 主筋 | M2: 主筋锚固
A3: 1 | B3: 塔楼 | D3: 600 | E3: 29 | F3: =3.7+3.7+1.5+1.2 -> 10.1 | G3: C35 | H3: =E3*3.14*0.3*0.3 -> 8.1954 | I3: =(3/0.1+2)*SQRT(0.1*0.1+3.14*(0.6-2*0.05)*3.14*(0.6-2*0.05))*0.26 -> 13.08887 | J3: =((E3-3)/0.2+1)*SQRT(0.3*0.3+3.14*(D3/1000-2*0.05)*3.14*(D3/1000-2*0.05))*0.26 -> 54.44169 | K3: =(ROUND(E3/2,0)+1)*(D3/1000-2*0.05)*3.14*0.888 -> 22.30656 | L3: =8*(20+0.8)*2+4*9*2 -> 404.8 | N3: =I3+J3+K3+L3+M3 -> 494.63712 | O3: =N3/E3 -> 17.056452
A4: 2 | B4: 地库抗压 | D4: 600 | E4: 15 | F4: =3.7+3.7+1.5+1.2 -> 10.1 | G4: C35 | H4: =E4*3.14*0.3*0.3 -> 4.239 | I4: =(3/0.1+2)*SQRT(0.1*0.1+3.14*(0.6-2*0.05)*3.14*(0.6-2*0.05))*0.26 -> 13.08887 | J4: =((E4-3)/0.2+1)*SQRT(0.3*0.3+3.14*(D4/1000-2*0.05)*3.14*(D4/1000-2*0.05))*0.26 -> 25.350711 | K4: =(ROUND(E4/2,0)+1)*(0.6-2*0.05)*3.14*0.888 -> 12.54744 | L4: =12*(15+0.8)*2 -> 379.2 | N4: =I4+J4+K4+L4+M4 -> 430.18702 | O4: =N4/E4 -> 28.679135
A5: 3
A7: 桩基工程主要单价分析表
A8: 序号 | B8: 单位 | C8: 单位 | D8: 本工程
D9: 每米工程量（A1） | F9: 单价 | G9: 延米单价 (元/m)A2 | H9: 立方米单价（元/m3)A3
A10: 塔楼，600mm旋挖灌注桩（有效桩长≥38m）
A11: 序号 | B11: 单位 | C11: 单位 | D11: 本工程
D12: 每米工程量 | E12: 每立方米工程量 | F12: 单价 | G12: 延米单价 (元/m)A2 | H12: 每立方米单价（元/m3）A | I12: 截面积
A13: 1 | B13: 成孔 | C13: m/m | D13: =(E3+F3)/E3 -> 1.3482759 | E13: =D13/I13 -> 4.7709691 | F13: 125 | G13: =D13*F13 -> 168.53448 | H13: =G13/I13 -> 596.37114 | I13: =3.14*0.3*0.3 -> 0.2826
A14: 2 | B14: 土方 | C14: m3/m | D14: =3.14*0.3*0.3*D13 -> 0.38102276 | E14: =D14/I14 -> 1.3482759 | F14: 130 | G14: =D14*F14 -> 49.532959 | H14: =G14/I14 -> 175.27586 | I14: =3.14*0.3*0.3 -> 0.2826
A15: 3 | B15: 钢筋 | C15: kg/m | D15: =O3 -> 17.056452 | E15: =D15/I15 -> 60.355458 | F15: 3.5 | G15: =D15*F15 -> 59.697583 | H15: =G15/I15 -> 211.2441 | I15: =3.14*0.3*0.3 -> 0.2826
A16: 4 | B16: 砼(C35) | C16: m3/m | D16: =3.14*0.3*0.3 -> 0.2826 | E16: =D16/I16 -> 1 | F16: 400 | G16: =D16*F16 -> 113.04 | H16: =G16/I16 -> 400 | I16: =3.14*0.3*0.3 -> 0.2826
A17: 5 | B17: 后注浆 | C17: t/m | D17: =3/29 -> 0.10344828 | E17: =D17/I17 -> 0.36605901 | F17: 500 | G17: =D17*F17 -> 51.724138 | H17: =G17/I17 -> 183.0295 | I17: =3.14*0.3*0.3 -> 0.2826
A18: 6 | B18: 注浆管 | C18: m/m | D18: =2*1.47 -> 2.94 | E18: =D18/I18 -> 10.403397 | F18: 9.45 | G18: =D18*F18 -> 27.783 | H18: =G18/I18 -> 98.312102 | I18: =3.14*0.3*0.3 -> 0.2826
A19: 7 | B19: 声测管 | C19: m/m | D19: =3*D13*0.1 -> 0.40448276 | E19: =D19/I19 -> 1.4312907 | F19: 9.76 | G19: =D19*F19 -> 3.9477517 | H19: =G19/I19 -> 13.969397 | I19: =3.14*0.3*0.3 -> 0.2826
A20: 8 | B20: 钻芯导管 | C20: m/m | D20: =1/35 -> 0.028571429 | E20: =D20/I20 -> 0.10110201 | F20: 61.22 | G20: =D20*F20 -> 1.7491429 | H20: =G20/I20 -> 6.1894652 | I20: =3.14*0.3*0.3 -> 0.2826
A21: 9 | B21: 截桩 | C21: 根/m | D21: =1/35 -> 0.028571429 | E21: =D21/I21 -> 0.10110201 | F21: 200 | G21: =D21*F21 -> 5.7142857 | H21: =G21/I21 -> 20.220402 | I21: =3.14*0.3*0.3 -> 0.2826
A22: 10 | B22: 开办费 | C22: 元/m
B23: 合计 | G23: =SUM(G13:G22) -> 481.72334
A26: 地下室，600mm旋挖灌注桩（抗拔、有效桩长≥15m）
A27: 序号 | B27: 单位 | C27: 单位 | D27: 本工程
D28: 每米工程量 | E28: 每立方米工程量 | F28: 单价 | G28: 延米单价 (元/m)A2 | H28: 每立方米单价（元/m3）A | I28: 截面积
A29: 1 | B29: 成孔 | C29: m/m3 | D29: =(E4+F4)/E4 -> 1.6733333 | E29: =D29/I29 -> 5.9212078 | F29: 125 | G29: =D29*F29 -> 209.16667 | H29: =G29/I29 -> 740.15098 | I29: =3.14*0.3*0.3 -> 0.2826
A30: 2 | B30: 土方 | C30: m3/m3 | D30: =3.14*0.3*0.3*D29 -> 0.472884 | E30: =D30/I30 -> 1.6733333 | F30: 130 | G30: =D30*F30 -> 61.47492 | H30: =G30/I30 -> 217.53333 | I30: =3.14*0.3*0.3 -> 0.2826
A31: 3 | B31: 钢筋 | C31: kg/m3 | D31: =O4 -> 28.679135 | E31: =D31/I31 -> 101.48314 | F31: 3.5 | G31: =D31*F31 -> 100.37697 | H31: =G31/I31 -> 355.19098 | I31: =3.14*0.3*0.3 -> 0.2826
A32: 4 | B32: 砼(C30) | C32: m3/m3 | D32: =3.14*0.3*0.3 -> 0.2826 | E32: =D32/I32 -> 1 | F32: 400 | G32: =D32*F32 -> 113.04 | H32: =G32/I32 -> 400 | I32: =3.14*0.3*0.3 -> 0.2826
A33: 5 | B33: 后注浆 (2T) | C33: t/m3 | D33: =2/15 -> 0.13333333 | E33: =D33/I33 -> 0.47180939 | F33: 500 | G33: =D33*F33 -> 66.666667 | H33: =G33/I33 -> 235.90469 | I33: =3.14*0.3*0.3 -> 0.2826
A34: 6 | B34: 侧注浆 (1T) | C34: t/m3 | E34: =D34/I34 -> 0 | G34: =D34*F34 -> 0 | H34: =G34/I34 -> 0 | I34: =3.14*0.3*0.3 -> 0.2826
A35: 7 | B35: 注浆管 | C35: m/m3 | D35: =2*D29 -> 3.3466667 | E35: =D35/I35 -> 11.842416 | F35: 9.45 | G35: =D35*F35 -> 31.626 | H35: =G35/I35 -> 111.91083 | I35: =3.14*0.3*0.3 -> 0.2826
A36: 8 | B36: 声测管 | C36: m/m | D36: =3*D29*0.1 -> 0.502 | E36: =D36/I36 -> 1.7763623 | F36: 9.76 | G36: =D36*F36 -> 4.89952 | H36: =G36/I36 -> 17.337297 | I36: =3.14*0.3*0.3 -> 0.2826
A37: 9 | B37: 钻芯导管 | C37: m/m3 | D37: =1/17 -> 0.058823529 | E37: =D37/I37 -> 0.2081512 | F37: 61.22 | G37: =D37*F37 -> 3.6011765 | H37: =G37/I37 -> 12.743017 | I37: =3.14*0.3*0.3 -> 0.2826
A38: 10 | B38: 截桩 | C38: 根/m3 | D38: =1/17 -> 0.058823529 | E38: =D38/I38 -> 0.2081512 | F38: 200 | G38: =D38*F38 -> 11.764706 | H38: =G38/I38 -> 41.63024 | I38: =3.14*0.3*0.3 -> 0.2826
A39: 11 | B39: 开办费 | C39: 元/m
B40: 合计 | G40: =SUM(G29:G39) -> 602.61663

Sheet 桩基
A1: 05表测算附表 桩基工程
A2: 桩基工程 | B2: 桩型 | C2: 部位 | D2: 基底面积 （m2) | E2: 桩基含量 | F2: 桩数（根） | G2: 单桩桩长 （m） | H2: 综合单价 （元/m） | I2: 控制值 （万元） | J2: 建筑面积（m2） | K2: 相对建筑面积单位成本（元/m2） | L2: 备注
B3: 10F小高140（4栋）,160（3栋），户型（北侧一排） | C3: YZ600-29-3，20/8根18,9/4根18-35 | F3: =I35 -> 401 | G3: =H35 -> 29 | H3: =桩基单价!G23 -> 481.72334 | I3: =F3*G3*H3/10000 -> 560.19608 | J3: ='02 项目基础信息（输入）'!C69 -> 74626.755
B4: 10F小高140（4栋）,160（4栋）户型 （南侧一排） | C4: PHC-500(110)AB-C60-14,14 | F4: =I36 -> 440 | G4: =H36 -> 28 | H4: 220 | I4: =F4*G4*H4/10000 -> 271.04 | J4: =J3 -> 74626.755
B5: 地下车库（室外覆土1.2m，带售楼处） | C5: BZ600-29-3，29/12根18-35 | F5: =I37 -> 438 | G5: =H37 -> 15 | H5: =桩基单价!G40 -> 602.61663 | I5: =F5*G5*H5/10000 -> 395.91912 | J5: =J3 -> 74626.755
B6: 地下车库（室外覆土1.2m，带售楼处） | C6: YZH-400B-15G-C60 | F6: =I38 -> 308 | G6: =H38 -> 15 | H6: 253 | I6: =F6*G6*H6/10000 -> 116.886 | J6: =J4 -> 74626.755
B7: 开办费 | C7: 百分比 | H7: 0.07 | I7: =SUM(I3:I6)*H7 -> 94.082884 | J7: =J3 -> 74626.755
C8: 小计 | F8: =SUM(F3:F7) -> 1587 | G8: 12 | H8: =I8/G8/F8*10000 -> 755.15862 | I8: =SUM(I3:I7) -> 1438.1241 | J8: =J7 -> 74626.755 | K8: =I8/J8*10000 -> 192.70891 | L8: 模拟总桩长 | M8: =I8/H8*10000 -> 19044
B9: 试桩 | C9: =C3 -> YZ600-29-3，20/8根18,9/4根18-35 | F9: 10 | G9: =G3 -> 29 | H9: =H3*1.2 -> 578.06801 | I9: =F9*G9*H9/10000 -> 16.763972 | J9: =J3 -> 74626.755 | L9: 一栋楼1根，每个桩型至少3根；地库至少3根
B10: 试桩 | C10: =C4 -> PHC-500(110)AB-C60-14,14 | F10: 7 | G10: =G4 -> 28 | H10: =H4*1.2 -> 264 | I10: =F10*G10*H10/10000 -> 5.1744 | J10: =J4 -> 74626.755
B11: 试桩 | C11: =C5 -> BZ600-29-3，29/12根18-35 | F11: 5 | G11: =G5 -> 15 | H11: =H5*1.2 -> 723.13995 | I11: =F11*G11*H11/10000 -> 5.4235496 | J11: =J5 -> 74626.755
B12: 试桩 | C12: =C6 -> YZH-400B-15G-C60 | F12: 3 | G12: =G6 -> 15 | H12: =H6*1.2 -> 303.6 | I12: =F12*G12*H12/10000 -> 1.3662 | J12: =J4 -> 74626.755
B13: 试桩开办费 | C13: 机械进退场 | F13: 1 | G13: 1 | H13: 100000 | I13: =F13*G13*H13/10000 -> 10 | J13: =J9 -> 74626.755
C14: 小计 | F14: =SUM(F9:F13) -> 26 | I14: =SUM(I9:I13) -> 38.728122 | J14: =J13 -> 74626.755 | K14: =I14/J14*10000 -> 5.1895761 | L14: 模拟总桩长
B15: 费用小计 | F15: =F8+F14 -> 1613 | G15: 12 | H15: =I15*10000/(F15*G15) -> 762.99453 | I15: =I14+I8 -> 1476.8522 | J15: =J14 -> 74626.755 | K15: =I15/J15*10000 -> 197.89849 | L15: 模拟总桩长 | M15: =I15/H15*10000 -> 19356 | O15: 指标输出至05表
A16: 桩基检测 | B16: 检测类型 | C16: 检测基数 | D16: 检测比例 | E16: 承载力极限值 （KN) | F16: 检测工程量 | G16: 单桩桩长 （m） | H16: 综合单价 （元） | I16: 控制值 （万元） | J16: 相对建筑面积（m2） | K16: 相对建筑面积单位成本 （元/m2） | L16: 备注
A17: 桩基检测 | B17: 静载-塔楼 | C17: 15 | D17: 3 | E17: 940 | F17: =C17*D17 -> 45 | H17: 16.7 | I17: =F17*E17*H17/10000 -> 70.641 | L17: 按每栋楼3根、不足 50 根的按照 2 根检测
B18: 静载-地库（抗压） | C18: =F4+F6 -> 748 | D18: 0.01 | E18: 940 | F18: =ROUND(C18*D18,0) -> 7 | H18: 16.7 | I18: =F18*E18*H18/10000 -> 10.9886 | L18: 地库桩基的1%
B19: 静载-地库（抗拔） | C19: =C18 -> 748 | D19: 0.01 | E19: 250 | F19: =ROUND(C19*D19,0) -> 7 | H19: 16.7 | I19: =F19*E19*H19/10000 -> 2.9225 | L19: 地库桩基的1%
B20: 声波 | D20: 1 | F20: =C20*D20 -> 0 | I20: =F20*H20/10000 -> 0 | L20: 全检
B21: 小应变 | C21: =F8+F14 -> 1613 | D21: 1 | F21: =C21*D21 -> 1613 | H21: 5 | I21: =F21*H21/10000 -> 0.8065 | L21: 全检
B22: 大应变 | C22: =C21 -> 1613 | D22: 0.1 | F22: =C22*D22 -> 161.3 | H22: 400 | I22: =F22*H22/10000 -> 6.452 | L22: 1/10，且不少于十根
B23: 钻芯-塔楼 | D23: 3 | F23: =C23*D23 -> 0 | L23: 按每栋楼3根、仅灌注桩
B24: 钻芯-地库 | D24: 0.02 | F24: =C24*D24 -> 0 | L24: 地库桩基的2%、仅灌注桩
B25: 试桩静载检测 | C25: =F9 -> 10 | D25: 1 | E25: 940 | F25: =C25*D25 -> 10 | H25: 16.7 | I25: =F25*E25*H25/10000 -> 15.698 | L25: 检测吨位数按照破坏上浮 20%
B26: 试桩静载检测 | C26: 3 | D26: 1 | E26: =E19*1.2 -> 300 | F26: =C26*D26 -> 3 | H26: 16.7 | I26: =F26*E26*H26/10000 -> 1.503 | L26: 检测吨位数按照破坏上浮 20%
B27: 其他 | C27: 1 | D27: 1 | F27: =C27*D27 -> 1 | H27: 25000 | I27: =F27*H27/10000 -> 2.5 | L27: 土壤氡检测及进出场费
B28: 费用小计 | I28: =SUM(I17:I27) -> 111.5116 | J28: =J3 -> 74626.755 | K28: =I28/J28*10000 -> 14.942577 | O28: 指标输出至05表
A29: 沉降观测 | H29: 1 | I29: 控制值 （万元） | J29: 相对建筑面积（m2） | K29: 相对建筑面积单位成本 （元/m2）
A30: 沉降观测 | H30: 1.5 | I30: =H30*J30/10000 -> 11.194013 | J30: =J8 -> 74626.755 | K30: =I30/J30*10000 -> 1.5 | L30: 参考以往项目单方计算 | O30: 指标输出至05表
A31: 总计 | I31: =I15+I28+I30 -> 1599.5578 | J31: =J30 -> 74626.755 | K31: =I31/J31*10000 -> 214.34107
A34: 单体 | B34: 桩型 | C34: 桩图集 | D34: 桩型 | E34: 砼等级 | F34: 预估抗压承载力特征值（KN） | G34: 预估抗拔承载力特征值（KN） | H34: 预估长度（m） | I34: 预估桩数量（根） | J34: 备注
